Workbook
Name Assessment: #REF!
Name Domain: #REF!
Name Health_Promotion: #REF!
Name Planning_and_Management: #REF!
Name Professional_Responsibilities: #REF!
Name Stage: 'Internal - tracking items'!$A$2:$A$10
Name System: #REF!
Name Workflow: 'Internal - tracking items'!$G$2:$G$6

Sheet Plan by domain (not used)
A2: Domain | B2: Subdomain | D2: Recall Items (Planned) | E2: Application Items (Planned) | F2: Analysis Items (Planned) | G2: Total (Planned) | H2: Submitted (from Items tab) | I2: Assigned total (See Writer entries to the right) | J2: Writer1 | K2: Writer2 | L2: Writer3 | M2: Writer4 | N2: Uncommitted | O2: Deviation from plan
D3: =SUM(D4:D39) -> 0 | E3: =SUM(E4:E39) -> 0 | F3: =SUM(F4:F39) -> 0 | G3: =SUM(D3:F3) -> 0 | H3: =SUM(H4:H39) -> #REF! | I3: =SUM(I4:I39) -> 0 | J3: =SUM(J4:J39) -> 0 | K3: =SUM(K4:K39) -> 0 | L3: =SUM(L4:L39) -> 0 | M3: =SUM(M4:M39) -> 0 | N3: =SUM(N4:N39) -> 0
A4: Domain1 | B4: Subdomain1_1 | G4: =SUM(D4:F4) -> 0 | H4: =#REF! -> #REF! | I4: =SUM(J4:M4) -> 0 | N4: =G4-I4 -> 0 | O4: =H4-G4 -> #REF!
A5: Domain1 | B5: Subdomain2_1 | G5: =SUM(D5:F5) -> 0 | H5: =#REF! -> #REF! | I5: =SUM(J5:M5) -> 0 | O5: =H5-G5 -> #REF!
A6: Domain1 | B6: Subdomain3_1 | G6: =SUM(D6:F6) -> 0 | H6: =#REF! -> #REF! | I6: =SUM(J6:M6) -> 0 | O6: =H6-G6 -> #REF!
A7: Domain1 | B7: Subdomain4_1 | G7: =SUM(D7:F7) -> 0 | H7: =#REF! -> #REF! | I7: =SUM(J7:M7) -> 0 | O7: =H7-G7 -> #REF!
A8: Domain1 | B8: Subdomain5_1 | G8: =SUM(D8:F8) -> 0 | H8: =#REF! -> #REF! | I8: =SUM(J8:M8) -> 0 | O8: =H8-G8 -> #REF!
A9: Domain1 | B9: Subdomain6_1 | G9: =SUM(D9:F9) -> 0 | H9: =#REF! -> #REF! | I9: =SUM(J9:M9) -> 0 | O9: =H9-G9 -> #REF!
A10: Domain2 | B10: Subdomain1_2 | G10: =SUM(D10:F10) -> 0 | H10: =#REF! -> #REF! | I10: =SUM(J10:M10) -> 0 | O10: =H10-G10 -> #REF!
A11: Domain2 | B11: Subdomain2_2 | G11: =SUM(D11:F11) -> 0 | H11: =#REF! -> #REF! | I11: =SUM(J11:M11) -> 0 | O11: =H11-G11 -> #REF!
A12: Domain2 | B12: Subdomain3_2 | G12: =SUM(D12:F12) -> 0 | H12: =#REF! -> #REF! | I12: =SUM(J12:M12) -> 0 | O12: =H12-G12 -> #REF!
A13: Domain2 | B13: Subdomain4_2 | G13: =SUM(D13:F13) -> 0 | H13: =#REF! -> #REF! | I13: =SUM(J13:M13) -> 0 | O13: =H13-G13 -> #REF!
A14: Domain2 | B14: Subdomain5_2 | G14: =SUM(D14:F14) -> 0 | H14: =#REF! -> #REF! | I14: =SUM(J14:M14) -> 0 | O14: =H14-G14 -> #REF!
A15: Domain2 | B15: Subdomain6_2 | G15: =SUM(D15:F15) -> 0 | H15: =#REF! -> #REF! | I15: =SUM(J15:M15) -> 0 | O15: =H15-G15 -> #REF!
A16: Domain3 | B16: Subdomain1_3 | G16: =SUM(D16:F16) -> 0 | H16: =#REF! -> #REF! | I16: =SUM(J16:M16) -> 0 | O16: =H16-G16 -> #REF!
... A39: Domain6 | B39: Subdomain6_6 | G39: =SUM(D39:F39) -> 0 | H39: =#REF! -> #REF! | I39: =SUM(J39:M39) -> 0 | O39: =H39-G39 -> #REF!

Sheet SPC-CPN_Q&A
A1: Unique ID Number | B1: Chapter Number | C1: Item Number in Chapter | D1: Item Type (Practice Question or Test Question?) | E1: Stem | F1: A | G1: B | H1: C | I1: D | J1: Correct Answer | K1: Correct Option | L1: Rationale | M1: CPN Domain | N1: SPC Topic | O1: Cognitive Level
A2: 1 | B2: 1 | C2: 1 | D2: Practice | E2: What is the STRONGEST outcome predictor for submersion injuries? | F2: Submersion duration | G2: Temperature of the water | H2: Type of water | I2: Length of resuscitation | J2: Submersion duration | K2: A | L2: The strongest outcome predictor for submersion injuries is submersion duration. Durations of fewer than 5 minutes are associated with more favorable outcomes. The worst outcomes occur when submersion duration is longer than 25 minutes. Submersion in colder, fresh water is correlated with better outcomes, but these factors are not the strongest predictors of outcome. Length of resuscitation is not a predictor of outcome in submersion injuries. | M2: Health_Promotion | O2: Recall
A3: 2 | B3: 4 | C3: 1 | D3: Practice | E3: A child from a divorced family discloses that they have not gone to school in 4 weeks because their father does not take them. The nurse's BEST action is to: | F3: Advise the child to suggest home schooling to the father | G3: Notify a case manager so transportation to school can be arranged | H3: Notify child protective services | I3: Inform the child's mother about the situation | J3: Notify child protective services | K3: C | L3: The child needs to be provided with basic education, and failing to do so is a form of neglect. The nurse should alert child protective services to investigate the child’s home life. Child protective services may assign a case manager, who will ensure that the father has the means to take the child to school or will provide guidance and direction if home schooling is an option for the father. In addition, child protective services would be responsible for notifying the child's mother about the situation. | M3: Professional_Responsibilities | N3: Neglect | O3: Application
A4: 4 | B4: 2 | C4: 1 | D4: Practice | E4: Which of the following should be heard when auscultating the chest of a patient with a Norwood repair? | F4: Shunt murmur | G4: No murmur | H4: Shunt clicks | I4: No clicks | J4: Shunt murmur | K4: A | L4: During a Norwood repair, a round tube or shunt routes blood either from the aorta or directly from the right ventricle to the pulmonary artery. Blood flowing through this repair will result in a murmur in the left upper chest, not a click, which is usually associated with valves. A murmur indicates that the shunt is patent. No murmur indicates that the Norwood repair is not functioning. | M4: Assessment | O4: Recall
A5: 5 | B5: 2 | C5: 2 | D5: Practice | E5: Which of the following is the MOST appropriate technique for assessing the tympanic membrane in a 3-year-old patient? | F5: Pull the pinnae of the ear upward and forward | G5: Pull the pinnae of the ear upward and backward | H5: Pull the pinnae of the ear downward and forward | I5: Pull the pinnae of the ear downward and backward | J5: Pull the pinnae of the ear upward and backward | K5: B | L5: Ear canals of patients who are 3 years or older curve downward and forward, and the drum slopes inward and forward. To visualize the tympanic membrane via an otoscope, the pinnae of the ear must be pulled upward and backward. Ear canals of infants curve upward, and the tympanic membrane is horizontal along the upper wall of the canal. Therefore, the pinnae of the ear must be pulled downward and backward to visualize the tympanic membrane. Pulling the pinnae upward and forward or downward and forward will not help visualize the membrane. | M5: Assessment | O5: Application
A6: 6 | B6: 2 | C6: 3 | D6: Practice | E6: The nurse is stroking the corner of a 2-month-old patient’s mouth. Which reflex is the nurse trying to elicit? | F6: Moro | G6: Sucking | H6: Rooting | I6: Tonic neck | J6: Rooting | K6: C | L6: Stroking the corner of the mouth will elicit the rooting reflex. The infant will move their head toward stimulation if the reflex is present. The sucking reflex is elicited by touching the infant’s lips with a finger. The Moro reflex is eliciting by making a loud noise or bracing the patient’s head and back while simulating falling. The infant will extend and flex the arms and fingers. To elicit the tonic neck reflex, the infant's head is turned to one side, and the upper and lower extremities on that side will extend while the opposite extremities flex. | M6: Assessment | O6: Recall
A7: 7 | B7: 2 | C7: 4 | D7: Practice | E7: What structure is being assessed when the nurse pushes the tip of the patient's nose upward and asks them to tilt their head back? | F7: Pinna | G7: Choroid | H7: Frenulum | I7: Anterior vestibule | J7: Anterior vestibule | K7: D | L7: The nurse can inspect the anterior vestibule of the nose by pushing the tip upward, tilting the head backward, and shining a light into the cavity. The tongue is attached to the floor of the mouth by a fold called the frenulum. The pinna, or auricle, is the exterior part of the ear. The choroid is a tissue layer that lies between the retina and the sclera. | M7: Assessment | O7: Recall
A8: 8 | B8: 2 | C8: 5 | D8: Practice | E8: A parent presents to the clinic with their infant son, who has trisomy 21 and poor oral intake. The nurse asks the parent how they feed the child. The parent responds, “I give him the bottle, but he hardly holds it, and the milk just goes everywhere.” The nurse's BEST next action is to: | F8: Perform a feeding task analysis | G8: Conduct a swallow study | H8: Place a nasogastric tube | I8: Ask the provider to evaluate the child for placement of a gastric tube | J8: Perform a feeding task analysis | K8: A | L8: The nurse should perform a feeding task analysis, which will help to identify which element of feeding is causing the most issues. Children with trisomy 21 (Down syndrome) may struggle with eating due to laxity in muscles, floppy head, and tongue protrusion that pushes food out. It is not appropriate to immediately place a nasogastric tube prior to assessing the child and his ability to feed orally. Once the study is complete, the nurse can ask the provider to evaluate the child for placement of a gastric tube. A swallow study can also be conducted after a feeding task analysis to ensure the child is not aspirating food. | M8: Assessment | O8: Analysis
A9: 9 | B9: 2 | C9: 6 | D9: Practice | E9: The nurse is assessing a male child who has a long face with a prominent jaw and large ears. The child is rocking back and forth during the assessment. The nurse recognizes these characteristics as features of: | F9: Down syndrome | G9: Fragile X syndrome | H9: Turner syndrome | I9: Trisomy 18 | J9: Fragile X syndrome | K9: B | L9: Classic characteristics of fragile X syndrome include a long face; prominent jaw; large, protruding ears; and autism-like behaviors such as rocking or fidgeting. Down syndrome presents with a flattened nasal bridge, almond-shaped eyes, short neck, and small ears. Only female patients are affected by Turner syndrome. They present with a web-like neck, a broad chest, and a high/narrow roof of the mouth. Children with trisomy 18 have small, abnormally shaped heads; small jaws; and clenched fists with overlapping fingers. | M9: Assessment | O9: Application
A10: 10 | B10: 5 | C10: 1 | D10: Test | E10: The nurse is assessing a 6-month-old patient who was brought to the ED with a low-grade fever, poor feeding, and restlessness. The infant has increased respiratory secretions, and the parents are concerned that the infant is having trouble breathing. Which monitoring intervention will the nurse PRIORITIZE until the patient is transferred to the pediatric ICU? | F10: Pediatric Glasgow Coma Scale | G10: Intake and output | H10: Cardiac rate and rhythm | I10: Frequent vital signs | J10: Pediatric Glasgow Coma Scale | K10: A | L10: The nurse will prioritize monitoring the infant’s level of consciousness using the pediatric Glasgow Coma Scale. If the patient becomes increasingly lethargic and less responsive, the nurse will take further action to assess the patient’s respiratory status and address any need for additional intervention. The nurse will also continue to assess the patient’s hemodynamic status by evaluating intake and output, monitoring cardiac rate and rhythm, and collecting frequent vital signs. | M10: Assessment | O10: Application
A11: 11 | B11: 2 | C11: 7 | D11: Practice | E11: While assessing a neonate, the nurse notes small, yellow-white, epithelial cysts along the roof of the infant’s mouth. The nurse recognizes these cysts as: | F11: Abscesses | G11: Epstein pearls | H11: Herpes simplex | I11: Koplik spots | J11: Epstein pearls | K11: B | L11: Epstein pearls are whitish-yellow cysts that form on the gums and roof of the mouth in newborns. The cysts contain keratin, a protein that occurs naturally in human skin, hair, and nails. Epstein pearls are a normal finding and resolve within a few weeks of birth. Abscesses form from infected wounds and contain a mixture of white blood cells and pus. Herpes simplex type 1 is a viral infection that presents with external sores and blisters on the mouth. Koplik spots, tiny white spots in the mouth, are a prodromal manifestation of the measles infection. | M11: Assessment | O11: Recall
A12: 13 | B12: 2 | C12: 8 | D12: Practice | E12: Which of the following are common clinical manifestations of HIV infection in children? | F12: Recurrent diarrhea, failure to thrive, developmental delay, and petechiae | G12: Oral candidiasis, recurrent diarrhea, petechiae, and epistaxis | H12: Failure to thrive, developmental delay, petechiae, and epistaxis | I12: Oral candidiasis, chronic diarrhea, failure to thrive, and developmental delay | J12: Oral candidiasis, chronic diarrhea, failure to thrive, and developmental delay | K12: D | L12: Common clinical manifestations of HIV are lymphadenopathy, hepatosplenomegaly, oral candidiasis, chronic or recurrent diarrhea, failure to thrive, developmental delay, and parotitis. Petechiae and epistaxis are common clinical manifestations of immune thrombocytopenia. | M12: Assessment | O12: Recall
A13: 14 | B13: 2 | C13: 9 | D13: Practice | E13: An infant admitted for shaken baby syndrome has poor capillary refill, tachypnea, and falling blood pressure. The nurse should recognize the patient is MOST likely experiencing which type of shock? | F13: Hypovolemic | G13: Distributive | H13: Cardiogenic | I13: Irreversible | J13: Hypovolemic | K13: A | L13: Shaken baby syndrome can cause bleeding into the brain, resulting in hypovolemic shock. Distributive shock occurs when there is an abnormal distribution of blood flow in the smallest blood vessels, resulting in inadequate supply of blood to the body’s tissues and organs. Cardiogenic shock is a medical emergency caused by inadequate blood flow due to the dysfunction of the ventricles of the heart. Injuries to the chest, abdomen, or pelvis, where hemorrhage can be difficult to detect and control, usually cause irreversible shock, which is often a fatal condition. | M13: Assessment | O13: Application
A14: 15 | B14: 2 | C14: 10 | D14: Practice | E14: Which of the following conditions are associated with a risk for a latex allergy? | F14: Imperforate anus, spina bifida, and prematurity | G14: Imperforate anus, prematurity, and Meckel diverticulum | H14: Imperforate anus, spina bifida, and Meckel diverticulum | I14: Spinal bifida, prematurity, and Meckel diverticulum | J14: Imperforate anus, spina bifida, and prematurity | K14: A | L14: Medical conditions associated with risk for latex allergy are spina bifida, urogenital anomalies, imperforate anus, tracheoesophageal fistula, VATER association (a group of birth defects that present together), prematurity, ventriculoperitoneal shunt, congenital impairment, cerebral palsy, spinal cord injuries, multiple surgeries, and atopy. Meckel diverticulum is a remnant of the fetal omphalomesenteric duct, which connects the yolk sac with the primitive midgut during fetal life. It is not associated with latex allergy. | M14: Assessment | O14: Recall
A15: 16 | B15: 2 | C15: 11 | D15: Practice | E15: Which of the following are common clinical manifestations of a cow’s milk allergy? | F15: Sneezing, pallor, fussiness, and bradycardia | G15: Atopic dermatitis, pallor, fussiness, and dysrhythmia | H15: Sneezing, atopic dermatitis, pallor, and fussiness | I15: Atopic dermatitis, fussiness, bradycardia, and sneezing | J15: Sneezing, atopic dermatitis, pallor, and fussiness | K15: C | L15: Cow’s milk allergy commonly manifests as sneezing, atopic dermatitis, pallor, and fussiness. While bradycardia and dysrhythmia are common indications of a severe allergy attack, they are not commonly found with a cow’s milk allergy. | M15: Assessment | O15: Recall
... A107: 115 | B107: 3 | C107: 23 | D107: Practice | E107: A child is undergoing suture repair of a laceration to the lower leg. The nurse instructs the patient that the sutures will be removed in how many days? | F107: 3 to 5 | G107: 5 to 7 | H107: 7 to 10 | I107: 10 to 14 | J107: 10 to 14 | K107: D | L107: Sutures to the lower legs and feet should be removed in 10 to 14 days. Most sutures in the face are removed in 3 to 5 days, but some face sutures, as well as scalp sutures, are removed in 5 to 7 days. Sutures on the torso are removed in 7 to 10 days. | M107: Planning_and_Management | O107: Recall
A108: 116 | B108: 4 | C108: 2 | D108: Practice | E108: The nurse is teaching the parents of a child with terminal cancer the differences between hospice care and palliative care. Which of the following statements by the nurse is MOST accurate? | F108: "Both hospice care and palliative care are provided for terminally ill patients only." | G108: "Palliative care can be provided to patients with a life expectancy of 12 months or less." | H108: "Unlike hospice care, palliative care is provided in the home setting only." | I108: "Life-prolonging medications can be used in palliative care but not in hospice care." | J108: "Life-prolonging medications can be used in palliative care but not in hospice care." | K108: D | L108: A key difference between hospice care and palliative care is the type of care that is provided. In palliative care, life-prolonging medications and equipment can be used, whereas in hospice care, curative and life-prolonging treatments cannot be provided. Another key difference is that palliative care is available to patients in all disease stages; life expectancy is not a factor. Hospice admission criteria require that the patient have a life expectancy of 6 months or less. Both hospice care and palliative care can take place in a variety of settings, although the majority of hospice care programs are home based. | M108: Professional_Responsibilities | N108: End of life | O108: Recall
A109: 117 | B109: 3 | C109: 24 | D109: Practice | E109: The nurse is teaching the parent of a child who is receiving palliative care about measuring oral medication using a dropper. The parent speaks English as a second language and has low proficiency. What is the BEST way to ensure that the instructions are understood? | F109: Provide hands-on learning with a dropper using water to practice | G109: Ask the parent to teach-back the skill being taught | H109: Provide written instructions after verbal instructions | I109: Arrange for a nurse’s aide to administer the medication | J109: Ask the parent to teach-back the skill being taught | K109: B | L109: To provide proper care for a child who is receiving palliative care, the family must be well-informed regarding the illness, disease progression, medication use, and use of equipment. The nurse must identify barriers to family education, such as low English proficiency, low literacy, low confidence, family dynamics, and cultural beliefs regarding care during illness. The best way to ensure that the instructions are understood and that the parent can complete the skill is to use the teach-back method. Hands-on practice can be provided, but the teach-back method more effectively ensures that the parent understands the skill well enough to explain it step by step. Verbal instructions can be supplemented with written instructions, but this does not ensure that the instructions have been understood. There is no evidence that the parent is unable to complete the skill; therefore, the nurse does not need to arrange for an aide to administer the medication. | M109: Planning_and_Management | O109: Analysis
A110: 118 | B110: 5 | C110: 29 | D110: Test | E110: During a death vigil, the MOST appropriate nursing intervention is to: | F110: Teach the family about the dying process | G110: Determine cultural needs at the time of death | H110: Arrange a team meeting to prepare for the loss | I110: Keep family members separated from the patient | J110: Teach the family about the dying process | K110: A | L110: When a child is approaching death, family members will draw near to spend the last days or hours with the child. This time is often referred to as the death vigil. The nurse can provide the most support for the family by teaching them about the process of dying. Any cultural considerations would have been determined earlier in the hospice process. It is not necessary to arrange for a team meeting to prepare for the loss. | M110: Planning_and_Management | O110: Application
A111: 119 | B111: 5 | C111: 30 | D111: Test | E111: The nurse is managing a patient who has undergone a cleft palate repair. Which of the following nursing interventions is MOST critical? | F111: Maintain an intact suture line | G111: Use a syringe or a cup when feeding | H111: Position the patient on their abdomen or side | I111: Keep hard and pointed objects away from the patient’s mouth | J111: Position the patient on their abdomen or side | K111: C | L111: Positioning the patient on their abdomen or side allows for a patent airway. Maintaining a patent airway is the most critical nursing intervention. The nurse should also assess for signs of respiratory distress. Using a syringe or cup during feedings helps prevent injury to the suture line, and rinsing and cleaning the suture line helps to maintain its integrity. However, these actions are not the most critical intervention. While keeping hard and pointed objects away from the patient is an important component of the plan, it is also not the most critical intervention. | M111: Planning_and_Management | O111: Analysis
A112: 120 | B112: 3 | C112: 25 | D112: Practice | E112: A parent brings their 13-year-old child to the clinic with a complaint of a nonpruritic lesion on the child's back that is more pronounced when exposed to sunlight. The nurse notes small areas of pigmented, dry skin. The nurse suspects that the patient has: | F112: Atopic dermatitis | G112: Folliculitis | H112: Contact dermatitis | I112: Tinea versicolor | J112: Tinea versicolor | K112: D | L112: The nurse recognizes that the patient likely has tinea versicolor, which is a fungal infection that interferes with normal pigmentation of the skin. The patient may have small, nonpruritic lesions that are lighter or darker than the surrounding skin. The lesions can be more pronounced when exposed to sunlight. Atopic dermatitis (eczema) is an inflammatory condition characterized by pruritic plaques on the skin. Folliculitis is an inflammation of the hair follicles that is typically caused by a Staphylococcus aureus infection. It is characterized by small red bumps or white-headed pimples around the follicles. Contact dermatitis is an inflammatory condition that develops as a response to an allergen or irritant. It is characterized by erythematous and pruritic skin lesions that appear after contact with a foreign substance. | M112: Planning_and_Management | O112: Application
A113: 121 | B113: 3 | C113: 26 | D113: Practice | E113: The nurse is caring for a 3-year-old patient who has been hospitalized for a week. The child is toilet-trained but is now urinating in the hospital bed. The nurse recognizes that the child is demonstrating: | F113: Self-assertion | G113: Regression | H113: Detachment | I113: Anger | J113: Regression | K113: B | L113: In times of stress, children may experience a temporary loss of developmental milestones, which is termed regression. A child may voice their wants due to their sense of autonomy (self-assertion), but this is not a manifestation of loss of a developmental milestone. Detachment is a break in the bond between parent and child that typically occurs after a prolonged separation. The child may be angry at their parents or at the situation, but that anger is unlikely to result in a developmental regression such as urinating in the bed after having been toilet-trained. | M113: Planning_and_Management | O113: Application
A114: 122 | B114: 3 | C114: 27 | D114: Practice | E114: The nurse is preparing to explain to a 4-year-old patient how a cast will be applied to their arm. Which of the following methods would MOST effectively meet the developmental needs of the child? | F114: Using a doll to demonstrate the casting procedure | G114: Explaining the procedure as it is performed | H114: Showing the child a diagram of the procedure | I114: Playing a video that describes the procedure | J114: Using a doll to demonstrate the casting procedure | K114: A | L114: The most effective teaching method for a preschool-aged child is to use play therapy to demonstrate the casting procedure on a doll. This will allow the child to see that the procedure is not painful and will minimize any fear of body mutilation or loss of body integrity, which is common during this period of development. This would not be effectively conveyed in a video or in explanations as the procedure is performed. The use of a diagram would be more appropriate for a school-aged child. | M114: Planning_and_Management | O114: Analysis
A115: 124 | B115: 5 | C115: 31 | D115: Test | E115: A child’s nursing diagnosis is “Constipation: Risk for, related to appendectomy and anesthetics.” Which of the following interventions is MOST appropriate on the first postoperative day? | F115: Limit activity until peristalsis has returned | G115: Offer liquids when bowel sounds are present | H115: Auscultate bowel sounds every shift | I115: Notify the provider if the child does not have a bowel movement | J115: Offer liquids when bowel sounds are present | K115: B | L115: Present bowel sounds is a sign that peristalsis has resumed and there is no paralytic ileus. The nurse can then offer the child liquids. Activity should not be limited until peristalsis has returned; instead, it should be increased as tolerated to promote gastric motility. Bowel sounds should be auscultated at least every 4 hours, not on shift change. The child is expected to have a bowel movement 3 to 4 days postoperatively, so the provider should not be contacted if there is no bowel movement on day one. | M115: Planning_and_Management | O115: Analysis
A116: 125 | B116: 3 | C116: 28 | D116: Practice | E116: Which of the following is a sign that a ventriculoperitoneal shunt is malfunctioning? | F116: Nausea and vomiting | G116: Decrease in blood pressure | H116: Lethargy and low-grade fever | I116: Febrile seizures | J116: Nausea and vomiting | K116: A | L116: A ventriculoperitoneal shunt drains excess cerebrospinal fluid when there is an obstruction in the normal outflow or decreased absorption of the fluid. It is used to treat hydrocephalus. Common signs of a malfunction include nausea and vomiting, redness over the shunt, headache, and lethargy. Fever, seizures, and low blood pressure are not signs of a malfunction. | M116: Planning_and_Management | O116: Recall
A117: 126 | B117: 5 | C117: 32 | D117: Test | E117: The nurse is educating parents on how to prevent diaper dermatitis. Which of the following will be included in the discharge instructions? | F117: Decrease the frequency of diaper changes | G117: Use zinc oxide barrier cream when changing diapers | H117: Use cloth diapers exclusively | I117: Use baby wipes with alcohol | J117: Use zinc oxide barrier cream when changing diapers | K117: B | L117: Diaper dermatitis is inflammation of the skin caused by skin irritation with urine and feces. Zinc oxide barrier cream provides the best protection against moisture in the area and will help to prevent dermatitis. Moisture increases the rash, so diapers should be changed promptly. Baby wipes with alcohol should not be used because the alcohol may further irritate the skin. There is no evidence that cloth diapers decrease moisture, so disposable diapers can be used. | M117: Planning_and_Management | O117: Application
A118: 127 | B118: 3 | C118: 29 | D118: Practice | E118: An infant is exhibiting increased effort of breathing, has a respiratory rate of 42 breaths/min, and is mildly cyanotic. Which of the following is the PRIORITY nursing intervention? | F118: Administer 100% oxygen and monitor oxygen saturation | G118: Maintain airway and reassess | H118: Administer 100% oxygen and provide comfort measures | I118: Maintain airway and administer oxygen via mask | J118: Administer 100% oxygen and monitor oxygen saturation | K118: A | L118: The child is in moderate respiratory distress with poor oxygen saturation, as evidenced by the mild cyanosis. The priority nursing intervention is to administer 100% oxygen and monitor oxygen saturation. There are no signs of an airway issue at this time, so the oxygen saturation takes precedence. | M118: Planning_and_Management | O118: Analysis
A119: 128 | B119: 3 | C119: 30 | D119: Practice | E119: The nurse is caring for a child with cystic fibrosis who receives pancreatic enzymes. Which statement by the parent demonstrates understanding of proper administration of the supplemental enzymes? | F119: “I will give the enzymes between meals for the best absorption.” | G119: “I will stop the enzymes if my child's stools become greasy.” | H119: “I will stop the enzymes if my child is given any antibiotics.” | I119: “I will give the enzymes before every meal and large snack.” | J119: “I will give the enzymes before every meal and large snack.” | K119: D | L119: In children with cystic fibrosis, the ducts in the pancreas become clogged with thick mucus, which blocks enzymes from reaching food in the small intestine. This can result in low weight gain, malnutrition, and, potentially, failure to thrive. Pancreatic enzyme replacement breaks down complex carbohydrates, fats, and proteins so that the body can absorb the calories, vitamins, and minerals required to gain and maintain weight. To maximize absorption, the enzymes should given before every meal and large snack. Greasy stools are a sign that the body is not effectively breaking down food, so the supplementation should continue to be administered. The enzymes are safe to administer with concurrent antibiotic treatment. | M119: Planning_and_Management | O119: Application
A120: 129 | B120: 3 | C120: 31 | D120: Practice | E120: The nurse is caring for a child immediately after a cardiac catheterization procedure. Which of the following is the PRIORITY nursing intervention? | F120: Assess the area proximal to the incision | G120: Apply a pressure dressing over the catheter site for several hours | H120: Elevate the head of the bed until patient comfort has been achieved | I120: Place the child on bed rest for approximately 2 hours following the procedure | J120: Apply a pressure dressing over the catheter site for several hours | K120: B | L120: A pressure dressing should be applied over the catheter site for several hours to prevent bleeding. In addition, the nurse should assess the area distal, not proximal, to the incision site. The child should be placed on bed rest for at least 6 hours to prevent disruption of the clot, which could lead to a hemorrhage. The child must lie flat to prevent hip flexion, which can predispose the child to bleeding. | M120: Planning_and_Management | O120: Application
... A256: 278 | B256: 3 | C256: 78 | D256: Practice | E256: The nurse is preparing a 3-year-old patient for morning labs. The patient was admitted for suspected child abuse due to multiple broken bones. The parents claim that the child has “brittle bones” and state that they do not abuse their child. The nurse anticipates that which of the following labs will MOST likely be ordered? | F256: Serum calcium, phosphorus, alkaline phosphatase | G256: Serum calcium, potassium, lumbar puncture | H256: Serum calcium, phosphorus, potassium | I256: Disseminated intravascular coagulation panel | J256: Serum calcium, phosphorus, alkaline phosphatase | K256: A | L256: Some bone diseases can lead to “brittle bones” and frequent fractures in different healing stages. The healthcare team should investigate all possible medical causes before concluding that the patient is being abused. Lab work would most likely include serum calcium, phosphorus, and alkaline phosphatase. A disseminated intravascular coagulation panel measures bleeding and clotting times. Lumbar puncture would be performed to test for infection. Potassium levels do not correlate with bone diseases. | M256: Planning_and_Management | O256: Analysis
A257: 279 | B257: 2 | C257: 77 | D257: Practice | E257: A 5-year-old patient is brought into the office by their father for a routine wellness check during the summer. The child has a burn mark on their right palm that is shaped like a square. The nurse's BEST action is to: | F257: Alert local authorities to suspected child abuse | G257: Treat the child for bacterial skin infection | H257: Refer the patient to the ED | I257: Educate the father on the burn wound and discharge with a scheduled follow-up | J257: Educate the father on the burn wound and discharge with a scheduled follow-up | K257: D | L257: Children can present with burn wounds on the palms for multiple reasons. Given the location and shape of the burn and the fact that it is summer, the nurse suspects that the child was burned with a seatbelt buckle. Seatbelt buckles can become extremely hot in direct sunlight and can easily burn the skin of a child. The nurse should care for the wound, educate the father on the potential source of the burn and how to avoid similar burns in the future, and schedule a follow-up. | M257: Assessment | N257: Abuse | O257: Analysis
A258: 280 | B258: 1 | C258: 26 | D258: Practice | E258: The nurse is caring for a child whose weight falls below the 10th percentile and whose length is below the 5th percentile. The plan of care would MOST likely include: | F258: Nutritional rehabilitation such as offering solid food before liquids | G258: Placement of a central line for parenteral nutrition | H258: Insertion of a percutaneous endoscopic gastrostomy tube | I258: Intravenous fluid hydration and protein shakes | J258: Nutritional rehabilitation such as offering solid food before liquids | K258: A | L258: A child with failure to thrive should first be managed with oral nutritional rehabilitation. This includes offering the child high-calorie solid foods prior to offering liquid preparations. Initial management would not include central line placement for parenteral (or intravenous) nutrition; this would be initiated if oral rehabilitation were not successful. A percutaneous endoscopic gastrostomy tube would not be placed initially. If the child is able to chew and swallow food, the oral route should not be bypassed. The use of intravenous fluid hydration and protein shakes would not provide the child with enough calories to gain weight. | M258: Health_Promotion | O258: Analysis
A259: 281 | B259: 3 | C259: 79 | D259: Practice | E259: Which medication is MOST likely to be prescribed to a 12-year-old patient diagnosed with tinea corporis? | F259: Erythromycin | G259: Mupirocin | H259: Metronidazole | I259: Itraconazole | J259: Itraconazole | K259: D | L259: Tinea corporis, also known as ringworm, is a superficial fungal infection (dermatophytosis) generally located on the arms and legs. Itraconazole is an oral antifungal used to treat this infection. Erythromycin, mupirocin, and metronidazole are antibiotics used to treat bacterial infections and are generally ineffective in the treatment of fungal infections. | M259: Planning_and_Management | O259: Application
A260: 282 | B260: 5 | C260: 75 | D260: Test | E260: The nurse is performing an assessment on a 3-month-old infant. The infant's 16-year-old mother notes that she recently dropped out of school and is staying at a male friend's apartment because her parents kicked her out of the house. Which of the following is the MOST accurate statement regarding this situation? | F260: The infant is at increased risk of cognitive delay. | G260: The mother is at increased risk of becoming an abuser. | H260: The mother is at increased risk of becoming a victim of sexual violence. | I260: The infant is at increased risk of malnutrition. | J260: The mother is at increased risk of becoming an abuser. | K260: B | L260: The mother is at increased risk of becoming an abuser toward the infant due to the following factors: young age, lack of a family support system, low education level, and being a new mother. There is not enough information to indicate that the child is at increased risk of cognitive delay or malnutrition. While the mother is staying with a male friend, the nurse cannot assume that the mother is at increased risk of becoming a victim of sexual violence. | M260: Health_Promotion | O260: Analysis
A261: 283 | B261: 3 | C261: 80 | D261: Practice | E261: The nurse is assessing a patient who presents with bright red, pruritic, crusty, and painful lesions. The parent notes that the child developed the rash after playing in the yard over the weekend. The nurse anticipates that the patient will MOST likely be referred to which of the following specialists? | F261: Allergist | G261: Hematologist | H261: Rheumatologist | I261: Dermatologist | J261: Allergist | K261: A | L261: The nurse suspects that the patient developed contact dermatitis after exposure to an allergen such as poison ivy. The patient will likely be referred to an allergist for patch testing. Because the diagnosis is contact dermatitis, a referral to a dermatologist is not necessary unless the rash does not resolve after treatment. A hematologist specializes in blood disorders, and a rheumatologist specializes in musculoskeletal conditions. | M261: Planning_and_Management | O261: Analysis
A262: 284 | B262: 2 | C262: 78 | D262: Practice | E262: While assessing a 3-year-old female patient during a wellness visit, the nurse notices blood in the child's underwear. Which of the following is the MOST accurate statement about this finding? | F262: It is a sign of neglect. | G262: It is a sign of physical abuse. | H262: It is a normal variant in girls due to hormone imbalances. | I262: It is a sign of sexual abuse. | J262: It is a sign of sexual abuse. | K262: D | L262: A 3-year-old girl should not have vaginal discharge or bleeding. Blood on undergarments, unusual odor in the genital area, and difficulty walking or sitting are all signs of sexual abuse in a patient of this age. Physical signs of abuse include bruises that resemble known objects, burn marks, and bruises and fractures in different stages of healing. Inadequate clothing and poor hygiene are two examples of possible signs of neglect. | M262: Assessment | O262: Application
A263: 285 | B263: 5 | C263: 76 | D263: Test | E263: A parent asks the nurse why their newborn son cannot breathe through the mouth when the nose is congested. The nurse's BEST response is: | F263: "You must open the infant's mouth to allow them to breathe." | G263: "Infants copy what they see, so you should breathe through your mouth to show the baby." | H263: "Infants breathe only through the nose until the age of 3 to 4 months." | I263: "Your child may have an oral defect that prevents breathing through the mouth." | J263: "Infants breathe only through the nose until the age of 3 to 4 months." | K263: C | L263: Infants breathe through their nose, even when congested, because they have not yet developed the ability to breathe through their mouths. That reflex typically develops at age 3 to 4 months. It is important to facilitate easier breathing by suctioning the infant’s nose if it is congested. The parent should not open the infant’s mouth to facilitate breathing. Infants do not have the ability to copy actions at this age, so there is no need for the parent to demonstrate the action. There are no indications that the newborn has an oral defect. | M263: Health_Promotion | O263: Application
A264: 286 | B264: 3 | C264: 81 | D264: Practice | E264: A child with a history of recurrent adenoiditis and sinusitis is a candidate for which surgery? | F264: Tonsillectomy | G264: Adenoidectomy | H264: Thyroidectomy | I264: Endoscopy | J264: Adenoidectomy | K264: B | L264: The patient is a candidate for an adenoidectomy, which is the removal of the adenoids. Palatine tonsils are removed during a tonsillectomy. Endoscopy is a diagnostic procedure that examines the esophagus and stomach. A thyroidectomy is the removal of all or part of the thyroid gland. | M264: Planning_and_Management | O264: Recall
A265: 287 | B265: 5 | C265: 77 | D265: Test | E265: When assessing the eyes of an infant with an ophthalmoscope, the nurse notes a white reflex, which indicates: | F265: Retinoblastoma | G265: A normal finding | H265: An eye infection | I265: Keratitis | J265: Retinoblastoma | K265: A | L265: Retinoblastoma, a malignant tumor of the retina, presents as a white reflex instead of the normal red reflex. It is an important finding that requires immediate referral to an ophthalmologist. It is not a normal finding or a sign of infection. Keratitis is an inflammation of the cornea. | M265: Assessment | O265: Recall
A266: 288 | B266: 5 | C266: 78 | D266: Test | E266: The nurse is caring for a 6-year-old patient with severe bacterial sinusitis and vomiting. The patient weighs 23 kg and has a nonsevere penicillin allergy. The nurse will prepare to administer which of the following? | F266: Ceftriaxone | G266: Cefdinir | H266: Amoxicillin | I266: Amoxicillin/clavulanate | J266: Cefdinir | K266: B | L266: Antibiotics should be prescribed for children with severe, worsening, or persistent acute bacterial sinusitis. Children with hypersensitivity to penicillin can be treated with cefdinir. Either amoxicillin or amoxicillin/clavulanate can be used as the first-line treatment in patients who do not have a penicillin allergy. Ceftriaxone IM can be given to children who are vomiting, who are unable take oral medications, or who do not have a penicillin allergy. | M266: Planning_and_Management | O266: Analysis
A267: 289 | B267: 1 | C267: 27 | D267: Practice | E267: A child is admitted with blunt trauma to the abdomen following a motor vehicle crash. The nurse will monitor for: | F267: Anaphylactic reaction | G267: Hemorrhage | H267: Laryngospasm | I267: Pulmonary edema | J267: Hemorrhage | K267: B | L267: Uncontrollable hemorrhage is the most frequent cause of early death in trauma patients. Hemorrhage is a common complication with blunt trauma to the abdomen. Massive hemorrhage may be exacerbated by coagulopathy early after trauma and may transition to critical bleeding that does not respond to surgical hemostasis. An anaphylactic reaction is not associated with blunt trauma to the abdomen. Laryngospasm is the sustained closure of the vocal cords resulting in the partial or complete loss of the patient's airway. Pulmonary edema can develop if excessive fluids/blood products are administered to a hemorrhaging patient. | M267: Health_Promotion | O267: Application
A268: 290 | B268: 3 | C268: 82 | D268: Practice | E268: A parent brings their child into the clinic, reporting that the child passed out during recess. The child complains of dizziness when exercising, has frequent headaches, and has fainted multiple times over the last 3 months. Which task should the nurse perform FIRST? | F268: Pain scale | G268: Vision test | H268: Four-extremity blood pressure | I268: Electrocardiogram | J268: Four-extremity blood pressure | K268: C | L268: The child has the classic symptoms of coarctation of the aorta. Initial assessment includes a four-extremity blood pressure measurement to aid the diagnosis. A blood pressure gradient is evident in these patients, with the upper-extremity blood pressure being 20 mmHg higher than that of the lower extremities. A pain scale and a vision test would not be beneficial in this case. An electrocardiogram is not critical for the diagnosis of coarctation of the aorta. | M268: Planning_and_Management | O268: Analysis
A269: 291 | B269: 1 | C269: 28 | D269: Practice | E269: Which of the following is the MOST appropriate intervention for a 2-year-old patient who has not received the measles, mumps, and rubella (MMR) vaccine? | F269: Administer two doses 4 weeks apart | G269: Administer one dose and then evaluate the patient’s immunity | H269: Administer one dose now and a second dose at age 4 years | I269: Administer two doses 4 weeks apart and then evaluate the patient's immunity | J269: Administer two doses 4 weeks apart | K269: A | L269: The most appropriate intervention is to administer two doses 4 weeks apart. Administering one dose of the MMR vaccine is not sufficient. It is not necessary to evaluate the patient’s immunity after administering any dose of the MMR vaccine. | M269: Health_Promotion | O269: Recall
... A284: 306 | B284: 5 | C284: 84 | D284: Test | E284: The nurse is caring for a child with intussusception who has just passed brown stool. Which of the following is MOST likely true regarding this patient's status? | F284: The physician may order an enema to resolve the condition. | G284: The intussusception has spontaneously resolved. | H284: Immediate surgery is required. | I284: The child was misdiagnosed. | J284: The intussusception has spontaneously resolved. | K284: B | L284: Intussusception occurs when a portion of the intestine telescopes into an adjacent part, leading to obstruction. This condition typically causes severe abdominal pain, vomiting, and the passage of "currant jelly" stools (which are a mix of blood and mucus). When a child with intussusception passes a normal brown stool, it usually signifies that the intestinal obstruction has spontaneously resolved and that the normal function of the intestines has returned. The nurse should report this to the physician immediately, so that the diagnostic and therapeutic care plan can be adjusted, if required. Enemas are often used to diagnose or treat intussusception, but if the condition has already resolved, the physician will not likely order another. Surgery is usually required only if the intussusception persists following more conservative treatment or if there are complications, such as perforation or ischemia. However, if the child has passed brown stool, the condition has likely already resolved, making an enema unnecessary. There is always potential for misdiagnosis, but spontaneous resolution is more likely to have occurred in this situation. | M284: Planning_and_Management | O284: Application
A285: 307 | B285: 2 | C285: 81 | D285: Practice | E285: An 8-year old patient has a partial-thickness circumferential (360-degree) burn to the right arm up to the top of the bicep. This burn constitutes which percentage of total body surface area (TBSA)? | F285: 9% | G285: 4.5% | H285: 18% | I285: 13.5% | J285: 9% | K285: A | L285: A circumferential burn of one entire arm in an 8-year-old patient would constitute 9% of TBSA. A circumferential burn of both arms in an 8-year-old patient would constitute 18% of TBSA. A burn covering one side of the arm only would constitute 4.5% of TBSA. | M285: Assessment | O285: Application
A286: 308 | B286: 2 | C286: 82 | D286: Practice | E286: Which of the following is considered a normal heart sound in children? | F286: Summation gallop | G286: S4 heart sound | H286: Mitral valve prolapse click | I286: S3 heart sound | J286: S3 heart sound | K286: D | L286: The S3 heart sound is considered a normal finding in children, pregnant people, and some athletes. A summation gallop is a pathological finding where all the heart sounds (S1 through S4) are heard in a row. The S4 sound is considered a normal finding in older adults when left ventricle stenosis is present, but it is not a normal finding in children. Mitral valve prolapse causes a murmur that begins right after a mid-systolic click and runs to the end of systole. The murmur is caused by blood backing up into the left atrium. | M286: Assessment | O286: Recall
A287: 309 | B287: 2 | C287: 83 | D287: Practice | E287: When examining a 10-year-old patient, the nurse will auscultate the point of maximal impulse (PMI) at the: | F287: Left fourth intercostal space, mid-clavicular line of chest | G287: Right fourth intercostal space, mid-clavicular line of chest | H287: Right fifth intercostal space, mid-clavicular line of chest | I287: Left fifth intercostal space, mid-clavicular line of chest | J287: Left fifth intercostal space, mid-clavicular line of chest | K287: D | L287: The heart is located on the left side of the sternum. The loudest point of the heartbeat is heard at the left ventricle. To auscultate the loudest heart sound (apical pulse) in a child older than 7 years, the nurse will place the stethoscope at the left side of the chest, at the mid-clavicular line down to the fifth intercostal space. | M287: Assessment | O287: Application
A288: 310 | B288: 3 | C288: 87 | D288: Practice | E288: While assessing a child with asthma, the nurse notes white spots on the tongue and the inside of the mouth. Which of the following is the MOST appropriate guidance to prevent this condition in the future? | F288: Use a spacer with inhaled steroids | G288: Decrease use of inhaled steroids | H288: Use nebulizers three times a day | I288: Use sensitive toothpaste and mouthwash | J288: Use a spacer with inhaled steroids | K288: A | L288: Aero chambers, or spacers, are recommended for use with inhalers. This increases the delivery of the medication, as well as minimizes risk of overgrowth of oral candidiasis (oral thrush), which can result from oral use of steroids and associated depression of the immune system. Oral thrush symptoms include white spots on the tongue and inside of the mouth. Nebulizers will not help to prevent oral thrush, nor will sensitive toothpaste and mouthwash. | M288: Planning_and_Management | O288: Analysis
A289: 311 | B289: 2 | C289: 84 | D289: Practice | E289: Which of the following is a sign that a 5-year-old patient's status is improving after an asthmatic exacerbation? | F289: Skin appears erythemic. | G289: Child appears to be sleeping. | H289: Wheezing breath sounds are auscultated. | I289: Respirations notably decrease. | J289: Wheezing breath sounds are auscultated. | K289: C | L289: Wheezing breath sounds indicate that air is moving through the lungs. A decrease in respirations or the patient appearing to be sleeping could indicate that the patient is experiencing lack of oxygen. Erythemic skin is not related to the asthma episode. | M289: Assessment | O289: Analysis
A290: 312 | B290: 3 | C290: 88 | D290: Practice | E290: The nurse is caring for a patient with epistaxis. The most appropriate INITIAL nursing action is to: | F290: Pinch the patient's nares for 5 minutes | G290: Pack the patient's nares for 10 minutes | H290: Pinch the bridge of the patient's nose for 10 minutes | I290: Place a cool cloth on the back of the patient's neck for 5 minutes | J290: Pinch the patient's nares for 5 minutes | K290: A | L290: Most anterior nasal bleeds respond to pressure. The nurse's best action is to pinch the nares together for a full 5 minutes with the child sitting upright and leaning forward to prevent swallowing of blood. If pinching the nares for 5 minutes does not work, the nurse should pack the nares. Pinching the bridge of the nose is an inappropriate action since it does not apply pressure to the inside of the nose. Placing a cool cloth on the back of the patient's neck is not an effective management strategy for a nosebleed. | M290: Planning_and_Management | O290: Application
A291: 313 | B291: 5 | C291: 85 | D291: Test | E291: While assessing a 1-month-old patient, the nurse notes nine café-au-lait spots that are larger than 5 mm. The nurse anticipates that the patient will MOST likely be referred to which of the following specialists? | F291: Oncologist | G291: Neurologist | H291: Dermatologist | I291: Cardiologist | J291: Neurologist | K291: B | L291: Café-au-lait spots are flat, light- to dark-brown spots. If an infant has six or more spots larger than 5 mm in diameter, neurofibromatosis (von Recklinghausen disease) should be ruled out. The patient will be referred to a neurologist for further assessment. Although the spots appear on the skin, the patient should not be referred to a dermatologist. Café-au-lait spots are not a sign of cancer, so the patient does not require a referral to an oncologist, nor is there a need for a cardiac referral. | M291: Planning_and_Management | O291: Analysis
A292: 314 | B292: 5 | C292: 86 | D292: Test | E292: The nurse is assessing a 5-month-old infant admitted for apnea. The parent mentions that their parents visited 15 days ago from out of town. The nurse's MOST relevant follow-up question is: | F292: "Did either grandparent have a persistent cough?" | G292: "Did either grandparent have a runny nose?" | H292: "Does either grandparent smoke?" | I292: "Did either grandparent have a fever?" | J292: "Did either grandparent have a persistent cough?" | K292: A | L292: It is possible that the patient has pertussis. Infants age 6 months or younger often present with apnea, rather than the typical cough. Symptoms of pertussis can occur up to 3 weeks after exposure, so the nurse should ask the parent if either grandparent had a cough when they visited. Runny nose and fever are less common signs and symptoms of pertussis; asking about persistent cough is most important. Secondhand smoke would not cause apnea. | M292: Assessment | O292: Analysis
A293: 315 | B293: 3 | C293: 89 | D293: Practice | E293: Which antibiotic is the first-line treatment for an unvaccinated infant diagnosed with pertussis? | F293: Penicillin | G293: Macrolide | H293: Cephalosporin | I293: Quinolone | J293: Macrolide | K293: B | L293: The first-line antibiotic treatment for an infant with pertussis is a macrolide (e.g., azithromycin, erythromycin, clarithromycin). Penicillin is indicated for strep throat and otitis media. Cephalosporin is appropriate for gram-positive cocci bacteria. Quinolones are effective against gram-negative and atypical bacteria. | M293: Planning_and_Management | O293: Application
A294: 316 | B294: 1 | C294: 32 | D294: Practice | E294: Which of the following is the MOST common cause of respiratory illness in otherwise healthy children? | F294: Cat dander | G294: Secondhand smoke | H294: Dust mites | I294: Cockroaches | J294: Secondhand smoke | K294: B | L294: Children exposed to secondhand passive or environmental tobacco smoke have increased risk and incidence of respiratory illnesses and symptoms, as well as poorer performance on pulmonary function tests. Dust mites, cockroaches, and cat dander are common household allergens that may exacerbate asthma, but they are not a common cause of respiratory illness in otherwise healthy children. | M294: Health_Promotion | O294: Recall
A295: 317 | B295: 2 | C295: 85 | D295: Practice | E295: What anatomic structure of the upper respiratory tract helps to filter air? | F295: Nose | G295: Cilia | H295: Oropharynx | I295: Pharynx | J295: Cilia | K295: B | L295: The nose and nasal passages serve as a conduit for air to move in and out of the lungs. They are lined with ciliated mucous membranes that filter, warm, and moisten the air. The pharynx is a muscular tube that connects the nasal cavities to the larynx and esophagus. The oropharynx is the middle compartment of the pharynx, which includes the tonsils, tongue base, soft palate, and pharyngeal walls. | M295: Assessment | O295: Recall
A296: 318 | B296: 1 | C296: 33 | D296: Practice | E296: The nurse is reviewing a 5-year-old patient’s immunization record, which includes DTaP, IPV, and influenza vaccines. The nurse will prepare to administer which additional immunization during this visit? | F296: Hepatitis A | G296: Rotavirus | H296: MMR | I296: PPSV | J296: MMR | K296: C | L296: Children age 4 to 6 years should receive the DTaP (diphtheria, tetanus, acellular pertussis), IPV (inactivated poliovirus), MMR (measles, mumps, rubella), varicella, and influenza vaccines. The hepatitis A vaccine is recommended for children age 12 to 23 months. The rotavirus vaccine series must be started by age 6 weeks and completed by age 32 weeks. PPSV (pneumococcal polysaccharide vaccine) is administered at this age only if the child has a high-risk condition. | M296: Health_Promotion | O296: Analysis
A297: 319 | B297: 5 | C297: 87 | D297: Test | E297: Which medication is MOST likely to be prescribed for a 3-year-old with nasal obstruction caused by a rhinovirus? | F297: Antiviral | G297: Decongestant | H297: Acetaminophen | I297: Corticosteroid | J297: Decongestant | K297: B | L297: Decongestants and antihistamines help relieve nasal obstruction caused by a rhinovirus. Antiviral drugs are not used to treat a rhinovirus. Corticosteroids have no effect on the symptoms of rhinovirus and may cause viral replication. Acetaminophen is used to treat a fever or body aches and pains. | M297: Planning_and_Management | O297: Application
... A346: 369 | B346: 5 | C346: 99 | D346: Test | E346: After administering epinephrine to a child in anaphylaxis, the nurse should monitor for: | F346: Bradycardia | G346: Hypertension | H346: Pallor | I346: Confusion | J346: Hypertension | K346: B | L346: Epinephrine induces increased vascular smooth muscle contraction, pupillary dilator muscle contraction, and intestinal sphincter muscle contraction. Other significant effects include increased heart rate, myocardial contractility, and renin release via beta-1 receptors. Signs of an adverse reaction to epinephrine include hypertension, tachycardia, irritability, headache, nausea, and tremors. | M346: Planning_and_Management | O346: Application
A347: 370 | B347: 5 | C347: 100 | D347: Test | E347: The nurse is assisting with the triage of a 4-year-old patient who appears malnourished and has multiple bruises in different healing stages. The nurse suspects child abuse. Which of the following is the MOST appropriate action? | F347: Take the child from their parents | G347: Contact local law enforcement to report abuse | H347: Confront the parents about the suspected abuse | I347: Nothing; children of this age are prone to falling and are picky eaters | J347: Contact local law enforcement to report abuse | K347: B | L347: Healthcare providers have a responsibility to report suspected or known child abuse. Red flags include signs of malnourishment and bruises in multiple stages of healing. The most appropriate action is to report the suspected or known abuse to child protective services, social services, or law enforcement. | M347: Professional_Responsibilities | N347: Abuse | O347: Application
A348: 371 | B348: 4 | C348: 3 | D348: Practice | E348: While the nurse is performing an assessment on a 12-year-old female patient, the child tells the nurse that while she was sleeping over at a friend's house 2 days ago, her friend's brother sexually assaulted her. The nurse's BEST action is to: | F348: Report the information to social services and initiate a forensic examination | G348: Report to social services but not initiate a forensic exam because the time window has passed | H348: Keep the information confidential to protect the patient's privacy | I348: Report to social services and hold the patient for interrogation | J348: Report the information to social services and initiate a forensic examination | K348: A | L348: If the sexual assault took place within 72 hours, a forensic examination should be performed, in addition to notifying the appropriate authorities. One should never interrogate a victim of sexual abuse. The nurse is required by law to report suspected abuse and assault to the proper authorities. | M348: Professional_Responsibilities | N348: Abuse | O348: Application
A349: 372 | B349: 3 | C349: 105 | D349: Practice | E349: The nurse is caring for a 7-month-old patient who suffered a traumatic brain injury. Throughout the day, the infant has become lethargic. A CT scan does not reveal any subdural hematomas or other abnormalities. The nurse's next BEST step is to: | F349: Administer 3% saline solution intravenously | G349: Check the infant’s blood glucose level | H349: Initiate enteral feeding | I349: Administer intramuscular glucagon | J349: Check the infant’s blood glucose level | K349: B | L349: Infants with traumatic brain injury are at increased risk for complications. A CT scan did not reveal any acute abnormalities, so the next best step would be to check the blood glucose level because a lethargic child may be hypoglycemic. It is important to avoid hypoglycemia to maintain proper brain function. Administration of 3% saline solution would be toxic to this infant. Starting the child on enteral feeds or glucagon would be inappropriate without first assessing the blood glucose level. | M349: Planning_and_Management | O349: Application
A350: 373 | B350: 2 | C350: 102 | D350: Practice | E350: Which of the following laboratory tests should be performed by a trained physician? | F350: Tympanometry | G350: Culture of the eye | H350: Culture of the ear | I350: Tympanic fluid culture | J350: Tympanic fluid culture | K350: D | L350: Tympanic fluid culture of fluid aspirated from the middle ear is painful for the patient and should be performed only by a trained physician. Culture of eye or ear drainage is easy to collect and relatively pain free. Tympanometry is not a laboratory test. It involves a probe that can be placed in the ear canal to measure movement of the eardrum. | M350: Assessment | O350: Recall
A351: 374 | B351: 3 | C351: 106 | D351: Practice | E351: Which of the following interventions is MOST appropriate for a trauma patient with no facial or cranial injury? | F351: Reverse Trendelenburg position | G351: Recovery position | H351: Orogastric or nasogastric tube | I351: Endotracheal tube | J351: Orogastric or nasogastric tube | K351: C | L351: An orogastric or nasogastric tube should be inserted in trauma patients without facial or cranial injury to prevent gastric distention, vomiting, and aspiration. The recovery position is a side-lying position, which is inappropriate for trauma patients because they should have spinal precautions until they have been cleared from spinal injuries. Reverse Trendelenburg places the patient supine with the head of the bed elevated to a 15- to 30-degree incline. In trauma, it is recommended to place a patient in Trendelenburg position with the patient's feet elevated to a 15- to 30-degree incline. Nurses do not insert endotracheal tubes. | M351: Planning_and_Management | O351: Application
A352: 375 | B352: 2 | C352: 103 | D352: Practice | E352: The respiratory rate threshold for diagnosing a 7-month old patient with pneumonia is: | F352: ≥60 breaths/min | G352: ≥50 breaths/min | H352: ≥40 breaths/min | I352: ≥30 breaths/min | J352: ≥50 breaths/min | K352: B | L352: Observing a child's respiratory effort during a physical exam is an important first step in diagnosing pneumonia. The respiratory rate thresholds for diagnosing children with pneumonia are ≥60 breaths/min for children younger than 2 months, ≥50 breaths/min for children age 2 to 11 months, and ≥40 breaths/min in children age 12 to 59 months. | M352: Assessment | O352: Recall
A353: 376 | B353: 5 | C353: 101 | D353: Test | E353: An infant with cystic fibrosis is MOST likely to present with: | F353: Diarrhea | G353: Bronchial breath sounds | H353: Pigeon chest | I353: Poor weight gain | J353: Poor weight gain | K353: D | L353: A child with cystic fibrosis may present with abdominal pain with poor weight gain; difficulty passing stools; bulky, greasy stools; meconium ileus or delayed meconium in the newborn period; respiratory distress with adventitious breath sounds; barrel chest; and nail clubbing. | M353: Assessment | O353: Recall
A354: 377 | B354: 1 | C354: 40 | D354: Practice | E354: The nurse is educating new parents on oral iron supplementation. The nurse will instruct the parents to: | F354: Give the supplement with milk as it may enhance absorption | G354: Discontinue supplementation if the child develops constipation | H354: Avoid vitamin C–containing juices, which hinder absorption | I354: Continue supplementation if the child's stool becomes dark in color | J354: Continue supplementation if the child's stool becomes dark in color | K354: D | L354: It is normal for stool to become dark in color as a result of oral iron supplementation. Oral iron supplementation may cause constipation; however, this is not cause to stop the supplementation. The nurse should instruct the parents to try laxative juices such as prune juice or talk to the provider about prescribed or over-the-counter laxatives. Oral iron supplementation should never be given with milk, as it will hinder absorption. Conversely, vitamin C–containing juices may enhance absorption of oral iron supplementation. | M354: Health_Promotion | O354: Application
A355: 378 | B355: 3 | C355: 107 | D355: Practice | E355: Which of the following disorders MOST commonly occurs after upper respiratory tract or human parvovirus infection? | F355: Immune thrombocytopenia | G355: Wiskott-Aldrich syndrome | H355: Severe combined immunodeficiency | I355: HIV | J355: Immune thrombocytopenia | K355: A | L355: Immune (or idiopathic) thrombocytopenia purpura (ITP) is described as a platelet count of <150,000 lasting longer than 6 months from initial manifestation. The acute form of ITP is typically preceded by vaccination or a viral infection, such as an upper respiratory tract or human parvovirus infection. HIV is contracted by sharing body fluids with someone who is infected with the virus. Severe combined immunodeficiency and Wiskott-Aldrich syndrome are caused by a chromosomal defect. | M355: Planning_and_Management | O355: Recall
A356: 380 | B356: 3 | C356: 108 | D356: Practice | E356: The nurse is assessing a patient with abdominal pain, decreased appetite, and behavioral changes. Labs reveal an elevated free erythrocyte protoporphyrin (FEP) level and a lead level of 68 mcg/dL. The treatment plan will MOST likely include: | F356: Nutrition counseling | G356: Oral chelation therapy | H356: Hospitalization | I356: Consultation with medical toxicology | J356: Oral chelation therapy | K356: B | L356: The patient is diagnostic for lead poisoning. Patients with a lead level of 45 to 69 mcg/dL should be removed from the source of the lead and treated with oral chelation medication. If the patient's lead level were 70 mcg/dL or higher, hospitalization and consultation with a medical toxicologist would be required. For levels below 45 mcg/dL, treatment includes education on nutrition (increasing calcium and iron) and reducing exposure to lead hazards. | M356: Planning_and_Management | O356: Analysis
A357: 382 | B357: 5 | C357: 102 | D357: Test | E357: What causes a bronzed complexion in children with thalassemia major? | F357: Amyloid | G357: Hyperbilirubinemia | H357: Hemosiderosis | I357: Nephrocalcinosis | J357: Hemosiderosis | K357: C | L357: The muddy bronze color results from hemosiderosis, a deposit of iron in the tissues as a result of rapid destruction of blood cells. Amyloid is an abnormal protein produced in bone marrow, which can be deposited in any tissue or organ. Hyperbilirubinemia is the buildup of bilirubin in the blood, which causes jaundice. Nephrocalcinosis is characterized by the deposition of calcium in the kidney parenchyma and tubules. | M357: Planning_and_Management | O357: Recall
A358: 383 | B358: 3 | C358: 109 | D358: Practice | E358: The nurse is administering intravenous (IV) fluid replacement to an infant who weighs 15 lb. What is the daily fluid maintenance requirement? | F358: 1,500 mL | G358: 700 mL | H358: 1,250 mL | I358: 500 mL | J358: 700 mL | K358: B | L358: Fluid intoxication can occur during IV fluid replacement. Infants are especially vulnerable to fluid volume excess. Daily fluid maintenance requirements are based on body weight (kg). Children who weigh 1 to 10 kg should receive 100 mL/kg/day. Children who weigh 11 to 20 kg should receive 1,000 mL plus 50 mL/kg for each kg above 10 kg. Children who weigh more than 20 kg should receive 1,500 mL plus 20 mL/kg for each kg above 20. The patient weighs 15 lb, which is approximately 7 kg, resulting in a daily limit of 700 mL. | M358: Planning_and_Management | O358: Analysis
A359: 384 | B359: 3 | C359: 110 | D359: Practice | E359: Which of the following statements BEST describes acrocyanosis? | F359: It is a sign of anemia. | G359: It is a normal finding in a newborn. | H359: It is an indication of cardiopulmonary disease. | I359: It is a late sign of respiratory distress. | J359: It is a normal finding in a newborn. | K359: B | L359: Acrocyanosis is a functional peripheral vascular disorder characterized by dusky, mottled discoloration, or cyanosis, of the hands, the feet, and sometimes the face. Acrocyanosis is a normal finding in a newborn. Central cyanosis is a late sign of respiratory distress in children, as well as an indication of cardiopulmonary disease. Pallor is a sign of anemia in children. | M359: Planning_and_Management | O359: Recall
A360: 385 | B360: 2 | C360: 104 | D360: Practice | E360: Jaundice is considered an abnormal assessment when observed at age: | F360: 72 hours | G360: 48 hours | H360: 96 hours | I360: 12 hours | J360: 12 hours | K360: D | L360: Physiologic jaundice typically appears on the second or third day of life and is a normal finding. Jaundice at age 12 hours is a pathologic finding that may indicate sepsis. | M360: Assessment | O360: Recall
... A375: 402 | B375: 3 | C375: 113 | D375: Practice | E375: The nurse is caring for a 5-year-old patient with a fractured forearm. The parent states that the child fell off their bike and landed on the hands with the arms extended. The x-ray shows a spiral fracture. The nurse suspects: | F375: Compartment syndrome | G375: Osteogenesis imperfecta | H375: Physical abuse | I375: Developmental delays | J375: Physical abuse | K375: C | L375: Injuries that are not consistent with the story presented can be a sign of physical abuse. A child who fell off a bike with arms extended would not present with a spiral fracture, which is typically caused by a twisting motion. Compartment syndrome is a condition caused by pressure buildup from swelling of tissues. Osteogenesis imperfecta is imperfect bone formation, which increases risk of fractures. Development delays are classified as physical or cognitive delays, which do not apply in this case. | M375: Planning_and_Management | O375: Application
A376: 403 | B376: 4 | C376: 4 | D376: Practice | E376: The four subcategories of child abuse are: | F376: Physical, material, nutritional, emotional | G376: Physical, material, emotional, sexual | H376: Physical, emotional, sexual, violent | I376: Physical, emotional, sexual, neglect | J376: Physical, emotional, sexual, neglect | K376: D | L376: Child abuse can be broken into four subcategories: physical abuse, emotional abuse, sexual abuse, and neglect. Violent, nutritional, and material abuse are not categories of child abuse. | M376: Professional_Responsibilities | N376: Abuse | O376: Recall
A377: 404 | B377: 2 | C377: 108 | D377: Practice | E377: The nurse is triaging a 16-year-old female patient who presents to the ED with pelvic pain. The patient is accompanied by her aunt. When the nurse asks the patient questions, the aunt quickly responds before the patient has an opportunity to do so. The nurse's BEST action is to: | F377: Interview the aunt and the patient separately | G377: Direct all questions to the aunt | H377: Attribute the patient's behavior to normal adolescent development | I377: Ask the patient directly if she is being abused while her aunt is still in the room | J377: Interview the aunt and the patient separately | K377: A | L377: When a family member or significant other is not allowing a patient to answer questions or talk for themselves, the nurse should interview the parties separately to assess for potential abuse. The nurse should not inquire about abuse while the aunt is still in the room. The nurse should not address all questions to the aunt, nor should the nurse assume that the patient is slow to respond due to adolescent development. | M377: Assessment | O377: Analysis
A378: 405 | B378: 5 | C378: 108 | D378: Test | E378: The nurse is caring for an 8-month-old child abuse victim who was repeatedly burned with cigarettes. The nurse is preparing the patient for a skeletal survey. A nursing assistant asks why a skeletal survey has been ordered for a patient with burn injuries. The nurse's BEST response is: | F378: "The skeletal survey assesses for other injuries and signs of abuse, such as fractured bones." | G378: "The skeletal survey assesses range of motion and helps determine if wounds are self-inflicted." | H378: "The skeletal survey assesses for growth milestones in infants to rule out structural disease." | I378: "All infants admitted to the unit should receive a skeletal survey." | J378: "The skeletal survey assesses for other injuries and signs of abuse, such as fractured bones." | K378: A | L378: When managing a child victim of abuse who is immobile or too young to provide a history, it is important to assess for all possible injuries. This can be done with a skeletal survey, which is a series of radiographs that looks at the entire anatomical structure for evidence of fractures consistent with abuse. | M378: Planning_and_Management | O378: Application
A379: 407 | B379: 5 | C379: 109 | D379: Test | E379: Prior to discharging a newborn, the nurse should ensure that close family members have been vaccinated against which disease? | F379: Diphtheria | G379: Pertussis | H379: Tetanus | I379: Polio | J379: Pertussis | K379: B | L379: Pertussis, also known as whooping cough, is a very contagious respiratory disease that presents a high risk to infants. Close family members of newborns should be vaccinated against pertussis to protect the infant. Generally, children receive the DTaP vaccine, and adolescents and adults receive the Tdap vaccine, as part of routine preventive care. It is not necessary for family members to receive the diphtheria, tetanus, or polio vaccinations before discharge of the newborn. | M379: Health_Promotion | O379: Recall
A380: 408 | B380: 5 | C380: 110 | D380: Test | E380: A 14-year-old female patient is admitted after ingesting approximately 25 acetaminophen tablets. After assessing airway, breathing, and circulation, the nurse should prepare to: | F380: Administer acetylcysteine | G380: Establish two large-bore intravenous lines | H380: Obtain an EKG | I380: Administer dopamine | J380: Administer acetylcysteine | K380: A | L380: The nurse should prepare to administer acetylcysteine, which is the appropriate initial treatment for acetaminophen overdose. Multiple large-bore intravenous lines are appropriate for trauma or hypovolemia. Obtaining an EKG is not an initial action for acetaminophen overdose, and dopamine is not used in the treatment of acetaminophen overdose. | M380: Planning_and_Management | O380: Recall
A381: 409 | B381: 2 | C381: 109 | D381: Practice | E381: A patient presents to the ED with tenderness and swelling of the forearm after a fall. What acronym should guide the nurse’s assessment? | F381: The 2 Ps | G381: The 3 Ps | H381: The 4 Ps | I381: The 5 Ps | J381: The 5 Ps | K381: D | L381: All patients with a suspected fracture should be assessed for the 5 Ps: pain, pulse, pallor, paresthesia, and paralysis. | M381: Assessment | O381: Recall
A382: 410 | B382: 1 | C382: 45 | D382: Practice | E382: Which of the following is a safety measure to reduce risk of infant suffocation? | F382: Keeping blankets in crib firmly tucked | G382: Keeping side rails of crib up | H382: Positioning crib by a window | I382: Ensuring that crib is free of pillows | J382: Ensuring that crib is free of pillows | K382: D | L382: The most common causes of unintentional injury in patients younger than 1 year are suffocation and motor vehicle crashes. To reduce risk of infant suffocation, cribs should be kept free of pillows and blankets, even those that are firmly tucked. While the side rails should always be kept up, it is a not a measure to reduce risk of infant suffocation. Cribs should be kept away from windows because they could have drapes or blind cords that can become wrapped around the infant’s neck, causing suffocation. | M382: Health_Promotion | O382: Recall
A383: 411 | B383: 3 | C383: 114 | D383: Practice | E383: The nurse is caring for a 4-year-old patient in status epilepticus. Which of the following is the PRIORITY nursing action? | F383: Maintain airway | G383: Obtain electrolyte values | H383: Obtain a blood glucose level | I383: Administer anticonvulsants | J383: Maintain airway | K383: A | L383: The priority nursing action for a patient in status epilepticus is the ABCs: airway, breathing, and circulation. Administration of anticonvulsants and obtaining blood glucose and electrolyte values should be done after basic life support is provided. | M383: Planning_and_Management | O383: Application
A384: 412 | B384: 5 | C384: 111 | D384: Test | E384: Which abnormal lab value would be found in a 9-year-old patient who is taking oxcarbazepine for treatment of partial seizures? | F384: Folate 21 ng/mL | G384: Sodium 128 mEq/L | H384: Creatinine 1.0 mg/dL | I384: ALT 55 U/L | J384: Sodium 128 mEq/L | K384: B | L384: Use of oxcarbazepine can cause hyponatremia and should be monitored and treated accordingly. A sodium level of 128 mEq/L is considered hyponatremic. Folate monitoring is required with phenytoin therapy. Normal plasma folate levels in children are 5 to 21 ng/mL. Creatinine should be monitored when a patient is receiving oxcarbazepine; however, a value of 0.5 to 1.0 mg/dL is normal. ALT (alanine transaminase) should be monitored when a patient is on phenobarbital. Normal ALT levels are 7 to 55 U/L. | M384: Planning_and_Management | O384: Application
A385: 413 | B385: 4 | C385: 5 | D385: Practice | E385: Which of the following is the BEST example of the nurse providing atraumatic care? | F385: Using the largest-gauge needle required | G385: Incorporating the use of pharmacologic strategies | H385: Placing a peripherally inserted central catheter if multiple blood samples are required | I385: Opting for heel stick instead of venipuncture when a large amount of blood is required in a newborn | J385: Placing a peripherally inserted central catheter if multiple blood samples are required | K385: C | L385: Using an intermittent infusion device or a peripherally inserted central catheter if multiple or repeated blood samples are necessary will decrease pain for the patient. This is an example of the nurse providing atraumatic care. Using the smallest-gauge needle possible or an automated lancet device to puncture the skin will reduce pain with a needlestick. The nurse should try nonpharmacologic strategies for pain relief first or in conjunction with pharmacologic interventions. The nurse may opt for venipuncture in newborns instead of a heel stick if the amount of blood required would result in significant painful squeezing of the heel. | M385: Professional_Responsibilities | N385: Atraumatic care | O385: Application
A386: 415 | B386: 2 | C386: 110 | D386: Practice | E386: The nurse is providing postoperative care for an 8-year-old patient who underwent a thyroidectomy. Which of the following emergency supplies should be kept at the bedside? | F386: Central-line tray | G386: Chest tube set | H386: Tracheostomy set | I386: Intraosseous kit | J386: Tracheostomy set | K386: C | L386: After a thyroidectomy, it is important to watch for signs of laryngospasm and to always have a tracheostomy set at the bedside for emergency use. Thyroidectomy is a high-risk procedure, and airway complications often occur. A central-line tray, a chest tube set, and an intraosseous kit are not indicated for a patient status post thyroidectomy. | M386: Assessment | O386: Application
A387: 416 | B387: 2 | C387: 111 | D387: Practice | E387: Which of the following is the MOST likely spinal muscle atrophy (SMA) diagnosis in a 1-month-old patient? | F387: SMA type 1 | G387: SMA type 2 | H387: SMA type 3 | I387: SMA type 4 | J387: SMA Type 1 | K387: A | L387: SMA is a genetic disorder characterized by weakness and atrophy in skeletal muscles. Type 1 is the most severe form of SMA, and it begins in utero or in early infancy. SMA type 2 occurs in later infancy. SMA type 3 is a juvenile form of the disease. SMA type 4 does not exist. | M387: Assessment | O387: Recall
A388: 417 | B388: 5 | C388: 112 | D388: Test | E388: Cranial nerve III is the: | F388: Olfactory nerve | G388: Trochlear nerve | H388: Trigeminal nerve | I388: Oculomotor nerve | J388: Oculomotor nerve | K388: D | L388: The oculomotor nerve is also known as cranial nerve III. The olfactory nerve is cranial nerve I, the trochlear nerve is cranial nerve IV, and the trigeminal nerve is cranial nerve V. | M388: Assessment | O388: Recall
A389: 418 | B389: 3 | C389: 115 | D389: Practice | E389: The nurse is managing a patient after a cleft lip repair. Which of the following nursing interventions is MOST critical? | F389: Maintain a patent airway | G389: Maintain an intact suture line | H389: Use a syringe with tubing to administer food | I389: Monitor for pain and administer medications | J389: Maintain a patent airway | K389: A | L389: Maintaining a patent airway is the most critical nursing intervention. Positioning the patient on their abdomen or side allows for a patent airway. The nurse should observe for cyanosis to detect signs of respiratory distress or compromise as the infant begins to breathe through their nose. The nurse should also perform other less-critical interventions, such as maintaining an intact suture line by keeping it clean and keeping the patient’s hands out of their mouth. When it is time to feed the patient, the nurse should use a syringe with tubing to administer foods in the side of the mouth. This will prevent trauma to the suture line. The nurse should also monitor for and address any pain or discomfort. | M389: Planning_and_Management | O389: Application
A390: 419 | B390: 3 | C390: 116 | D390: Practice | E390: Which of the following nursing actions can help reduce a patient's fever? | F390: Promoting shivering | G390: Applying heat packs | H390: Administering NSAIDs | I390: Placing a blanket | J390: Administer NSAIDs | K390: C | L390: Reducing fever helps maintain optimal cerebral perfusion by reducing the metabolic needs of the brain. To reduce fever, the nurse can administer antipyretics such as acetaminophen and NSAIDs such as ibuprofen. The nurse can reduce environmental temperature by using cooling blankets, fans, cold compresses, and tepid baths. It is important to avoid measures that cause shivering because shivering increases heat production. | M390: Planning_and_Management | O390: Recall
A391: 420 | B391: 3 | C391: 117 | D391: Practice | E391: Which of the following is an indication for the intramuscular (IM) administration of epinephrine in a child with a life-threatening anaphylactic reaction? | F391: Barky cough | G391: Vomiting | H391: Fever | I391: Pallor | J391: Barky cough | K391: A | L391: Indications for the IM administration of epinephrine include itching sensation or tightness in the throat, hoarseness, barky cough, difficulty swallowing, dyspnea, wheezing or stridor, itching, flushing, urticaria, angioedema, anxiety, confusion, sense of impending doom, syncope, bradycardia, dysrhythmia, or hypotension. Vomiting, fever, and pallor are not signs of life-threatening anaphylactic reaction. | M391: Planning_and_Management | O391: Application
A392: 421 | B392: 5 | C392: 113 | D392: Test | E392: Which test is MOST diagnostic for an arteriovenous malformation (AVM)? | F392: Ultrasound | G392: Cerebral arteriography | H392: MRI | I392: CT scan | J392: Cerebral arteriography | K392: B | L392: The cerebral arteriography test is the most diagnostic test for AVM. This test indicates the location and characteristics of the feeding arteries and draining veins. A CT scan uses a series of x-rays to create a thorough cross-sectional image of the brain. MRI uses magnets and radio waves to create comprehensive images of the brain. It is more sensitive than a CT scan and can show more subtle changes in brain tissue. Ultrasound is an imaging method that uses high-frequency sound waves to produce images of structures. It is not used on the brain. | M392: Planning_and_Management | O392: Recall
A393: 422 | B393: 3 | C393: 118 | D393: Practice | E393: A 10-year-old patient presents to the ED with an animal bite. Which of the following is MOST likely to be included in this patient’s treatment plan? | F393: Admission for observation, administration of tetanus toxoid and antibiotics | G393: Radiographic studies, administration of tetanus toxoid and antibiotics | H393: Radiographic studies, admission for observation, administration of antibiotics | I393: Admission for observation, radiographic studies, administration of tetanus toxoid | J393: Radiographic studies, administration of tetanus toxoid and antibiotics | K393: B | L393: The treatment plan for this patient will likely include the following: radiographic studies to assess for underlying damage due to the bite, a tetanus vaccine, and antibiotics to prevent infection. There are no indications that the patient should be admitted for observation. | M393: Planning_and_Management | O393: Application
A394: 423 | B394: 2 | C394: 112 | D394: Practice | E394: The nurse is performing a neurologic assessment of an adolescent patient. When passively providing forward flexion of the neck, the patient involuntarily raises their knees. The patient is exhibiting a positive: | F394: Battle sign | G394: Kernig sign | H394: Babinski sign | I394: Brudzinski sign | J394: Brudzinski sign | K394: D | L394: Brudzinski sign is positive when passive forward flexion of the neck causes the patient to involuntarily raise their knees or hips in flexion. Kernig sign is performed by having the patient, positioned on their back with hips and knees flexed, extend the leg passively. The test is positive if the leg extension causes pain. In children older than 2 years, a positive Babinski sign occurs when the big toe bends up and back to the top of the foot and the other toes fan out. This can indicate an underlying nervous system or brain condition that is causing reflexes to react abnormally. Battle sign is a bruise behind the ear that indicates a fracture at the bottom of the skull. | M394: Assessment | O394: Application
A395: 424 | B395: 5 | C395: 114 | D395: Test | E395: To prevent mechanical friction while rewarming a frostbitten extremity, the nurse will: | F395: Apply dry heat | G395: Stop rewarming if the patient indicates pain | H395: Avoid tissue-to-tissue contact | I395: Apply sterile gauze bandages | J395: Avoid tissue-to-tissue contact | K395: C | L395: Rapid rewarming in circulating water is the recommended treatment for frostbite. The nurse can prevent mechanical friction by not touching the extremity and by avoiding tissue-to-tissue contact. The nurse should avoid applying dry heat, as the loss of temperature sensitivity in the injured area may lead to burns. Sterile nonadherent dressings should be used, not sterile gauze bandages. The most common error in this stage of treatment is premature termination of the rewarming process because of reperfusion pain. | M395: Planning_and_Management | O395: Application
A396: 425 | B396: 1 | C396: 46 | D396: Practice | E396: High doses of which supplement can cause urine to turn bright yellow? | F396: Riboflavin | G396: Anthocyanin | H396: Vitamin B12 | I396: Beetroot | J396: Riboflavin | K396: A | L396: Riboflavin is a water-soluble vitamin that has a naturally intense yellow color. Any excess riboflavin in the body is excreted through the urine, causing a distinctive bright or “neon” yellow appearance. Anthocyanin can cause urine to turn a blue-green color. High doses of certain forms of vitamin B12 can tinge urine with a light pink or reddish color. Beetroot (and beetroot supplements) can cause a red or pinkish discoloration of urine (known as “beeturia”). | M396: Health_Promotion | O396: Recall
A397: 427 | B397: 1 | C397: 47 | D397: Practice | E397: Which stage of Erikson’s psychosocial theory occurs between the ages of 6 and 11 years? | F397: Initiative versus guilt | G397: Industry versus inferiority | H397: Identity versus role diffusion | I397: Autonomy versus shame and doubt | J397: Industry versus inferiority | K397: B | L397: At age 6 to 11 years, children begin to develop a sense of pride in their accomplishments, which takes place in the industry versus inferiority stage. Initiative versus guilt, when children assert themselves more frequently and develop a sense of initiative, occurs at age 3 to 5 years. At age 1 to 3 years, children begin to gain their independence. This is the autonomy versus shame and doubt stage. Identity versus role diffusion happens from age 11 years to the end of adolescence. In this stage, the child becomes more independent and begins to form their own identity. | M397: Health_Promotion | O397: Recall
... A531: 566 | B531: 1 | C531: 68 | D531: Practice | E531: Who are the MOST likely perpetrators of infant abuse? | F531: Daycare workers | G531: Older siblings | H531: Relatives living outside the home | I531: Parents of the child | J531: Parents of the child | K531: D | L531: Parents are the most likely perpetrators of abuse in infants, followed by daycare workers, and then relatives living outside the home. Siblings are not statistically significant abusers. | M531: Health_Promotion | O531: Recall
A532: 568 | B532: 4 | C532: 6 | D532: Practice | E532: A parent is reprimanding their child in the waiting room, and the nurse overhears the following statement: “Who cares if you're missing school today? You'll never amount to anything anyway.” The nurse notifies the provider about their concern for: | F532: Developmental delay | G532: Emotional abuse | H532: Physical abuse | I532: Uneducated parent | J532: Emotional abuse | K532: B | L532: Emotional abuse can present as ridicule, rejection, isolation, and terrorizing of the child. Physical abuse involves physical harm to the child, such as burning, cutting, or hitting. Developmental delays are classified as physical or cognitive delays. Uneducated parents are something to note in the patient's record; however, the healthcare staff can provide only general information to help the parent understand the importance of education and support. | M532: Professional_Responsibilities | N532: Abuse | O532: Application
A533: 569 | B533: 5 | C533: 157 | D533: Test | E533: When performing a well-child check on a 5-year-old patient, the nurse notes that the child is underweight and is wearing dirty clothing. When the nurse asks the parent what the child eats during a typical day, the parent responds, “I don’t know. I work two jobs. I don't have time to watch my child eat.” The nurse is concerned about possible: | F533: Child abuse | G533: Child neglect | H533: Gastrointestinal disease | I533: Viral infection | J533: Child neglect | K533: B | L533: Neglect involves the absence of care or the absence of necessities. Caregivers should provide a child with food, clean clothing, and shelter. When the caregiver is not providing the child with these necessities, and the child is suffering as a result, it is called neglect. Abuse is active harm to a child and takes the form of physical abuse (e.g., hitting, burning with cigarettes), sexual abuse, or active emotional abuse. A viral infection presents with head, eyes, ears, nose, and throat (HEENT) symptoms and fever. Gastrointestinal disease would manifest as nausea, vomiting, diarrhea, and possible fever. | M533: Professional_Responsibilities | N533: Neglect | O533: Application
A534: 570 | B534: 1 | C534: 69 | D534: Practice | E534: The nurse is assessing a previously healthy 11-year-old female patient who has started speaking in three-word sentences, throwing tantrums, and drawing crude stick figures. The concerned parent notes that the child used to read books and write in her journal daily. The nurse recognizes that the child is exhibiting signs of: | F534: Neurodevelopmental delay | G534: Child abuse | H534: Meningitis | I534: General anxiety disorder | J534: Child abuse | K534: B | L534: Regression is a sign of abuse, which can include physical, sexual, or emotional abuse. Any child who was previously healthy and showed no signs of developmental delay should be evaluated for abuse when regression is noted. Neurodevelopmental delay is a delay in skill development, not a regression. Meningitis is the inflammation of the membranes covering the brain and spinal cord. It manifests with headache, fever, and stiff neck. General anxiety disorder presents as worry, restlessness, and difficulty concentrating. | M534: Health_Promotion | O534: Application
A535: 571 | B535: 3 | C535: 158 | D535: Practice | E535: The nurse is caring for an 8-year-old patient who is being treated for burns on the buttocks secondary to hot water. The nurse notes that the child has “dunk” wounds. Which of the following is the MOST accurate statement regarding this patient? | F535: The child was lying in the tub of hot water with their legs up. | G535: The child was placed into the hot water by another person. | H535: The child spilled hot water onto their skin. | I535: The child was splashed with hot water. | J535: The child was placed into the hot water by another person. | K535: B | L535: The child presents with burns on the buttocks and “dunk” wounds, meaning that the soles of the feet and parts of the legs were spared. This indicates that when the child was placed in the tub by another person, they retracted the feet and legs due to the extreme heat. The nurse should contact child protective services and local authorities to report abuse. | M535: Planning_and_Management | O535: Application
...

Sheet Batch planning - review
G1: Review of 4e Practice Test Items | M1: Review of 5e Knowledge Check Items
A2: Topic | C2: Recall Items (Planned) | D2: Application Items (Planned) | E2: Analysis Items (Planned) | F2: Total (Planned) | G2: Practice Test items from 4e (from Items tab) | H2: Teri Berry | I2: Amber Dortch | J2: Katherine Glass | K2: Tiffany Glass | L2: Uncommitted | M2: Knowledge Check items for 5e | N2: Teri Berry | O2: Amber Dortch | P2: Katherine Glass | Q2: Tiffany Glass | R2: Uncommitted | S2: Writer1 | T2: Writer2 | U2: Writer3 | V2: Writer4 | W2: Uncommitted | X2: Deviation from plan
C3: =SUM(C4:C18) -> 0 | D3: =SUM(D4:D18) -> 0 | E3: =SUM(E4:E18) -> 0 | F3: =SUM(C3:E3) -> 0 | G3: =SUM(G4:G18) -> #REF! | H3: =SUM(H4:H18) -> #REF! | I3: =SUM(I4:I18) -> #REF! | J3: =SUM(J4:J18) -> #REF! | K3: =SUM(K4:K18) -> #REF! | L3: =SUM(L4:L18) -> #REF! | M3: =SUM(M4:M18) -> #REF! | N3: =SUM(N4:N18) -> #REF! | ... W3: =SUM(W4:W18) -> #REF!
A4: Cardiovascular System | F4: =SUM(C4:E4) -> 0 | G4: =COUNTIFS(#REF!,$A4,#REF!,"N/A (4e)",#REF!,"Practice Test") -> #REF! | H4: =COUNTIFS(#REF!,$A4,#REF!,"N/A (4e)",#REF!,"Practice Test",#REF!,H$2) -> #REF! | I4: =COUNTIFS(#REF!,$A4,#REF!,"N/A (4e)",#REF!,"Practice Test",#REF!,I$2) -> #REF! | J4: =COUNTIFS(#REF!,$A4,#REF!,"N/A (4e)",#REF!,"Practice Test",#REF!,J$2) -> #REF! | K4: =COUNTIFS(#REF!,$A4,#REF!,"N/A (4e)",#REF!,"Practice Test",#REF!,K$2) -> #REF! | L4: =G4-SUM(H4:K4) -> #REF! | M4: =COUNTIFS(#REF!,$A4,#REF!,"<>N/A (4e)",#REF!,"Knowledge Check") -> #REF! | N4: =COUNTIFS(#REF!,$A4,#REF!,"Knowledge Check",#REF!,N$2) -> #REF! | O4: =COUNTIFS(#REF!,$A4,#REF!,"Knowledge Check",#REF!,O$2) -> #REF! | P4: =COUNTIFS(#REF!,$A4,#REF!,"Knowledge Check",#REF!,P$2) -> #REF! | Q4: =COUNTIFS(#REF!,$A4,#REF!,"Knowledge Check",#REF!,Q$2) -> #REF! | R4: =M4-SUM(N4:Q4) -> #REF! | W4: =F4-#REF! -> #REF! | X4: =G4-F4 -> #REF!
A5: Endocrine System | F5: =SUM(C5:E5) -> 0 | G5: =COUNTIFS(#REF!,$A5,#REF!,"N/A (4e)",#REF!,"Practice Test") -> #REF! | H5: =COUNTIFS(#REF!,$A5,#REF!,"N/A (4e)",#REF!,"Practice Test",#REF!,H$2) -> #REF! | I5: =COUNTIFS(#REF!,$A5,#REF!,"N/A (4e)",#REF!,"Practice Test",#REF!,I$2) -> #REF! | J5: =COUNTIFS(#REF!,$A5,#REF!,"N/A (4e)",#REF!,"Practice Test",#REF!,J$2) -> #REF! | K5: =COUNTIFS(#REF!,$A5,#REF!,"N/A (4e)",#REF!,"Practice Test",#REF!,K$2) -> #REF! | L5: =G5-SUM(H5:K5) -> #REF! | M5: =COUNTIFS(#REF!,$A5,#REF!,"<>N/A (4e)",#REF!,"Knowledge Check") -> #REF! | N5: =COUNTIFS(#REF!,$A5,#REF!,"Knowledge Check",#REF!,N$2) -> #REF! | O5: =COUNTIFS(#REF!,$A5,#REF!,"Knowledge Check",#REF!,O$2) -> #REF! | P5: =COUNTIFS(#REF!,$A5,#REF!,"Knowledge Check",#REF!,P$2) -> #REF! | Q5: =COUNTIFS(#REF!,$A5,#REF!,"Knowledge Check",#REF!,Q$2) -> #REF! | R5: =M5-SUM(N5:Q5) -> #REF! | X5: =G5-F5 -> #REF!
A6: Gastrointestinal System | F6: =SUM(C6:E6) -> 0 | G6: =COUNTIFS(#REF!,$A6,#REF!,"N/A (4e)",#REF!,"Practice Test") -> #REF! | H6: =COUNTIFS(#REF!,$A6,#REF!,"N/A (4e)",#REF!,"Practice Test",#REF!,H$2) -> #REF! | I6: =COUNTIFS(#REF!,$A6,#REF!,"N/A (4e)",#REF!,"Practice Test",#REF!,I$2) -> #REF! | J6: =COUNTIFS(#REF!,$A6,#REF!,"N/A (4e)",#REF!,"Practice Test",#REF!,J$2) -> #REF! | K6: =COUNTIFS(#REF!,$A6,#REF!,"N/A (4e)",#REF!,"Practice Test",#REF!,K$2) -> #REF! | L6: =G6-SUM(H6:K6) -> #REF! | M6: =COUNTIFS(#REF!,$A6,#REF!,"<>N/A (4e)",#REF!,"Knowledge Check") -> #REF! | N6: =COUNTIFS(#REF!,$A6,#REF!,"Knowledge Check",#REF!,N$2) -> #REF! | O6: =COUNTIFS(#REF!,$A6,#REF!,"Knowledge Check",#REF!,O$2) -> #REF! | P6: =COUNTIFS(#REF!,$A6,#REF!,"Knowledge Check",#REF!,P$2) -> #REF! | Q6: =COUNTIFS(#REF!,$A6,#REF!,"Knowledge Check",#REF!,Q$2) -> #REF! | R6: =M6-SUM(N6:Q6) -> #REF! | X6: =G6-F6 -> #REF!
A7: Genitourinary and Renal System | F7: =SUM(C7:E7) -> 0 | G7: =COUNTIFS(#REF!,$A7,#REF!,"N/A (4e)",#REF!,"Practice Test") -> #REF! | H7: =COUNTIFS(#REF!,$A7,#REF!,"N/A (4e)",#REF!,"Practice Test",#REF!,H$2) -> #REF! | I7: =COUNTIFS(#REF!,$A7,#REF!,"N/A (4e)",#REF!,"Practice Test",#REF!,I$2) -> #REF! | J7: =COUNTIFS(#REF!,$A7,#REF!,"N/A (4e)",#REF!,"Practice Test",#REF!,J$2) -> #REF! | K7: =COUNTIFS(#REF!,$A7,#REF!,"N/A (4e)",#REF!,"Practice Test",#REF!,K$2) -> #REF! | L7: =G7-SUM(H7:K7) -> #REF! | M7: =COUNTIFS(#REF!,$A7,#REF!,"<>N/A (4e)",#REF!,"Knowledge Check") -> #REF! | N7: =COUNTIFS(#REF!,$A7,#REF!,"Knowledge Check",#REF!,N$2) -> #REF! | O7: =COUNTIFS(#REF!,$A7,#REF!,"Knowledge Check",#REF!,O$2) -> #REF! | P7: =COUNTIFS(#REF!,$A7,#REF!,"Knowledge Check",#REF!,P$2) -> #REF! | Q7: =COUNTIFS(#REF!,$A7,#REF!,"Knowledge Check",#REF!,Q$2) -> #REF! | R7: =M7-SUM(N7:Q7) -> #REF! | X7: =G7-F7 -> #REF!
A8: Head, Eyes, Ears, Nose, and Throat | F8: =SUM(C8:E8) -> 0 | G8: =COUNTIFS(#REF!,$A8,#REF!,"N/A (4e)",#REF!,"Practice Test") -> #REF! | H8: =COUNTIFS(#REF!,$A8,#REF!,"N/A (4e)",#REF!,"Practice Test",#REF!,H$2) -> #REF! | I8: =COUNTIFS(#REF!,$A8,#REF!,"N/A (4e)",#REF!,"Practice Test",#REF!,I$2) -> #REF! | J8: =COUNTIFS(#REF!,$A8,#REF!,"N/A (4e)",#REF!,"Practice Test",#REF!,J$2) -> #REF! | K8: =COUNTIFS(#REF!,$A8,#REF!,"N/A (4e)",#REF!,"Practice Test",#REF!,K$2) -> #REF! | L8: =G8-SUM(H8:K8) -> #REF! | M8: =COUNTIFS(#REF!,$A8,#REF!,"<>N/A (4e)",#REF!,"Knowledge Check") -> #REF! | N8: =COUNTIFS(#REF!,$A8,#REF!,"Knowledge Check",#REF!,N$2) -> #REF! | O8: =COUNTIFS(#REF!,$A8,#REF!,"Knowledge Check",#REF!,O$2) -> #REF! | P8: =COUNTIFS(#REF!,$A8,#REF!,"Knowledge Check",#REF!,P$2) -> #REF! | Q8: =COUNTIFS(#REF!,$A8,#REF!,"Knowledge Check",#REF!,Q$2) -> #REF! | R8: =M8-SUM(N8:Q8) -> #REF! | X8: =G8-F8 -> #REF!
A9: Health Promotion, Screening, and Disease Prevention | F9: =SUM(C9:E9) -> 0 | G9: =COUNTIFS(#REF!,$A9,#REF!,"N/A (4e)",#REF!,"Practice Test") -> #REF! | H9: =COUNTIFS(#REF!,$A9,#REF!,"N/A (4e)",#REF!,"Practice Test",#REF!,H$2) -> #REF! | I9: =COUNTIFS(#REF!,$A9,#REF!,"N/A (4e)",#REF!,"Practice Test",#REF!,I$2) -> #REF! | J9: =COUNTIFS(#REF!,$A9,#REF!,"N/A (4e)",#REF!,"Practice Test",#REF!,J$2) -> #REF! | K9: =COUNTIFS(#REF!,$A9,#REF!,"N/A (4e)",#REF!,"Practice Test",#REF!,K$2) -> #REF! | L9: =G9-SUM(H9:K9) -> #REF! | M9: =COUNTIFS(#REF!,$A9,#REF!,"<>N/A (4e)",#REF!,"Knowledge Check") -> #REF! | N9: =COUNTIFS(#REF!,$A9,#REF!,"Knowledge Check",#REF!,N$2) -> #REF! | O9: =COUNTIFS(#REF!,$A9,#REF!,"Knowledge Check",#REF!,O$2) -> #REF! | P9: =COUNTIFS(#REF!,$A9,#REF!,"Knowledge Check",#REF!,P$2) -> #REF! | Q9: =COUNTIFS(#REF!,$A9,#REF!,"Knowledge Check",#REF!,Q$2) -> #REF! | R9: =M9-SUM(N9:Q9) -> #REF! | X9: =G9-F9 -> #REF!
A10: Hematopoietic System | F10: =SUM(C10:E10) -> 0 | G10: =COUNTIFS(#REF!,$A10,#REF!,"N/A (4e)",#REF!,"Practice Test") -> #REF! | H10: =COUNTIFS(#REF!,$A10,#REF!,"N/A (4e)",#REF!,"Practice Test",#REF!,H$2) -> #REF! | I10: =COUNTIFS(#REF!,$A10,#REF!,"N/A (4e)",#REF!,"Practice Test",#REF!,I$2) -> #REF! | J10: =COUNTIFS(#REF!,$A10,#REF!,"N/A (4e)",#REF!,"Practice Test",#REF!,J$2) -> #REF! | K10: =COUNTIFS(#REF!,$A10,#REF!,"N/A (4e)",#REF!,"Practice Test",#REF!,K$2) -> #REF! | L10: =G10-SUM(H10:K10) -> #REF! | M10: =COUNTIFS(#REF!,$A10,#REF!,"<>N/A (4e)",#REF!,"Knowledge Check") -> #REF! | N10: =COUNTIFS(#REF!,$A10,#REF!,"Knowledge Check",#REF!,N$2) -> #REF! | O10: =COUNTIFS(#REF!,$A10,#REF!,"Knowledge Check",#REF!,O$2) -> #REF! | P10: =COUNTIFS(#REF!,$A10,#REF!,"Knowledge Check",#REF!,P$2) -> #REF! | Q10: =COUNTIFS(#REF!,$A10,#REF!,"Knowledge Check",#REF!,Q$2) -> #REF! | R10: =M10-SUM(N10:Q10) -> #REF! | X10: =G10-F10 -> #REF!
A11: Integumentary System | F11: =SUM(C11:E11) -> 0 | G11: =COUNTIFS(#REF!,$A11,#REF!,"N/A (4e)",#REF!,"Practice Test") -> #REF! | H11: =COUNTIFS(#REF!,$A11,#REF!,"N/A (4e)",#REF!,"Practice Test",#REF!,H$2) -> #REF! | I11: =COUNTIFS(#REF!,$A11,#REF!,"N/A (4e)",#REF!,"Practice Test",#REF!,I$2) -> #REF! | J11: =COUNTIFS(#REF!,$A11,#REF!,"N/A (4e)",#REF!,"Practice Test",#REF!,J$2) -> #REF! | K11: =COUNTIFS(#REF!,$A11,#REF!,"N/A (4e)",#REF!,"Practice Test",#REF!,K$2) -> #REF! | L11: =G11-SUM(H11:K11) -> #REF! | M11: =COUNTIFS(#REF!,$A11,#REF!,"<>N/A (4e)",#REF!,"Knowledge Check") -> #REF! | N11: =COUNTIFS(#REF!,$A11,#REF!,"Knowledge Check",#REF!,N$2) -> #REF! | O11: =COUNTIFS(#REF!,$A11,#REF!,"Knowledge Check",#REF!,O$2) -> #REF! | P11: =COUNTIFS(#REF!,$A11,#REF!,"Knowledge Check",#REF!,P$2) -> #REF! | Q11: =COUNTIFS(#REF!,$A11,#REF!,"Knowledge Check",#REF!,Q$2) -> #REF! | R11: =M11-SUM(N11:Q11) -> #REF! | X11: =G11-F11 -> #REF!
A12: Musculoskeletal System | F12: =SUM(C12:E12) -> 0 | G12: =COUNTIFS(#REF!,$A12,#REF!,"N/A (4e)",#REF!,"Practice Test") -> #REF! | H12: =COUNTIFS(#REF!,$A12,#REF!,"N/A (4e)",#REF!,"Practice Test",#REF!,H$2) -> #REF! | I12: =COUNTIFS(#REF!,$A12,#REF!,"N/A (4e)",#REF!,"Practice Test",#REF!,I$2) -> #REF! | J12: =COUNTIFS(#REF!,$A12,#REF!,"N/A (4e)",#REF!,"Practice Test",#REF!,J$2) -> #REF! | K12: =COUNTIFS(#REF!,$A12,#REF!,"N/A (4e)",#REF!,"Practice Test",#REF!,K$2) -> #REF! | L12: =G12-SUM(H12:K12) -> #REF! | M12: =COUNTIFS(#REF!,$A12,#REF!,"<>N/A (4e)",#REF!,"Knowledge Check") -> #REF! | N12: =COUNTIFS(#REF!,$A12,#REF!,"Knowledge Check",#REF!,N$2) -> #REF! | O12: =COUNTIFS(#REF!,$A12,#REF!,"Knowledge Check",#REF!,O$2) -> #REF! | P12: =COUNTIFS(#REF!,$A12,#REF!,"Knowledge Check",#REF!,P$2) -> #REF! | Q12: =COUNTIFS(#REF!,$A12,#REF!,"Knowledge Check",#REF!,Q$2) -> #REF! | R12: =M12-SUM(N12:Q12) -> #REF! | X12: =G12-F12 -> #REF!
A13: Nervous System | F13: =SUM(C13:E13) -> 0 | G13: =COUNTIFS(#REF!,$A13,#REF!,"N/A (4e)",#REF!,"Practice Test") -> #REF! | H13: =COUNTIFS(#REF!,$A13,#REF!,"N/A (4e)",#REF!,"Practice Test",#REF!,H$2) -> #REF! | I13: =COUNTIFS(#REF!,$A13,#REF!,"N/A (4e)",#REF!,"Practice Test",#REF!,I$2) -> #REF! | J13: =COUNTIFS(#REF!,$A13,#REF!,"N/A (4e)",#REF!,"Practice Test",#REF!,J$2) -> #REF! | K13: =COUNTIFS(#REF!,$A13,#REF!,"N/A (4e)",#REF!,"Practice Test",#REF!,K$2) -> #REF! | L13: =G13-SUM(H13:K13) -> #REF! | M13: =COUNTIFS(#REF!,$A13,#REF!,"<>N/A (4e)",#REF!,"Knowledge Check") -> #REF! | N13: =COUNTIFS(#REF!,$A13,#REF!,"Knowledge Check",#REF!,N$2) -> #REF! | O13: =COUNTIFS(#REF!,$A13,#REF!,"Knowledge Check",#REF!,O$2) -> #REF! | P13: =COUNTIFS(#REF!,$A13,#REF!,"Knowledge Check",#REF!,P$2) -> #REF! | Q13: =COUNTIFS(#REF!,$A13,#REF!,"Knowledge Check",#REF!,Q$2) -> #REF! | R13: =M13-SUM(N13:Q13) -> #REF! | X13: =G13-F13 -> #REF!
A14: Pharmacology | F14: =SUM(C14:E14) -> 0 | G14: =COUNTIFS(#REF!,$A14,#REF!,"N/A (4e)",#REF!,"Practice Test") -> #REF! | H14: =COUNTIFS(#REF!,$A14,#REF!,"N/A (4e)",#REF!,"Practice Test",#REF!,H$2) -> #REF! | I14: =COUNTIFS(#REF!,$A14,#REF!,"N/A (4e)",#REF!,"Practice Test",#REF!,I$2) -> #REF! | J14: =COUNTIFS(#REF!,$A14,#REF!,"N/A (4e)",#REF!,"Practice Test",#REF!,J$2) -> #REF! | K14: =COUNTIFS(#REF!,$A14,#REF!,"N/A (4e)",#REF!,"Practice Test",#REF!,K$2) -> #REF! | L14: =G14-SUM(H14:K14) -> #REF! | M14: =COUNTIFS(#REF!,$A14,#REF!,"<>N/A (4e)",#REF!,"Knowledge Check") -> #REF! | N14: =COUNTIFS(#REF!,$A14,#REF!,"Knowledge Check",#REF!,N$2) -> #REF! | O14: =COUNTIFS(#REF!,$A14,#REF!,"Knowledge Check",#REF!,O$2) -> #REF! | P14: =COUNTIFS(#REF!,$A14,#REF!,"Knowledge Check",#REF!,P$2) -> #REF! | Q14: =COUNTIFS(#REF!,$A14,#REF!,"Knowledge Check",#REF!,Q$2) -> #REF! | R14: =M14-SUM(N14:Q14) -> #REF! | X14: =G14-F14 -> #REF!
A15: Professional Role | F15: =SUM(C15:E15) -> 0 | G15: =COUNTIFS(#REF!,$A15,#REF!,"N/A (4e)",#REF!,"Practice Test") -> #REF! | H15: =COUNTIFS(#REF!,$A15,#REF!,"N/A (4e)",#REF!,"Practice Test",#REF!,H$2) -> #REF! | I15: =COUNTIFS(#REF!,$A15,#REF!,"N/A (4e)",#REF!,"Practice Test",#REF!,I$2) -> #REF! | J15: =COUNTIFS(#REF!,$A15,#REF!,"N/A (4e)",#REF!,"Practice Test",#REF!,J$2) -> #REF! | K15: =COUNTIFS(#REF!,$A15,#REF!,"N/A (4e)",#REF!,"Practice Test",#REF!,K$2) -> #REF! | L15: =G15-SUM(H15:K15) -> #REF! | M15: =COUNTIFS(#REF!,$A15,#REF!,"<>N/A (4e)",#REF!,"Knowledge Check") -> #REF! | N15: =COUNTIFS(#REF!,$A15,#REF!,"Knowledge Check",#REF!,N$2) -> #REF! | O15: =COUNTIFS(#REF!,$A15,#REF!,"Knowledge Check",#REF!,O$2) -> #REF! | P15: =COUNTIFS(#REF!,$A15,#REF!,"Knowledge Check",#REF!,P$2) -> #REF! | Q15: =COUNTIFS(#REF!,$A15,#REF!,"Knowledge Check",#REF!,Q$2) -> #REF! | R15: =M15-SUM(N15:Q15) -> #REF! | X15: =G15-F15 -> #REF!
A16: Psychiatric-Mental Health | F16: =SUM(C16:E16) -> 0 | G16: =COUNTIFS(#REF!,$A16,#REF!,"N/A (4e)",#REF!,"Practice Test") -> #REF! | H16: =COUNTIFS(#REF!,$A16,#REF!,"N/A (4e)",#REF!,"Practice Test",#REF!,H$2) -> #REF! | I16: =COUNTIFS(#REF!,$A16,#REF!,"N/A (4e)",#REF!,"Practice Test",#REF!,I$2) -> #REF! | J16: =COUNTIFS(#REF!,$A16,#REF!,"N/A (4e)",#REF!,"Practice Test",#REF!,J$2) -> #REF! | K16: =COUNTIFS(#REF!,$A16,#REF!,"N/A (4e)",#REF!,"Practice Test",#REF!,K$2) -> #REF! | L16: =G16-SUM(H16:K16) -> #REF! | M16: =COUNTIFS(#REF!,$A16,#REF!,"<>N/A (4e)",#REF!,"Knowledge Check") -> #REF! | N16: =COUNTIFS(#REF!,$A16,#REF!,"Knowledge Check",#REF!,N$2) -> #REF! | O16: =COUNTIFS(#REF!,$A16,#REF!,"Knowledge Check",#REF!,O$2) -> #REF! | P16: =COUNTIFS(#REF!,$A16,#REF!,"Knowledge Check",#REF!,P$2) -> #REF! | Q16: =COUNTIFS(#REF!,$A16,#REF!,"Knowledge Check",#REF!,Q$2) -> #REF! | R16: =M16-SUM(N16:Q16) -> #REF! | X16: =G16-F16 -> #REF!
... A18: Respiratory System | F18: =SUM(C18:E18) -> 0 | G18: =COUNTIFS(#REF!,$A18,#REF!,"N/A (4e)",#REF!,"Practice Test") -> #REF! | H18: =COUNTIFS(#REF!,$A18,#REF!,"N/A (4e)",#REF!,"Practice Test",#REF!,H$2) -> #REF! | I18: =COUNTIFS(#REF!,$A18,#REF!,"N/A (4e)",#REF!,"Practice Test",#REF!,I$2) -> #REF! | J18: =COUNTIFS(#REF!,$A18,#REF!,"N/A (4e)",#REF!,"Practice Test",#REF!,J$2) -> #REF! | K18: =COUNTIFS(#REF!,$A18,#REF!,"N/A (4e)",#REF!,"Practice Test",#REF!,K$2) -> #REF! | L18: =G18-SUM(H18:K18) -> #REF! | M18: =COUNTIFS(#REF!,$A18,#REF!,"<>N/A (4e)",#REF!,"Knowledge Check") -> #REF! | N18: =COUNTIFS(#REF!,$A18,#REF!,"Knowledge Check",#REF!,N$2) -> #REF! | O18: =COUNTIFS(#REF!,$A18,#REF!,"Knowledge Check",#REF!,O$2) -> #REF! | P18: =COUNTIFS(#REF!,$A18,#REF!,"Knowledge Check",#REF!,P$2) -> #REF! | Q18: =COUNTIFS(#REF!,$A18,#REF!,"Knowledge Check",#REF!,Q$2) -> #REF! | R18: =M18-SUM(N18:Q18) -> #REF! | X18: =G18-F18 -> #REF!

Sheet Writing assignments
E1: All SMEs | J1: Remaining to assign | K1: GPT_DA | M1: Louise Comer | W1: Kathleen Andresen | AG1: Crystal Lane-Tillerson | AQ1: Kris Louque - REASSIGN | AV1: Christie Cavallo | BF1: Nan Pritchard | BP1: Portia Thomas | BZ1: SME 1
B2: Domain | C2: Subdomain | E2: Recall (Planned) | F2: Application (Planned) | G2: Reasoning (Planned) | H2: Total (Planned) | J2: =SUM(J5:J98) -> -1 | L2: Total | N2: Assigned total | O2: Assigned Recall | P2: Assigned App. | Q2: Assigned Analysis | S2: Actual total | T2: Actual Recall | U2: Actual App. | V2: Actual Analysis | X2: Assigned total | Y2: Assigned Recall | Z2: Assigned App. | AA2: Assigned Analysis | AC2: Actual total | AD2: Actual Recall | AE2: Actual App. | AF2: Actual Analysis | AH2: Assigned total | AI2: Assigned Recall | AJ2: Assigned App. | AK2: Assigned Analysis | AM2: Actual total | AN2: Actual Recall | AO2: Actual App. | AP2: Actual Analysis | AR2: Total | AS2: Recall | AT2: App. | AU2: Analysis | AW2: Assigned total | AX2: Assigned Recall | AY2: Assigned App. | AZ2: Assigned Analysis | BB2: Actual total | BC2: Actual Recall | BD2: Actual App. | BE2: Actual Analysis | BG2: Assigned total | BH2: Assigned Recall | BI2: Assigned App. | BJ2: Assigned Analysis | BL2: Actual total | BM2: Actual Recall | BN2: Actual App. | BO2: Actual Analysis | BQ2: Assigned total | BR2: Assigned Recall | BS2: Assigned App. | BT2: Assigned Analysis | BV2: Actual total | BW2: Actual Recall | BX2: Actual App. | BY2: Actual Analysis
E3: =SUM(E5:E98) -> 65 | F3: =SUM(F5:F98) -> 300 | G3: =SUM(G5:G98) -> 135 | H3: =SUM(E3:G3) -> 500 | L3: =SUM(L5:L98) -> 73 | N3: =SUM(N5:N98) -> 50 | O3: =SUM(O5:O98) -> 1 | P3: =SUM(P5:P98) -> 41 | Q3: =SUM(Q5:Q98) -> 8 | X3: =SUM(X5:X98) -> 82 | Y3: =SUM(Y5:Y98) -> 13 | Z3: =SUM(Z5:Z98) -> 45 | AA3: =SUM(AA5:AA98) -> 24 | AH3: =SUM(AH5:AH98) -> 82 | AI3: =SUM(AI5:AI98) -> 11 | AJ3: =SUM(AJ5:AJ98) -> 44 | AK3: =SUM(AK5:AK98) -> 27 | AR3: =SUM(AR5:AR98) -> 32 | AS3: =SUM(AS5:AS98) -> 5 | AT3: =SUM(AT5:AT98) -> 18 | AU3: =SUM(AU5:AU98) -> 9 | AW3: =SUM(AW5:AW98) -> 50 | AX3: =SUM(AX5:AX98) -> 7 | AY3: =SUM(AY5:AY98) -> 26 | AZ3: =SUM(AZ5:AZ98) -> 17 | BG3: =SUM(BG5:BG98) -> 82 | BH3: =SUM(BH5:BH98) -> 11 | BI3: =SUM(BI5:BI98) -> 47 | BJ3: =SUM(BJ5:BJ98) -> 24 | BQ3: =SUM(BQ5:BQ98) -> 82 | BR3: =SUM(BR5:BR98) -> 11 | BS3: =SUM(BS5:BS98) -> 45 | BT3: =SUM(BT5:BT98) -> 26
B5: Facilitate_Learning | C5: Implement a variety of active teaching and learning strategies appropriate to content/concepts | E5: 1 | F5: 6 | G5: 3 | H5: =SUM(E5:G5) -> 10 | J5: =H5-SUM(N5,X5,AH5,AW5,BG5,BQ5,L5,CA5) -> 0 | K5: X | L5: 1 | M5: X | N5: =SUM(O5:Q5) -> 1 | P5: 1 | S5: =SUM(T5:V5) -> #REF! | T5: =COUNTIFS('SPC-CPN_Q&A'!#REF!,M$1,'SPC-CPN_Q&A'!#REF!,'Writing assignments'!$C5,'SPC-CPN_Q&A'!$O:$O,"Recall") -> #REF! | U5: =COUNTIFS('SPC-CPN_Q&A'!#REF!,M$1,'SPC-CPN_Q&A'!#REF!,'Writing assignments'!$C5,'SPC-CPN_Q&A'!$O:$O,"Application") -> #REF! | V5: =COUNTIFS('SPC-CPN_Q&A'!#REF!,M$1,'SPC-CPN_Q&A'!#REF!,'Writing assignments'!$C5,'SPC-CPN_Q&A'!$O:$O,"Analysis") -> #REF! | W5: X | X5: 2 | Y5: 1 | Z5: 1 | AA5: 0 | AC5: =SUM(AD5:AF5) -> #REF! | AD5: =COUNTIFS('SPC-CPN_Q&A'!#REF!,W$1,'SPC-CPN_Q&A'!#REF!,'Writing assignments'!$C5,'SPC-CPN_Q&A'!$O:$O,"Recall") -> #REF! | AE5: =COUNTIFS('SPC-CPN_Q&A'!#REF!,W$1,'SPC-CPN_Q&A'!#REF!,'Writing assignments'!$C5,'SPC-CPN_Q&A'!$O:$O,"Application") -> #REF! | AF5: =COUNTIFS('SPC-CPN_Q&A'!#REF!,W$1,'SPC-CPN_Q&A'!#REF!,'Writing assignments'!$C5,'SPC-CPN_Q&A'!$O:$O,"Analysis") -> #REF! | AG5: X | AH5: 2 | AI5: 0 | AJ5: 1 | AK5: 1 | AM5: =SUM(AN5:AP5) -> #REF! | AN5: =COUNTIFS('SPC-CPN_Q&A'!#REF!,AG$1,'SPC-CPN_Q&A'!#REF!,'Writing assignments'!$C5,'SPC-CPN_Q&A'!$O:$O,"Recall") -> #REF! | AO5: =COUNTIFS('SPC-CPN_Q&A'!#REF!,AG$1,'SPC-CPN_Q&A'!#REF!,'Writing assignments'!$C5,'SPC-CPN_Q&A'!$O:$O,"Application") -> #REF! | AP5: =COUNTIFS('SPC-CPN_Q&A'!#REF!,AG$1,'SPC-CPN_Q&A'!#REF!,'Writing assignments'!$C5,'SPC-CPN_Q&A'!$O:$O,"Analysis") -> #REF! | AV5: X | AW5: 2 | AX5: 0 | AY5: 1 | AZ5: 1 | BB5: =SUM(BC5:BE5) -> #REF! | BC5: =COUNTIFS('SPC-CPN_Q&A'!#REF!,AV$1,'SPC-CPN_Q&A'!#REF!,'Writing assignments'!$C5,'SPC-CPN_Q&A'!$O:$O,"Recall") -> #REF! | BD5: =COUNTIFS('SPC-CPN_Q&A'!#REF!,AV$1,'SPC-CPN_Q&A'!#REF!,'Writing assignments'!$C5,'SPC-CPN_Q&A'!$O:$O,"Application") -> #REF! | BE5: =COUNTIFS('SPC-CPN_Q&A'!#REF!,AV$1,'SPC-CPN_Q&A'!#REF!,'Writing assignments'!$C5,'SPC-CPN_Q&A'!$O:$O,"Analysis") -> #REF! | BF5: X | BG5: 2 | BI5: 1 | BJ5: 1 | BL5: =SUM(BM5:BO5) -> #REF! | BM5: =COUNTIFS('SPC-CPN_Q&A'!#REF!,BF$1,'SPC-CPN_Q&A'!#REF!,'Writing assignments'!$C5,'SPC-CPN_Q&A'!$O:$O,"Recall") -> #REF! | BN5: =COUNTIFS('SPC-CPN_Q&A'!#REF!,BF$1,'SPC-CPN_Q&A'!#REF!,'Writing assignments'!$C5,'SPC-CPN_Q&A'!$O:$O,"Application") -> #REF! | BO5: =COUNTIFS('SPC-CPN_Q&A'!#REF!,BF$1,'SPC-CPN_Q&A'!#REF!,'Writing assignments'!$C5,'SPC-CPN_Q&A'!$O:$O,"Analysis") -> #REF! | BV5: =SUM(BW5:BY5) -> #REF! | BW5: =COUNTIFS('SPC-CPN_Q&A'!#REF!,BP$1,'SPC-CPN_Q&A'!#REF!,'Writing assignments'!$C5,'SPC-CPN_Q&A'!$O:$O,"Recall") -> #REF! | BX5: =COUNTIFS('SPC-CPN_Q&A'!#REF!,BP$1,'SPC-CPN_Q&A'!#REF!,'Writing assignments'!$C5,'SPC-CPN_Q&A'!$O:$O,"Application") -> #REF! | BY5: =COUNTIFS('SPC-CPN_Q&A'!#REF!,BP$1,'SPC-CPN_Q&A'!#REF!,'Writing assignments'!$C5,'SPC-CPN_Q&A'!$O:$O,"Analysis") -> #REF! | CA5: 0
B6: Facilitate_Learning | C6: Implement a variety of active teaching and learning strategies appropriate to setting | E6: 1 | F6: 6 | G6: 3 | H6: =SUM(E6:G6) -> 10 | J6: =H6-SUM(N6,X6,AH6,AW6,BG6,BQ6,L6,CA6) -> 0 | L6: 0 | M6: X | N6: =SUM(O6:Q6) -> 3 | P6: 2 | Q6: 1 | S6: =SUM(T6:V6) -> #REF! | T6: =COUNTIFS('SPC-CPN_Q&A'!#REF!,M$1,'SPC-CPN_Q&A'!#REF!,'Writing assignments'!$C6,'SPC-CPN_Q&A'!$O:$O,"Recall") -> #REF! | U6: =COUNTIFS('SPC-CPN_Q&A'!#REF!,M$1,'SPC-CPN_Q&A'!#REF!,'Writing assignments'!$C6,'SPC-CPN_Q&A'!$O:$O,"Application") -> #REF! | V6: =COUNTIFS('SPC-CPN_Q&A'!#REF!,M$1,'SPC-CPN_Q&A'!#REF!,'Writing assignments'!$C6,'SPC-CPN_Q&A'!$O:$O,"Analysis") -> #REF! | AC6: =SUM(AD6:AF6) -> #REF! | AD6: =COUNTIFS('SPC-CPN_Q&A'!#REF!,W$1,'SPC-CPN_Q&A'!#REF!,'Writing assignments'!$C6,'SPC-CPN_Q&A'!$O:$O,"Recall") -> #REF! | AE6: =COUNTIFS('SPC-CPN_Q&A'!#REF!,W$1,'SPC-CPN_Q&A'!#REF!,'Writing assignments'!$C6,'SPC-CPN_Q&A'!$O:$O,"Application") -> #REF! | AF6: =COUNTIFS('SPC-CPN_Q&A'!#REF!,W$1,'SPC-CPN_Q&A'!#REF!,'Writing assignments'!$C6,'SPC-CPN_Q&A'!$O:$O,"Analysis") -> #REF! | AM6: =SUM(AN6:AP6) -> #REF! | AN6: =COUNTIFS('SPC-CPN_Q&A'!#REF!,AG$1,'SPC-CPN_Q&A'!#REF!,'Writing assignments'!$C6,'SPC-CPN_Q&A'!$O:$O,"Recall") -> #REF! | AO6: =COUNTIFS('SPC-CPN_Q&A'!#REF!,AG$1,'SPC-CPN_Q&A'!#REF!,'Writing assignments'!$C6,'SPC-CPN_Q&A'!$O:$O,"Application") -> #REF! | AP6: =COUNTIFS('SPC-CPN_Q&A'!#REF!,AG$1,'SPC-CPN_Q&A'!#REF!,'Writing assignments'!$C6,'SPC-CPN_Q&A'!$O:$O,"Analysis") -> #REF! | AV6: X | AW6: 3 | AX6: 1 | AY6: 1 | AZ6: 1 | BB6: =SUM(BC6:BE6) -> #REF! | BC6: =COUNTIFS('SPC-CPN_Q&A'!#REF!,AV$1,'SPC-CPN_Q&A'!#REF!,'Writing assignments'!$C6,'SPC-CPN_Q&A'!$O:$O,"Recall") -> #REF! | BD6: =COUNTIFS('SPC-CPN_Q&A'!#REF!,AV$1,'SPC-CPN_Q&A'!#REF!,'Writing assignments'!$C6,'SPC-CPN_Q&A'!$O:$O,"Application") -> #REF! | BE6: =COUNTIFS('SPC-CPN_Q&A'!#REF!,AV$1,'SPC-CPN_Q&A'!#REF!,'Writing assignments'!$C6,'SPC-CPN_Q&A'!$O:$O,"Analysis") -> #REF! | BF6: X | BG6: 2 | BH6: 0 | BI6: 1 | BJ6: 1 | BL6: =SUM(BM6:BO6) -> #REF! | BM6: =COUNTIFS('SPC-CPN_Q&A'!#REF!,BF$1,'SPC-CPN_Q&A'!#REF!,'Writing assignments'!$C6,'SPC-CPN_Q&A'!$O:$O,"Recall") -> #REF! | BN6: =COUNTIFS('SPC-CPN_Q&A'!#REF!,BF$1,'SPC-CPN_Q&A'!#REF!,'Writing assignments'!$C6,'SPC-CPN_Q&A'!$O:$O,"Application") -> #REF! | BO6: =COUNTIFS('SPC-CPN_Q&A'!#REF!,BF$1,'SPC-CPN_Q&A'!#REF!,'Writing assignments'!$C6,'SPC-CPN_Q&A'!$O:$O,"Analysis") -> #REF! | BP6: X | BQ6: 2 | BR6: 0 | BS6: 1 | BT6: 1 | BV6: =SUM(BW6:BY6) -> #REF! | BW6: =COUNTIFS('SPC-CPN_Q&A'!#REF!,BP$1,'SPC-CPN_Q&A'!#REF!,'Writing assignments'!$C6,'SPC-CPN_Q&A'!$O:$O,"Recall") -> #REF! | BX6: =COUNTIFS('SPC-CPN_Q&A'!#REF!,BP$1,'SPC-CPN_Q&A'!#REF!,'Writing assignments'!$C6,'SPC-CPN_Q&A'!$O:$O,"Application") -> #REF! | BY6: =COUNTIFS('SPC-CPN_Q&A'!#REF!,BP$1,'SPC-CPN_Q&A'!#REF!,'Writing assignments'!$C6,'SPC-CPN_Q&A'!$O:$O,"Analysis") -> #REF! | CA6: 0
B7: Facilitate_Learning | C7: Implement a variety of active teaching and learning strategies appropriate to learner attributes and needs | E7: 1 | F7: 6 | G7: 3 | H7: =SUM(E7:G7) -> 10 | J7: =H7-SUM(N7,X7,AH7,AW7,BG7,BQ7,L7,CA7) -> 0 | K7: X | L7: 1 | N7: =SUM(O7:Q7) -> 0 | S7: =SUM(T7:V7) -> #REF! | T7: =COUNTIFS('SPC-CPN_Q&A'!#REF!,M$1,'SPC-CPN_Q&A'!#REF!,'Writing assignments'!$C7,'SPC-CPN_Q&A'!$O:$O,"Recall") -> #REF! | U7: =COUNTIFS('SPC-CPN_Q&A'!#REF!,M$1,'SPC-CPN_Q&A'!#REF!,'Writing assignments'!$C7,'SPC-CPN_Q&A'!$O:$O,"Application") -> #REF! | V7: =COUNTIFS('SPC-CPN_Q&A'!#REF!,M$1,'SPC-CPN_Q&A'!#REF!,'Writing assignments'!$C7,'SPC-CPN_Q&A'!$O:$O,"Analysis") -> #REF! | W7: X | X7: 3 | Y7: 0 | Z7: 2 | AA7: 1 | AC7: =SUM(AD7:AF7) -> #REF! | AD7: =COUNTIFS('SPC-CPN_Q&A'!#REF!,W$1,'SPC-CPN_Q&A'!#REF!,'Writing assignments'!$C7,'SPC-CPN_Q&A'!$O:$O,"Recall") -> #REF! | AE7: =COUNTIFS('SPC-CPN_Q&A'!#REF!,W$1,'SPC-CPN_Q&A'!#REF!,'Writing assignments'!$C7,'SPC-CPN_Q&A'!$O:$O,"Application") -> #REF! | AF7: =COUNTIFS('SPC-CPN_Q&A'!#REF!,W$1,'SPC-CPN_Q&A'!#REF!,'Writing assignments'!$C7,'SPC-CPN_Q&A'!$O:$O,"Analysis") -> #REF! | AG7: X | AH7: 3 | AI7: 1 | AJ7: 1 | AK7: 1 | AM7: =SUM(AN7:AP7) -> #REF! | AN7: =COUNTIFS('SPC-CPN_Q&A'!#REF!,AG$1,'SPC-CPN_Q&A'!#REF!,'Writing assignments'!$C7,'SPC-CPN_Q&A'!$O:$O,"Recall") -> #REF! | AO7: =COUNTIFS('SPC-CPN_Q&A'!#REF!,AG$1,'SPC-CPN_Q&A'!#REF!,'Writing assignments'!$C7,'SPC-CPN_Q&A'!$O:$O,"Application") -> #REF! | AP7: =COUNTIFS('SPC-CPN_Q&A'!#REF!,AG$1,'SPC-CPN_Q&A'!#REF!,'Writing assignments'!$C7,'SPC-CPN_Q&A'!$O:$O,"Analysis") -> #REF! | BB7: =SUM(BC7:BE7) -> #REF! | BC7: =COUNTIFS('SPC-CPN_Q&A'!#REF!,AV$1,'SPC-CPN_Q&A'!#REF!,'Writing assignments'!$C7,'SPC-CPN_Q&A'!$O:$O,"Recall") -> #REF! | BD7: =COUNTIFS('SPC-CPN_Q&A'!#REF!,AV$1,'SPC-CPN_Q&A'!#REF!,'Writing assignments'!$C7,'SPC-CPN_Q&A'!$O:$O,"Application") -> #REF! | BE7: =COUNTIFS('SPC-CPN_Q&A'!#REF!,AV$1,'SPC-CPN_Q&A'!#REF!,'Writing assignments'!$C7,'SPC-CPN_Q&A'!$O:$O,"Analysis") -> #REF! | BF7: X | BG7: 3 | BH7: 0 | BI7: 2 | BJ7: 1 | BL7: =SUM(BM7:BO7) -> #REF! | BM7: =COUNTIFS('SPC-CPN_Q&A'!#REF!,BF$1,'SPC-CPN_Q&A'!#REF!,'Writing assignments'!$C7,'SPC-CPN_Q&A'!$O:$O,"Recall") -> #REF! | BN7: =COUNTIFS('SPC-CPN_Q&A'!#REF!,BF$1,'SPC-CPN_Q&A'!#REF!,'Writing assignments'!$C7,'SPC-CPN_Q&A'!$O:$O,"Application") -> #REF! | BO7: =COUNTIFS('SPC-CPN_Q&A'!#REF!,BF$1,'SPC-CPN_Q&A'!#REF!,'Writing assignments'!$C7,'SPC-CPN_Q&A'!$O:$O,"Analysis") -> #REF! | BV7: =SUM(BW7:BY7) -> #REF! | BW7: =COUNTIFS('SPC-CPN_Q&A'!#REF!,BP$1,'SPC-CPN_Q&A'!#REF!,'Writing assignments'!$C7,'SPC-CPN_Q&A'!$O:$O,"Recall") -> #REF! | BX7: =COUNTIFS('SPC-CPN_Q&A'!#REF!,BP$1,'SPC-CPN_Q&A'!#REF!,'Writing assignments'!$C7,'SPC-CPN_Q&A'!$O:$O,"Application") -> #REF! | BY7: =COUNTIFS('SPC-CPN_Q&A'!#REF!,BP$1,'SPC-CPN_Q&A'!#REF!,'Writing assignments'!$C7,'SPC-CPN_Q&A'!$O:$O,"Analysis") -> #REF! | CA7: 0
B8: Facilitate_Learning | C8: Implement a variety of active teaching and learning strategies appropriate to learner outcomes | E8: 1 | F8: 6 | G8: 3 | H8: =SUM(E8:G8) -> 10 | J8: =H8-SUM(N8,X8,AH8,AW8,BG8,BQ8,L8,CA8) -> 0 | L8: 0 | M8: X | N8: =SUM(O8:Q8) -> 1 | P8: 1 | S8: =SUM(T8:V8) -> #REF! | T8: =COUNTIFS('SPC-CPN_Q&A'!#REF!,M$1,'SPC-CPN_Q&A'!#REF!,'Writing assignments'!$C8,'SPC-CPN_Q&A'!$O:$O,"Recall") -> #REF! | U8: =COUNTIFS('SPC-CPN_Q&A'!#REF!,M$1,'SPC-CPN_Q&A'!#REF!,'Writing assignments'!$C8,'SPC-CPN_Q&A'!$O:$O,"Application") -> #REF! | V8: =COUNTIFS('SPC-CPN_Q&A'!#REF!,M$1,'SPC-CPN_Q&A'!#REF!,'Writing assignments'!$C8,'SPC-CPN_Q&A'!$O:$O,"Analysis") -> #REF! | AC8: =SUM(AD8:AF8) -> #REF! | AD8: =COUNTIFS('SPC-CPN_Q&A'!#REF!,W$1,'SPC-CPN_Q&A'!#REF!,'Writing assignments'!$C8,'SPC-CPN_Q&A'!$O:$O,"Recall") -> #REF! | AE8: =COUNTIFS('SPC-CPN_Q&A'!#REF!,W$1,'SPC-CPN_Q&A'!#REF!,'Writing assignments'!$C8,'SPC-CPN_Q&A'!$O:$O,"Application") -> #REF! | AF8: =COUNTIFS('SPC-CPN_Q&A'!#REF!,W$1,'SPC-CPN_Q&A'!#REF!,'Writing assignments'!$C8,'SPC-CPN_Q&A'!$O:$O,"Analysis") -> #REF! | AM8: =SUM(AN8:AP8) -> #REF! | AN8: =COUNTIFS('SPC-CPN_Q&A'!#REF!,AG$1,'SPC-CPN_Q&A'!#REF!,'Writing assignments'!$C8,'SPC-CPN_Q&A'!$O:$O,"Recall") -> #REF! | AO8: =COUNTIFS('SPC-CPN_Q&A'!#REF!,AG$1,'SPC-CPN_Q&A'!#REF!,'Writing assignments'!$C8,'SPC-CPN_Q&A'!$O:$O,"Application") -> #REF! | AP8: =COUNTIFS('SPC-CPN_Q&A'!#REF!,AG$1,'SPC-CPN_Q&A'!#REF!,'Writing assignments'!$C8,'SPC-CPN_Q&A'!$O:$O,"Analysis") -> #REF! | AV8: X | AW8: 3 | AX8: 0 | AY8: 2 | AZ8: 1 | BB8: =SUM(BC8:BE8) -> #REF! | BC8: =COUNTIFS('SPC-CPN_Q&A'!#REF!,AV$1,'SPC-CPN_Q&A'!#REF!,'Writing assignments'!$C8,'SPC-CPN_Q&A'!$O:$O,"Recall") -> #REF! | BD8: =COUNTIFS('SPC-CPN_Q&A'!#REF!,AV$1,'SPC-CPN_Q&A'!#REF!,'Writing assignments'!$C8,'SPC-CPN_Q&A'!$O:$O,"Application") -> #REF! | BE8: =COUNTIFS('SPC-CPN_Q&A'!#REF!,AV$1,'SPC-CPN_Q&A'!#REF!,'Writing assignments'!$C8,'SPC-CPN_Q&A'!$O:$O,"Analysis") -> #REF! | BF8: X | BG8: 3 | BH8: 1 | BI8: 1 | BJ8: 1 | BL8: =SUM(BM8:BO8) -> #REF! | BM8: =COUNTIFS('SPC-CPN_Q&A'!#REF!,BF$1,'SPC-CPN_Q&A'!#REF!,'Writing assignments'!$C8,'SPC-CPN_Q&A'!$O:$O,"Recall") -> #REF! | BN8: =COUNTIFS('SPC-CPN_Q&A'!#REF!,BF$1,'SPC-CPN_Q&A'!#REF!,'Writing assignments'!$C8,'SPC-CPN_Q&A'!$O:$O,"Application") -> #REF! | BO8: =COUNTIFS('SPC-CPN_Q&A'!#REF!,BF$1,'SPC-CPN_Q&A'!#REF!,'Writing assignments'!$C8,'SPC-CPN_Q&A'!$O:$O,"Analysis") -> #REF! | BP8: X | BQ8: 3 | BR8: 0 | BS8: 2 | BT8: 1 | BV8: =SUM(BW8:BY8) -> #REF! | BW8: =COUNTIFS('SPC-CPN_Q&A'!#REF!,BP$1,'SPC-CPN_Q&A'!#REF!,'Writing assignments'!$C8,'SPC-CPN_Q&A'!$O:$O,"Recall") -> #REF! | BX8: =COUNTIFS('SPC-CPN_Q&A'!#REF!,BP$1,'SPC-CPN_Q&A'!#REF!,'Writing assignments'!$C8,'SPC-CPN_Q&A'!$O:$O,"Application") -> #REF! | BY8: =COUNTIFS('SPC-CPN_Q&A'!#REF!,BP$1,'SPC-CPN_Q&A'!#REF!,'Writing assignments'!$C8,'SPC-CPN_Q&A'!$O:$O,"Analysis") -> #REF! | CA8: 0
B9: Facilitate_Learning | C9: Implement a variety of active teaching and learning strategies appropriate to method of delivery | E9: 1 | F9: 6 | G9: 3 | H9: =SUM(E9:G9) -> 10 | J9: =H9-SUM(N9,X9,AH9,AW9,BG9,BQ9,L9,CA9) -> 0 | L9: 0 | N9: =SUM(O9:Q9) -> 0 | S9: =SUM(T9:V9) -> #REF! | T9: =COUNTIFS('SPC-CPN_Q&A'!#REF!,M$1,'SPC-CPN_Q&A'!#REF!,'Writing assignments'!$C9,'SPC-CPN_Q&A'!$O:$O,"Recall") -> #REF! | U9: =COUNTIFS('SPC-CPN_Q&A'!#REF!,M$1,'SPC-CPN_Q&A'!#REF!,'Writing assignments'!$C9,'SPC-CPN_Q&A'!$O:$O,"Application") -> #REF! | V9: =COUNTIFS('SPC-CPN_Q&A'!#REF!,M$1,'SPC-CPN_Q&A'!#REF!,'Writing assignments'!$C9,'SPC-CPN_Q&A'!$O:$O,"Analysis") -> #REF! | W9: X | X9: 4 | Y9: 1 | Z9: 2 | AA9: 1 | AC9: =SUM(AD9:AF9) -> #REF! | AD9: =COUNTIFS('SPC-CPN_Q&A'!#REF!,W$1,'SPC-CPN_Q&A'!#REF!,'Writing assignments'!$C9,'SPC-CPN_Q&A'!$O:$O,"Recall") -> #REF! | AE9: =COUNTIFS('SPC-CPN_Q&A'!#REF!,W$1,'SPC-CPN_Q&A'!#REF!,'Writing assignments'!$C9,'SPC-CPN_Q&A'!$O:$O,"Application") -> #REF! | AF9: =COUNTIFS('SPC-CPN_Q&A'!#REF!,W$1,'SPC-CPN_Q&A'!#REF!,'Writing assignments'!$C9,'SPC-CPN_Q&A'!$O:$O,"Analysis") -> #REF! | AG9: X | AH9: 3 | AI9: 0 | AJ9: 2 | AK9: 1 | AM9: =SUM(AN9:AP9) -> #REF! | AN9: =COUNTIFS('SPC-CPN_Q&A'!#REF!,AG$1,'SPC-CPN_Q&A'!#REF!,'Writing assignments'!$C9,'SPC-CPN_Q&A'!$O:$O,"Recall") -> #REF! | AO9: =COUNTIFS('SPC-CPN_Q&A'!#REF!,AG$1,'SPC-CPN_Q&A'!#REF!,'Writing assignments'!$C9,'SPC-CPN_Q&A'!$O:$O,"Application") -> #REF! | AP9: =COUNTIFS('SPC-CPN_Q&A'!#REF!,AG$1,'SPC-CPN_Q&A'!#REF!,'Writing assignments'!$C9,'SPC-CPN_Q&A'!$O:$O,"Analysis") -> #REF! | BB9: =SUM(BC9:BE9) -> #REF! | BC9: =COUNTIFS('SPC-CPN_Q&A'!#REF!,AV$1,'SPC-CPN_Q&A'!#REF!,'Writing assignments'!$C9,'SPC-CPN_Q&A'!$O:$O,"Recall") -> #REF! | BD9: =COUNTIFS('SPC-CPN_Q&A'!#REF!,AV$1,'SPC-CPN_Q&A'!#REF!,'Writing assignments'!$C9,'SPC-CPN_Q&A'!$O:$O,"Application") -> #REF! | BE9: =COUNTIFS('SPC-CPN_Q&A'!#REF!,AV$1,'SPC-CPN_Q&A'!#REF!,'Writing assignments'!$C9,'SPC-CPN_Q&A'!$O:$O,"Analysis") -> #REF! | BL9: =SUM(BM9:BO9) -> #REF! | BM9: =COUNTIFS('SPC-CPN_Q&A'!#REF!,BF$1,'SPC-CPN_Q&A'!#REF!,'Writing assignments'!$C9,'SPC-CPN_Q&A'!$O:$O,"Recall") -> #REF! | BN9: =COUNTIFS('SPC-CPN_Q&A'!#REF!,BF$1,'SPC-CPN_Q&A'!#REF!,'Writing assignments'!$C9,'SPC-CPN_Q&A'!$O:$O,"Application") -> #REF! | BO9: =COUNTIFS('SPC-CPN_Q&A'!#REF!,BF$1,'SPC-CPN_Q&A'!#REF!,'Writing assignments'!$C9,'SPC-CPN_Q&A'!$O:$O,"Analysis") -> #REF! | BP9: X | BQ9: 3 | BR9: 0 | BS9: 2 | BT9: 1 | BV9: =SUM(BW9:BY9) -> #REF! | BW9: =COUNTIFS('SPC-CPN_Q&A'!#REF!,BP$1,'SPC-CPN_Q&A'!#REF!,'Writing assignments'!$C9,'SPC-CPN_Q&A'!$O:$O,"Recall") -> #REF! | BX9: =COUNTIFS('SPC-CPN_Q&A'!#REF!,BP$1,'SPC-CPN_Q&A'!#REF!,'Writing assignments'!$C9,'SPC-CPN_Q&A'!$O:$O,"Application") -> #REF! | BY9: =COUNTIFS('SPC-CPN_Q&A'!#REF!,BP$1,'SPC-CPN_Q&A'!#REF!,'Writing assignments'!$C9,'SPC-CPN_Q&A'!$O:$O,"Analysis") -> #REF! | CA9: 0
B10: Facilitate_Learning | C10: Use teaching and learning strategies based on education theories | E10: 1 | F10: 6 | G10: 3 | H10: =SUM(E10:G10) -> 10 | J10: =H10-SUM(N10,X10,AH10,AW10,BG10,BQ10,L10,CA10) -> 0 | K10: X | L10: 1 | N10: =SUM(O10:Q10) -> 0 | S10: =SUM(T10:V10) -> #REF! | T10: =COUNTIFS('SPC-CPN_Q&A'!#REF!,M$1,'SPC-CPN_Q&A'!#REF!,'Writing assignments'!$C10,'SPC-CPN_Q&A'!$O:$O,"Recall") -> #REF! | U10: =COUNTIFS('SPC-CPN_Q&A'!#REF!,M$1,'SPC-CPN_Q&A'!#REF!,'Writing assignments'!$C10,'SPC-CPN_Q&A'!$O:$O,"Application") -> #REF! | V10: =COUNTIFS('SPC-CPN_Q&A'!#REF!,M$1,'SPC-CPN_Q&A'!#REF!,'Writing assignments'!$C10,'SPC-CPN_Q&A'!$O:$O,"Analysis") -> #REF! | W10: X | X10: 3 | Y10: 0 | Z10: 2 | AA10: 1 | AC10: =SUM(AD10:AF10) -> #REF! | AD10: =COUNTIFS('SPC-CPN_Q&A'!#REF!,W$1,'SPC-CPN_Q&A'!#REF!,'Writing assignments'!$C10,'SPC-CPN_Q&A'!$O:$O,"Recall") -> #REF! | AE10: =COUNTIFS('SPC-CPN_Q&A'!#REF!,W$1,'SPC-CPN_Q&A'!#REF!,'Writing assignments'!$C10,'SPC-CPN_Q&A'!$O:$O,"Application") -> #REF! | AF10: =COUNTIFS('SPC-CPN_Q&A'!#REF!,W$1,'SPC-CPN_Q&A'!#REF!,'Writing assignments'!$C10,'SPC-CPN_Q&A'!$O:$O,"Analysis") -> #REF! | AM10: =SUM(AN10:AP10) -> #REF! | AN10: =COUNTIFS('SPC-CPN_Q&A'!#REF!,AG$1,'SPC-CPN_Q&A'!#REF!,'Writing assignments'!$C10,'SPC-CPN_Q&A'!$O:$O,"Recall") -> #REF! | AO10: =COUNTIFS('SPC-CPN_Q&A'!#REF!,AG$1,'SPC-CPN_Q&A'!#REF!,'Writing assignments'!$C10,'SPC-CPN_Q&A'!$O:$O,"Application") -> #REF! | AP10: =COUNTIFS('SPC-CPN_Q&A'!#REF!,AG$1,'SPC-CPN_Q&A'!#REF!,'Writing assignments'!$C10,'SPC-CPN_Q&A'!$O:$O,"Analysis") -> #REF! | BB10: =SUM(BC10:BE10) -> #REF! | BC10: =COUNTIFS('SPC-CPN_Q&A'!#REF!,AV$1,'SPC-CPN_Q&A'!#REF!,'Writing assignments'!$C10,'SPC-CPN_Q&A'!$O:$O,"Recall") -> #REF! | BD10: =COUNTIFS('SPC-CPN_Q&A'!#REF!,AV$1,'SPC-CPN_Q&A'!#REF!,'Writing assignments'!$C10,'SPC-CPN_Q&A'!$O:$O,"Application") -> #REF! | BE10: =COUNTIFS('SPC-CPN_Q&A'!#REF!,AV$1,'SPC-CPN_Q&A'!#REF!,'Writing assignments'!$C10,'SPC-CPN_Q&A'!$O:$O,"Analysis") -> #REF! | BF10: X | BG10: 3 | BH10: 0 | BI10: 2 | BJ10: 1 | BL10: =SUM(BM10:BO10) -> #REF! | BM10: =COUNTIFS('SPC-CPN_Q&A'!#REF!,BF$1,'SPC-CPN_Q&A'!#REF!,'Writing assignments'!$C10,'SPC-CPN_Q&A'!$O:$O,"Recall") -> #REF! | BN10: =COUNTIFS('SPC-CPN_Q&A'!#REF!,BF$1,'SPC-CPN_Q&A'!#REF!,'Writing assignments'!$C10,'SPC-CPN_Q&A'!$O:$O,"Application") -> #REF! | BO10: =COUNTIFS('SPC-CPN_Q&A'!#REF!,BF$1,'SPC-CPN_Q&A'!#REF!,'Writing assignments'!$C10,'SPC-CPN_Q&A'!$O:$O,"Analysis") -> #REF! | BP10: X | BQ10: 3 | BR10: 1 | BS10: 1 | BT10: 1 | BV10: =SUM(BW10:BY10) -> #REF! | BW10: =COUNTIFS('SPC-CPN_Q&A'!#REF!,BP$1,'SPC-CPN_Q&A'!#REF!,'Writing assignments'!$C10,'SPC-CPN_Q&A'!$O:$O,"Recall") -> #REF! | BX10: =COUNTIFS('SPC-CPN_Q&A'!#REF!,BP$1,'SPC-CPN_Q&A'!#REF!,'Writing assignments'!$C10,'SPC-CPN_Q&A'!$O:$O,"Application") -> #REF! | BY10: =COUNTIFS('SPC-CPN_Q&A'!#REF!,BP$1,'SPC-CPN_Q&A'!#REF!,'Writing assignments'!$C10,'SPC-CPN_Q&A'!$O:$O,"Analysis") -> #REF! | CA10: 0
B11: Facilitate_Learning | C11: Use teaching and learning strategies based on evidence-based practices related to education | E11: 1 | F11: 6 | G11: 3 | H11: =SUM(E11:G11) -> 10 | J11: =H11-SUM(N11,X11,AH11,AW11,BG11,BQ11,L11,CA11) -> 0 | L11: 0 | M11: X | N11: =SUM(O11:Q11) -> 4 | P11: 3 | Q11: 1 | S11: =SUM(T11:V11) -> #REF! | T11: =COUNTIFS('SPC-CPN_Q&A'!#REF!,M$1,'SPC-CPN_Q&A'!#REF!,'Writing assignments'!$C11,'SPC-CPN_Q&A'!$O:$O,"Recall") -> #REF! | U11: =COUNTIFS('SPC-CPN_Q&A'!#REF!,M$1,'SPC-CPN_Q&A'!#REF!,'Writing assignments'!$C11,'SPC-CPN_Q&A'!$O:$O,"Application") -> #REF! | V11: =COUNTIFS('SPC-CPN_Q&A'!#REF!,M$1,'SPC-CPN_Q&A'!#REF!,'Writing assignments'!$C11,'SPC-CPN_Q&A'!$O:$O,"Analysis") -> #REF! | AC11: =SUM(AD11:AF11) -> #REF! | AD11: =COUNTIFS('SPC-CPN_Q&A'!#REF!,W$1,'SPC-CPN_Q&A'!#REF!,'Writing assignments'!$C11,'SPC-CPN_Q&A'!$O:$O,"Recall") -> #REF! | AE11: =COUNTIFS('SPC-CPN_Q&A'!#REF!,W$1,'SPC-CPN_Q&A'!#REF!,'Writing assignments'!$C11,'SPC-CPN_Q&A'!$O:$O,"Application") -> #REF! | AF11: =COUNTIFS('SPC-CPN_Q&A'!#REF!,W$1,'SPC-CPN_Q&A'!#REF!,'Writing assignments'!$C11,'SPC-CPN_Q&A'!$O:$O,"Analysis") -> #REF! | AM11: =SUM(AN11:AP11) -> #REF! | AN11: =COUNTIFS('SPC-CPN_Q&A'!#REF!,AG$1,'SPC-CPN_Q&A'!#REF!,'Writing assignments'!$C11,'SPC-CPN_Q&A'!$O:$O,"Recall") -> #REF! | AO11: =COUNTIFS('SPC-CPN_Q&A'!#REF!,AG$1,'SPC-CPN_Q&A'!#REF!,'Writing assignments'!$C11,'SPC-CPN_Q&A'!$O:$O,"Application") -> #REF! | AP11: =COUNTIFS('SPC-CPN_Q&A'!#REF!,AG$1,'SPC-CPN_Q&A'!#REF!,'Writing assignments'!$C11,'SPC-CPN_Q&A'!$O:$O,"Analysis") -> #REF! | AQ11: X | AR11: 3 | AS11: 1 | AT11: 1 | AU11: 1 | BB11: =SUM(BC11:BE11) -> #REF! | BC11: =COUNTIFS('SPC-CPN_Q&A'!#REF!,AV$1,'SPC-CPN_Q&A'!#REF!,'Writing assignments'!$C11,'SPC-CPN_Q&A'!$O:$O,"Recall") -> #REF! | BD11: =COUNTIFS('SPC-CPN_Q&A'!#REF!,AV$1,'SPC-CPN_Q&A'!#REF!,'Writing assignments'!$C11,'SPC-CPN_Q&A'!$O:$O,"Application") -> #REF! | BE11: =COUNTIFS('SPC-CPN_Q&A'!#REF!,AV$1,'SPC-CPN_Q&A'!#REF!,'Writing assignments'!$C11,'SPC-CPN_Q&A'!$O:$O,"Analysis") -> #REF! | BF11: X | BG11: 3 | BH11: 0 | BI11: 2 | BJ11: 1 | BL11: =SUM(BM11:BO11) -> #REF! | BM11: =COUNTIFS('SPC-CPN_Q&A'!#REF!,BF$1,'SPC-CPN_Q&A'!#REF!,'Writing assignments'!$C11,'SPC-CPN_Q&A'!$O:$O,"Recall") -> #REF! | BN11: =COUNTIFS('SPC-CPN_Q&A'!#REF!,BF$1,'SPC-CPN_Q&A'!#REF!,'Writing assignments'!$C11,'SPC-CPN_Q&A'!$O:$O,"Application") -> #REF! | BO11: =COUNTIFS('SPC-CPN_Q&A'!#REF!,BF$1,'SPC-CPN_Q&A'!#REF!,'Writing assignments'!$C11,'SPC-CPN_Q&A'!$O:$O,"Analysis") -> #REF! | BP11: X | BQ11: 3 | BR11: 0 | BS11: 2 | BT11: 1 | BV11: =SUM(BW11:BY11) -> #REF! | BW11: =COUNTIFS('SPC-CPN_Q&A'!#REF!,BP$1,'SPC-CPN_Q&A'!#REF!,'Writing assignments'!$C11,'SPC-CPN_Q&A'!$O:$O,"Recall") -> #REF! | BX11: =COUNTIFS('SPC-CPN_Q&A'!#REF!,BP$1,'SPC-CPN_Q&A'!#REF!,'Writing assignments'!$C11,'SPC-CPN_Q&A'!$O:$O,"Application") -> #REF! | BY11: =COUNTIFS('SPC-CPN_Q&A'!#REF!,BP$1,'SPC-CPN_Q&A'!#REF!,'Writing assignments'!$C11,'SPC-CPN_Q&A'!$O:$O,"Analysis") -> #REF! | CA11: 0
B12: Facilitate_Learning | C12: Modify teaching strategies and learning experiences based on consideration of learners' diversity | E12: 1 | F12: 6 | G12: 3 | H12: =SUM(E12:G12) -> 10 | J12: =H12-SUM(N12,X12,AH12,AW12,BG12,BQ12,L12,CA12) -> 0 | L12: 0 | M12: X | N12: =SUM(O12:Q12) -> 1 | P12: 1 | S12: =SUM(T12:V12) -> #REF! | T12: =COUNTIFS('SPC-CPN_Q&A'!#REF!,M$1,'SPC-CPN_Q&A'!#REF!,'Writing assignments'!$C12,'SPC-CPN_Q&A'!$O:$O,"Recall") -> #REF! | U12: =COUNTIFS('SPC-CPN_Q&A'!#REF!,M$1,'SPC-CPN_Q&A'!#REF!,'Writing assignments'!$C12,'SPC-CPN_Q&A'!$O:$O,"Application") -> #REF! | V12: =COUNTIFS('SPC-CPN_Q&A'!#REF!,M$1,'SPC-CPN_Q&A'!#REF!,'Writing assignments'!$C12,'SPC-CPN_Q&A'!$O:$O,"Analysis") -> #REF! | W12: X | X12: 3 | Y12: 0 | Z12: 2 | AA12: 1 | AC12: =SUM(AD12:AF12) -> #REF! | AD12: =COUNTIFS('SPC-CPN_Q&A'!#REF!,W$1,'SPC-CPN_Q&A'!#REF!,'Writing assignments'!$C12,'SPC-CPN_Q&A'!$O:$O,"Recall") -> #REF! | AE12: =COUNTIFS('SPC-CPN_Q&A'!#REF!,W$1,'SPC-CPN_Q&A'!#REF!,'Writing assignments'!$C12,'SPC-CPN_Q&A'!$O:$O,"Application") -> #REF! | AF12: =COUNTIFS('SPC-CPN_Q&A'!#REF!,W$1,'SPC-CPN_Q&A'!#REF!,'Writing assignments'!$C12,'SPC-CPN_Q&A'!$O:$O,"Analysis") -> #REF! | AG12: X | AH12: 3 | AI12: 0 | AJ12: 2 | AK12: 1 | AM12: =SUM(AN12:AP12) -> #REF! | AN12: =COUNTIFS('SPC-CPN_Q&A'!#REF!,AG$1,'SPC-CPN_Q&A'!#REF!,'Writing assignments'!$C12,'SPC-CPN_Q&A'!$O:$O,"Recall") -> #REF! | AO12: =COUNTIFS('SPC-CPN_Q&A'!#REF!,AG$1,'SPC-CPN_Q&A'!#REF!,'Writing assignments'!$C12,'SPC-CPN_Q&A'!$O:$O,"Application") -> #REF! | AP12: =COUNTIFS('SPC-CPN_Q&A'!#REF!,AG$1,'SPC-CPN_Q&A'!#REF!,'Writing assignments'!$C12,'SPC-CPN_Q&A'!$O:$O,"Analysis") -> #REF! | BB12: =SUM(BC12:BE12) -> #REF! | BC12: =COUNTIFS('SPC-CPN_Q&A'!#REF!,AV$1,'SPC-CPN_Q&A'!#REF!,'Writing assignments'!$C12,'SPC-CPN_Q&A'!$O:$O,"Recall") -> #REF! | BD12: =COUNTIFS('SPC-CPN_Q&A'!#REF!,AV$1,'SPC-CPN_Q&A'!#REF!,'Writing assignments'!$C12,'SPC-CPN_Q&A'!$O:$O,"Application") -> #REF! | BE12: =COUNTIFS('SPC-CPN_Q&A'!#REF!,AV$1,'SPC-CPN_Q&A'!#REF!,'Writing assignments'!$C12,'SPC-CPN_Q&A'!$O:$O,"Analysis") -> #REF! | BL12: =SUM(BM12:BO12) -> #REF! | BM12: =COUNTIFS('SPC-CPN_Q&A'!#REF!,BF$1,'SPC-CPN_Q&A'!#REF!,'Writing assignments'!$C12,'SPC-CPN_Q&A'!$O:$O,"Recall") -> #REF! | BN12: =COUNTIFS('SPC-CPN_Q&A'!#REF!,BF$1,'SPC-CPN_Q&A'!#REF!,'Writing assignments'!$C12,'SPC-CPN_Q&A'!$O:$O,"Application") -> #REF! | BO12: =COUNTIFS('SPC-CPN_Q&A'!#REF!,BF$1,'SPC-CPN_Q&A'!#REF!,'Writing assignments'!$C12,'SPC-CPN_Q&A'!$O:$O,"Analysis") -> #REF! | BP12: X | BQ12: 3 | BR12: 1 | BS12: 1 | BT12: 1 | BV12: =SUM(BW12:BY12) -> #REF! | BW12: =COUNTIFS('SPC-CPN_Q&A'!#REF!,BP$1,'SPC-CPN_Q&A'!#REF!,'Writing assignments'!$C12,'SPC-CPN_Q&A'!$O:$O,"Recall") -> #REF! | BX12: =COUNTIFS('SPC-CPN_Q&A'!#REF!,BP$1,'SPC-CPN_Q&A'!#REF!,'Writing assignments'!$C12,'SPC-CPN_Q&A'!$O:$O,"Application") -> #REF! | BY12: =COUNTIFS('SPC-CPN_Q&A'!#REF!,BP$1,'SPC-CPN_Q&A'!#REF!,'Writing assignments'!$C12,'SPC-CPN_Q&A'!$O:$O,"Analysis") -> #REF! | CA12: 0
B13: Facilitate_Learning | C13: Modify teaching strategies and learning experiences based on consideration of learners' social determinants of learning (i.e., physical health, psychosocial health, economic stability, physical environment, social environment, and self- motivation) | E13: 1 | F13: 6 | G13: 3 | H13: =SUM(E13:G13) -> 10 | J13: =H13-SUM(N13,X13,AH13,AW13,BG13,BQ13,L13,CA13) -> 0 | K13: X | L13: 1 | N13: =SUM(O13:Q13) -> 0 | S13: =SUM(T13:V13) -> #REF! | T13: =COUNTIFS('SPC-CPN_Q&A'!#REF!,M$1,'SPC-CPN_Q&A'!#REF!,'Writing assignments'!$C13,'SPC-CPN_Q&A'!$O:$O,"Recall") -> #REF! | U13: =COUNTIFS('SPC-CPN_Q&A'!#REF!,M$1,'SPC-CPN_Q&A'!#REF!,'Writing assignments'!$C13,'SPC-CPN_Q&A'!$O:$O,"Application") -> #REF! | V13: =COUNTIFS('SPC-CPN_Q&A'!#REF!,M$1,'SPC-CPN_Q&A'!#REF!,'Writing assignments'!$C13,'SPC-CPN_Q&A'!$O:$O,"Analysis") -> #REF! | AC13: =SUM(AD13:AF13) -> #REF! | AD13: =COUNTIFS('SPC-CPN_Q&A'!#REF!,W$1,'SPC-CPN_Q&A'!#REF!,'Writing assignments'!$C13,'SPC-CPN_Q&A'!$O:$O,"Recall") -> #REF! | AE13: =COUNTIFS('SPC-CPN_Q&A'!#REF!,W$1,'SPC-CPN_Q&A'!#REF!,'Writing assignments'!$C13,'SPC-CPN_Q&A'!$O:$O,"Application") -> #REF! | AF13: =COUNTIFS('SPC-CPN_Q&A'!#REF!,W$1,'SPC-CPN_Q&A'!#REF!,'Writing assignments'!$C13,'SPC-CPN_Q&A'!$O:$O,"Analysis") -> #REF! | AM13: =SUM(AN13:AP13) -> #REF! | AN13: =COUNTIFS('SPC-CPN_Q&A'!#REF!,AG$1,'SPC-CPN_Q&A'!#REF!,'Writing assignments'!$C13,'SPC-CPN_Q&A'!$O:$O,"Recall") -> #REF! | AO13: =COUNTIFS('SPC-CPN_Q&A'!#REF!,AG$1,'SPC-CPN_Q&A'!#REF!,'Writing assignments'!$C13,'SPC-CPN_Q&A'!$O:$O,"Application") -> #REF! | AP13: =COUNTIFS('SPC-CPN_Q&A'!#REF!,AG$1,'SPC-CPN_Q&A'!#REF!,'Writing assignments'!$C13,'SPC-CPN_Q&A'!$O:$O,"Analysis") -> #REF! | AV13: X | AW13: 3 | AX13: 0 | AY13: 2 | AZ13: 1 | BB13: =SUM(BC13:BE13) -> #REF! | BC13: =COUNTIFS('SPC-CPN_Q&A'!#REF!,AV$1,'SPC-CPN_Q&A'!#REF!,'Writing assignments'!$C13,'SPC-CPN_Q&A'!$O:$O,"Recall") -> #REF! | BD13: =COUNTIFS('SPC-CPN_Q&A'!#REF!,AV$1,'SPC-CPN_Q&A'!#REF!,'Writing assignments'!$C13,'SPC-CPN_Q&A'!$O:$O,"Application") -> #REF! | BE13: =COUNTIFS('SPC-CPN_Q&A'!#REF!,AV$1,'SPC-CPN_Q&A'!#REF!,'Writing assignments'!$C13,'SPC-CPN_Q&A'!$O:$O,"Analysis") -> #REF! | BF13: X | BG13: 3 | BH13: 1 | BI13: 1 | BJ13: 1 | BL13: =SUM(BM13:BO13) -> #REF! | BM13: =COUNTIFS('SPC-CPN_Q&A'!#REF!,BF$1,'SPC-CPN_Q&A'!#REF!,'Writing assignments'!$C13,'SPC-CPN_Q&A'!$O:$O,"Recall") -> #REF! | BN13: =COUNTIFS('SPC-CPN_Q&A'!#REF!,BF$1,'SPC-CPN_Q&A'!#REF!,'Writing assignments'!$C13,'SPC-CPN_Q&A'!$O:$O,"Application") -> #REF! | BO13: =COUNTIFS('SPC-CPN_Q&A'!#REF!,BF$1,'SPC-CPN_Q&A'!#REF!,'Writing assignments'!$C13,'SPC-CPN_Q&A'!$O:$O,"Analysis") -> #REF! | BP13: X | BQ13: 3 | BR13: 0 | BS13: 2 | BT13: 1 | BV13: =SUM(BW13:BY13) -> #REF! | BW13: =COUNTIFS('SPC-CPN_Q&A'!#REF!,BP$1,'SPC-CPN_Q&A'!#REF!,'Writing assignments'!$C13,'SPC-CPN_Q&A'!$O:$O,"Recall") -> #REF! | BX13: =COUNTIFS('SPC-CPN_Q&A'!#REF!,BP$1,'SPC-CPN_Q&A'!#REF!,'Writing assignments'!$C13,'SPC-CPN_Q&A'!$O:$O,"Application") -> #REF! | BY13: =COUNTIFS('SPC-CPN_Q&A'!#REF!,BP$1,'SPC-CPN_Q&A'!#REF!,'Writing assignments'!$C13,'SPC-CPN_Q&A'!$O:$O,"Analysis") -> #REF! | CA13: 0
B14: Facilitate_Learning | C14: Modify teaching strategies and learning experiences based on consideration of learners' past clinical, educational, and life experiences | E14: 1 | F14: 6 | G14: 3 | H14: =SUM(E14:G14) -> 10 | J14: =H14-SUM(N14,X14,AH14,AW14,BG14,BQ14,L14,CA14) -> 0 | K14: X | L14: 1 | M14: X | N14: =SUM(O14:Q14) -> 1 | P14: 1 | S14: =SUM(T14:V14) -> #REF! | T14: =COUNTIFS('SPC-CPN_Q&A'!#REF!,M$1,'SPC-CPN_Q&A'!#REF!,'Writing assignments'!$C14,'SPC-CPN_Q&A'!$O:$O,"Recall") -> #REF! | U14: =COUNTIFS('SPC-CPN_Q&A'!#REF!,M$1,'SPC-CPN_Q&A'!#REF!,'Writing assignments'!$C14,'SPC-CPN_Q&A'!$O:$O,"Application") -> #REF! | V14: =COUNTIFS('SPC-CPN_Q&A'!#REF!,M$1,'SPC-CPN_Q&A'!#REF!,'Writing assignments'!$C14,'SPC-CPN_Q&A'!$O:$O,"Analysis") -> #REF! | W14: X | X14: 3 | Y14: 0 | Z14: 2 | AA14: 1 | AC14: =SUM(AD14:AF14) -> #REF! | AD14: =COUNTIFS('SPC-CPN_Q&A'!#REF!,W$1,'SPC-CPN_Q&A'!#REF!,'Writing assignments'!$C14,'SPC-CPN_Q&A'!$O:$O,"Recall") -> #REF! | AE14: =COUNTIFS('SPC-CPN_Q&A'!#REF!,W$1,'SPC-CPN_Q&A'!#REF!,'Writing assignments'!$C14,'SPC-CPN_Q&A'!$O:$O,"Application") -> #REF! | AF14: =COUNTIFS('SPC-CPN_Q&A'!#REF!,W$1,'SPC-CPN_Q&A'!#REF!,'Writing assignments'!$C14,'SPC-CPN_Q&A'!$O:$O,"Analysis") -> #REF! | AG14: X | AH14: 3 | AI14: 1 | AJ14: 1 | AK14: 1 | AM14: =SUM(AN14:AP14) -> #REF! | AN14: =COUNTIFS('SPC-CPN_Q&A'!#REF!,AG$1,'SPC-CPN_Q&A'!#REF!,'Writing assignments'!$C14,'SPC-CPN_Q&A'!$O:$O,"Recall") -> #REF! | AO14: =COUNTIFS('SPC-CPN_Q&A'!#REF!,AG$1,'SPC-CPN_Q&A'!#REF!,'Writing assignments'!$C14,'SPC-CPN_Q&A'!$O:$O,"Application") -> #REF! | AP14: =COUNTIFS('SPC-CPN_Q&A'!#REF!,AG$1,'SPC-CPN_Q&A'!#REF!,'Writing assignments'!$C14,'SPC-CPN_Q&A'!$O:$O,"Analysis") -> #REF! | AV14: X | AW14: 2 | AX14: 0 | AY14: 2 | AZ14: 0 | BB14: =SUM(BC14:BE14) -> #REF! | BC14: =COUNTIFS('SPC-CPN_Q&A'!#REF!,AV$1,'SPC-CPN_Q&A'!#REF!,'Writing assignments'!$C14,'SPC-CPN_Q&A'!$O:$O,"Recall") -> #REF! | BD14: =COUNTIFS('SPC-CPN_Q&A'!#REF!,AV$1,'SPC-CPN_Q&A'!#REF!,'Writing assignments'!$C14,'SPC-CPN_Q&A'!$O:$O,"Application") -> #REF! | BE14: =COUNTIFS('SPC-CPN_Q&A'!#REF!,AV$1,'SPC-CPN_Q&A'!#REF!,'Writing assignments'!$C14,'SPC-CPN_Q&A'!$O:$O,"Analysis") -> #REF! | BL14: =SUM(BM14:BO14) -> #REF! | BM14: =COUNTIFS('SPC-CPN_Q&A'!#REF!,BF$1,'SPC-CPN_Q&A'!#REF!,'Writing assignments'!$C14,'SPC-CPN_Q&A'!$O:$O,"Recall") -> #REF! | BN14: =COUNTIFS('SPC-CPN_Q&A'!#REF!,BF$1,'SPC-CPN_Q&A'!#REF!,'Writing assignments'!$C14,'SPC-CPN_Q&A'!$O:$O,"Application") -> #REF! | BO14: =COUNTIFS('SPC-CPN_Q&A'!#REF!,BF$1,'SPC-CPN_Q&A'!#REF!,'Writing assignments'!$C14,'SPC-CPN_Q&A'!$O:$O,"Analysis") -> #REF! | BV14: =SUM(BW14:BY14) -> #REF! | BW14: =COUNTIFS('SPC-CPN_Q&A'!#REF!,BP$1,'SPC-CPN_Q&A'!#REF!,'Writing assignments'!$C14,'SPC-CPN_Q&A'!$O:$O,"Recall") -> #REF! | BX14: =COUNTIFS('SPC-CPN_Q&A'!#REF!,BP$1,'SPC-CPN_Q&A'!#REF!,'Writing assignments'!$C14,'SPC-CPN_Q&A'!$O:$O,"Application") -> #REF! | BY14: =COUNTIFS('SPC-CPN_Q&A'!#REF!,BP$1,'SPC-CPN_Q&A'!#REF!,'Writing assignments'!$C14,'SPC-CPN_Q&A'!$O:$O,"Analysis") -> #REF! | CA14: 0
B15: Facilitate_Learning | C15: Use technologies to support the teaching-learning process | E15: 1 | F15: 6 | G15: 3 | H15: =SUM(E15:G15) -> 10 | J15: =H15-SUM(N15,X15,AH15,AW15,BG15,BQ15,L15,CA15) -> 0 | K15: X | L15: 1 | N15: =SUM(O15:Q15) -> 0 | S15: =SUM(T15:V15) -> #REF! | T15: =COUNTIFS('SPC-CPN_Q&A'!#REF!,M$1,'SPC-CPN_Q&A'!#REF!,'Writing assignments'!$C15,'SPC-CPN_Q&A'!$O:$O,"Recall") -> #REF! | U15: =COUNTIFS('SPC-CPN_Q&A'!#REF!,M$1,'SPC-CPN_Q&A'!#REF!,'Writing assignments'!$C15,'SPC-CPN_Q&A'!$O:$O,"Application") -> #REF! | V15: =COUNTIFS('SPC-CPN_Q&A'!#REF!,M$1,'SPC-CPN_Q&A'!#REF!,'Writing assignments'!$C15,'SPC-CPN_Q&A'!$O:$O,"Analysis") -> #REF! | AC15: =SUM(AD15:AF15) -> #REF! | AD15: =COUNTIFS('SPC-CPN_Q&A'!#REF!,W$1,'SPC-CPN_Q&A'!#REF!,'Writing assignments'!$C15,'SPC-CPN_Q&A'!$O:$O,"Recall") -> #REF! | AE15: =COUNTIFS('SPC-CPN_Q&A'!#REF!,W$1,'SPC-CPN_Q&A'!#REF!,'Writing assignments'!$C15,'SPC-CPN_Q&A'!$O:$O,"Application") -> #REF! | AF15: =COUNTIFS('SPC-CPN_Q&A'!#REF!,W$1,'SPC-CPN_Q&A'!#REF!,'Writing assignments'!$C15,'SPC-CPN_Q&A'!$O:$O,"Analysis") -> #REF! | AG15: X | AH15: 3 | AI15: 1 | AJ15: 1 | AK15: 1 | AM15: =SUM(AN15:AP15) -> #REF! | AN15: =COUNTIFS('SPC-CPN_Q&A'!#REF!,AG$1,'SPC-CPN_Q&A'!#REF!,'Writing assignments'!$C15,'SPC-CPN_Q&A'!$O:$O,"Recall") -> #REF! | AO15: =COUNTIFS('SPC-CPN_Q&A'!#REF!,AG$1,'SPC-CPN_Q&A'!#REF!,'Writing assignments'!$C15,'SPC-CPN_Q&A'!$O:$O,"Application") -> #REF! | AP15: =COUNTIFS('SPC-CPN_Q&A'!#REF!,AG$1,'SPC-CPN_Q&A'!#REF!,'Writing assignments'!$C15,'SPC-CPN_Q&A'!$O:$O,"Analysis") -> #REF! | AV15: X | AW15: 3 | AX15: 0 | AY15: 2 | AZ15: 1 | BB15: =SUM(BC15:BE15) -> #REF! | BC15: =COUNTIFS('SPC-CPN_Q&A'!#REF!,AV$1,'SPC-CPN_Q&A'!#REF!,'Writing assignments'!$C15,'SPC-CPN_Q&A'!$O:$O,"Recall") -> #REF! | BD15: =COUNTIFS('SPC-CPN_Q&A'!#REF!,AV$1,'SPC-CPN_Q&A'!#REF!,'Writing assignments'!$C15,'SPC-CPN_Q&A'!$O:$O,"Application") -> #REF! | BE15: =COUNTIFS('SPC-CPN_Q&A'!#REF!,AV$1,'SPC-CPN_Q&A'!#REF!,'Writing assignments'!$C15,'SPC-CPN_Q&A'!$O:$O,"Analysis") -> #REF! | BF15: X | BG15: 3 | BH15: 0 | BI15: 2 | BJ15: 1 | BL15: =SUM(BM15:BO15) -> #REF! | BM15: =COUNTIFS('SPC-CPN_Q&A'!#REF!,BF$1,'SPC-CPN_Q&A'!#REF!,'Writing assignments'!$C15,'SPC-CPN_Q&A'!$O:$O,"Recall") -> #REF! | BN15: =COUNTIFS('SPC-CPN_Q&A'!#REF!,BF$1,'SPC-CPN_Q&A'!#REF!,'Writing assignments'!$C15,'SPC-CPN_Q&A'!$O:$O,"Application") -> #REF! | BO15: =COUNTIFS('SPC-CPN_Q&A'!#REF!,BF$1,'SPC-CPN_Q&A'!#REF!,'Writing assignments'!$C15,'SPC-CPN_Q&A'!$O:$O,"Analysis") -> #REF! | BV15: =SUM(BW15:BY15) -> #REF! | BW15: =COUNTIFS('SPC-CPN_Q&A'!#REF!,BP$1,'SPC-CPN_Q&A'!#REF!,'Writing assignments'!$C15,'SPC-CPN_Q&A'!$O:$O,"Recall") -> #REF! | BX15: =COUNTIFS('SPC-CPN_Q&A'!#REF!,BP$1,'SPC-CPN_Q&A'!#REF!,'Writing assignments'!$C15,'SPC-CPN_Q&A'!$O:$O,"Application") -> #REF! | BY15: =COUNTIFS('SPC-CPN_Q&A'!#REF!,BP$1,'SPC-CPN_Q&A'!#REF!,'Writing assignments'!$C15,'SPC-CPN_Q&A'!$O:$O,"Analysis") -> #REF! | CA15: 0
B16: Facilitate_Learning | C16: Communicate effectively to convey ideas in a variety of contexts | E16: 1 | F16: 6 | G16: 3 | H16: =SUM(E16:G16) -> 10 | J16: =H16-SUM(N16,X16,AH16,AW16,BG16,BQ16,L16,CA16) -> 0 | K16: X | L16: 1 | N16: =SUM(O16:Q16) -> 0 | S16: =SUM(T16:V16) -> #REF! | T16: =COUNTIFS('SPC-CPN_Q&A'!#REF!,M$1,'SPC-CPN_Q&A'!#REF!,'Writing assignments'!$C16,'SPC-CPN_Q&A'!$O:$O,"Recall") -> #REF! | U16: =COUNTIFS('SPC-CPN_Q&A'!#REF!,M$1,'SPC-CPN_Q&A'!#REF!,'Writing assignments'!$C16,'SPC-CPN_Q&A'!$O:$O,"Application") -> #REF! | V16: =COUNTIFS('SPC-CPN_Q&A'!#REF!,M$1,'SPC-CPN_Q&A'!#REF!,'Writing assignments'!$C16,'SPC-CPN_Q&A'!$O:$O,"Analysis") -> #REF! | W16: X | X16: 3 | Y16: 0 | Z16: 2 | AA16: 1 | AC16: =SUM(AD16:AF16) -> #REF! | AD16: =COUNTIFS('SPC-CPN_Q&A'!#REF!,W$1,'SPC-CPN_Q&A'!#REF!,'Writing assignments'!$C16,'SPC-CPN_Q&A'!$O:$O,"Recall") -> #REF! | AE16: =COUNTIFS('SPC-CPN_Q&A'!#REF!,W$1,'SPC-CPN_Q&A'!#REF!,'Writing assignments'!$C16,'SPC-CPN_Q&A'!$O:$O,"Application") -> #REF! | AF16: =COUNTIFS('SPC-CPN_Q&A'!#REF!,W$1,'SPC-CPN_Q&A'!#REF!,'Writing assignments'!$C16,'SPC-CPN_Q&A'!$O:$O,"Analysis") -> #REF! | AG16: X | AH16: 3 | AI16: 0 | AJ16: 2 | AK16: 1 | AM16: =SUM(AN16:AP16) -> #REF! | AN16: =COUNTIFS('SPC-CPN_Q&A'!#REF!,AG$1,'SPC-CPN_Q&A'!#REF!,'Writing assignments'!$C16,'SPC-CPN_Q&A'!$O:$O,"Recall") -> #REF! | AO16: =COUNTIFS('SPC-CPN_Q&A'!#REF!,AG$1,'SPC-CPN_Q&A'!#REF!,'Writing assignments'!$C16,'SPC-CPN_Q&A'!$O:$O,"Application") -> #REF! | AP16: =COUNTIFS('SPC-CPN_Q&A'!#REF!,AG$1,'SPC-CPN_Q&A'!#REF!,'Writing assignments'!$C16,'SPC-CPN_Q&A'!$O:$O,"Analysis") -> #REF! | AV16: X | AW16: 3 | AX16: 1 | AY16: 1 | AZ16: 1 | BB16: =SUM(BC16:BE16) -> #REF! | BC16: =COUNTIFS('SPC-CPN_Q&A'!#REF!,AV$1,'SPC-CPN_Q&A'!#REF!,'Writing assignments'!$C16,'SPC-CPN_Q&A'!$O:$O,"Recall") -> #REF! | BD16: =COUNTIFS('SPC-CPN_Q&A'!#REF!,AV$1,'SPC-CPN_Q&A'!#REF!,'Writing assignments'!$C16,'SPC-CPN_Q&A'!$O:$O,"Application") -> #REF! | BE16: =COUNTIFS('SPC-CPN_Q&A'!#REF!,AV$1,'SPC-CPN_Q&A'!#REF!,'Writing assignments'!$C16,'SPC-CPN_Q&A'!$O:$O,"Analysis") -> #REF! | BL16: =SUM(BM16:BO16) -> #REF! | BM16: =COUNTIFS('SPC-CPN_Q&A'!#REF!,BF$1,'SPC-CPN_Q&A'!#REF!,'Writing assignments'!$C16,'SPC-CPN_Q&A'!$O:$O,"Recall") -> #REF! | BN16: =COUNTIFS('SPC-CPN_Q&A'!#REF!,BF$1,'SPC-CPN_Q&A'!#REF!,'Writing assignments'!$C16,'SPC-CPN_Q&A'!$O:$O,"Application") -> #REF! | BO16: =COUNTIFS('SPC-CPN_Q&A'!#REF!,BF$1,'SPC-CPN_Q&A'!#REF!,'Writing assignments'!$C16,'SPC-CPN_Q&A'!$O:$O,"Analysis") -> #REF! | BV16: =SUM(BW16:BY16) -> #REF! | BW16: =COUNTIFS('SPC-CPN_Q&A'!#REF!,BP$1,'SPC-CPN_Q&A'!#REF!,'Writing assignments'!$C16,'SPC-CPN_Q&A'!$O:$O,"Recall") -> #REF! | BX16: =COUNTIFS('SPC-CPN_Q&A'!#REF!,BP$1,'SPC-CPN_Q&A'!#REF!,'Writing assignments'!$C16,'SPC-CPN_Q&A'!$O:$O,"Application") -> #REF! | BY16: =COUNTIFS('SPC-CPN_Q&A'!#REF!,BP$1,'SPC-CPN_Q&A'!#REF!,'Writing assignments'!$C16,'SPC-CPN_Q&A'!$O:$O,"Analysis") -> #REF! | CA16: 0
B17: Facilitate_Learning | C17: Model reflective thinking practices | E17: 1 | F17: 6 | G17: 3 | H17: =SUM(E17:G17) -> 10 | J17: =H17-SUM(N17,X17,AH17,AW17,BG17,BQ17,L17,CA17) -> 0 | K17: X | L17: 1 | M17: X | N17: =SUM(O17:Q17) -> 1 | P17: 1 | S17: =SUM(T17:V17) -> #REF! | T17: =COUNTIFS('SPC-CPN_Q&A'!#REF!,M$1,'SPC-CPN_Q&A'!#REF!,'Writing assignments'!$C17,'SPC-CPN_Q&A'!$O:$O,"Recall") -> #REF! | U17: =COUNTIFS('SPC-CPN_Q&A'!#REF!,M$1,'SPC-CPN_Q&A'!#REF!,'Writing assignments'!$C17,'SPC-CPN_Q&A'!$O:$O,"Application") -> #REF! | V17: =COUNTIFS('SPC-CPN_Q&A'!#REF!,M$1,'SPC-CPN_Q&A'!#REF!,'Writing assignments'!$C17,'SPC-CPN_Q&A'!$O:$O,"Analysis") -> #REF! | AC17: =SUM(AD17:AF17) -> #REF! | AD17: =COUNTIFS('SPC-CPN_Q&A'!#REF!,W$1,'SPC-CPN_Q&A'!#REF!,'Writing assignments'!$C17,'SPC-CPN_Q&A'!$O:$O,"Recall") -> #REF! | AE17: =COUNTIFS('SPC-CPN_Q&A'!#REF!,W$1,'SPC-CPN_Q&A'!#REF!,'Writing assignments'!$C17,'SPC-CPN_Q&A'!$O:$O,"Application") -> #REF! | AF17: =COUNTIFS('SPC-CPN_Q&A'!#REF!,W$1,'SPC-CPN_Q&A'!#REF!,'Writing assignments'!$C17,'SPC-CPN_Q&A'!$O:$O,"Analysis") -> #REF! | AM17: =SUM(AN17:AP17) -> #REF! | AN17: =COUNTIFS('SPC-CPN_Q&A'!#REF!,AG$1,'SPC-CPN_Q&A'!#REF!,'Writing assignments'!$C17,'SPC-CPN_Q&A'!$O:$O,"Recall") -> #REF! | AO17: =COUNTIFS('SPC-CPN_Q&A'!#REF!,AG$1,'SPC-CPN_Q&A'!#REF!,'Writing assignments'!$C17,'SPC-CPN_Q&A'!$O:$O,"Application") -> #REF! | AP17: =COUNTIFS('SPC-CPN_Q&A'!#REF!,AG$1,'SPC-CPN_Q&A'!#REF!,'Writing assignments'!$C17,'SPC-CPN_Q&A'!$O:$O,"Analysis") -> #REF! | AV17: X | AW17: 2 | AX17: 0 | AY17: 1 | AZ17: 1 | BB17: =SUM(BC17:BE17) -> #REF! | BC17: =COUNTIFS('SPC-CPN_Q&A'!#REF!,AV$1,'SPC-CPN_Q&A'!#REF!,'Writing assignments'!$C17,'SPC-CPN_Q&A'!$O:$O,"Recall") -> #REF! | BD17: =COUNTIFS('SPC-CPN_Q&A'!#REF!,AV$1,'SPC-CPN_Q&A'!#REF!,'Writing assignments'!$C17,'SPC-CPN_Q&A'!$O:$O,"Application") -> #REF! | BE17: =COUNTIFS('SPC-CPN_Q&A'!#REF!,AV$1,'SPC-CPN_Q&A'!#REF!,'Writing assignments'!$C17,'SPC-CPN_Q&A'!$O:$O,"Analysis") -> #REF! | BF17: X | BG17: 3 | BH17: 0 | BI17: 2 | BJ17: 1 | BL17: =SUM(BM17:BO17) -> #REF! | BM17: =COUNTIFS('SPC-CPN_Q&A'!#REF!,BF$1,'SPC-CPN_Q&A'!#REF!,'Writing assignments'!$C17,'SPC-CPN_Q&A'!$O:$O,"Recall") -> #REF! | BN17: =COUNTIFS('SPC-CPN_Q&A'!#REF!,BF$1,'SPC-CPN_Q&A'!#REF!,'Writing assignments'!$C17,'SPC-CPN_Q&A'!$O:$O,"Application") -> #REF! | BO17: =COUNTIFS('SPC-CPN_Q&A'!#REF!,BF$1,'SPC-CPN_Q&A'!#REF!,'Writing assignments'!$C17,'SPC-CPN_Q&A'!$O:$O,"Analysis") -> #REF! | BP17: X | BQ17: 3 | BR17: 1 | BS17: 1 | BT17: 1 | BV17: =SUM(BW17:BY17) -> #REF! | BW17: =COUNTIFS('SPC-CPN_Q&A'!#REF!,BP$1,'SPC-CPN_Q&A'!#REF!,'Writing assignments'!$C17,'SPC-CPN_Q&A'!$O:$O,"Recall") -> #REF! | BX17: =COUNTIFS('SPC-CPN_Q&A'!#REF!,BP$1,'SPC-CPN_Q&A'!#REF!,'Writing assignments'!$C17,'SPC-CPN_Q&A'!$O:$O,"Application") -> #REF! | BY17: =COUNTIFS('SPC-CPN_Q&A'!#REF!,BP$1,'SPC-CPN_Q&A'!#REF!,'Writing assignments'!$C17,'SPC-CPN_Q&A'!$O:$O,"Analysis") -> #REF! | CA17: 0
B18: Facilitate_Learning | C18: Create opportunities for learners to develop clinical judgment | E18: 1 | F18: 6 | G18: 3 | H18: =SUM(E18:G18) -> 10 | J18: =H18-SUM(N18,X18,AH18,AW18,BG18,BQ18,L18,CA18) -> 0 | K18: X | L18: 1 | M18: X | N18: =SUM(O18:Q18) -> 3 | P18: 2 | Q18: 1 | S18: =SUM(T18:V18) -> #REF! | T18: =COUNTIFS('SPC-CPN_Q&A'!#REF!,M$1,'SPC-CPN_Q&A'!#REF!,'Writing assignments'!$C18,'SPC-CPN_Q&A'!$O:$O,"Recall") -> #REF! | U18: =COUNTIFS('SPC-CPN_Q&A'!#REF!,M$1,'SPC-CPN_Q&A'!#REF!,'Writing assignments'!$C18,'SPC-CPN_Q&A'!$O:$O,"Application") -> #REF! | V18: =COUNTIFS('SPC-CPN_Q&A'!#REF!,M$1,'SPC-CPN_Q&A'!#REF!,'Writing assignments'!$C18,'SPC-CPN_Q&A'!$O:$O,"Analysis") -> #REF! | W18: X | X18: 2 | Y18: 0 | Z18: 1 | AA18: 1 | AC18: =SUM(AD18:AF18) -> #REF! | AD18: =COUNTIFS('SPC-CPN_Q&A'!#REF!,W$1,'SPC-CPN_Q&A'!#REF!,'Writing assignments'!$C18,'SPC-CPN_Q&A'!$O:$O,"Recall") -> #REF! | AE18: =COUNTIFS('SPC-CPN_Q&A'!#REF!,W$1,'SPC-CPN_Q&A'!#REF!,'Writing assignments'!$C18,'SPC-CPN_Q&A'!$O:$O,"Application") -> #REF! | AF18: =COUNTIFS('SPC-CPN_Q&A'!#REF!,W$1,'SPC-CPN_Q&A'!#REF!,'Writing assignments'!$C18,'SPC-CPN_Q&A'!$O:$O,"Analysis") -> #REF! | AM18: =SUM(AN18:AP18) -> #REF! | AN18: =COUNTIFS('SPC-CPN_Q&A'!#REF!,AG$1,'SPC-CPN_Q&A'!#REF!,'Writing assignments'!$C18,'SPC-CPN_Q&A'!$O:$O,"Recall") -> #REF! | AO18: =COUNTIFS('SPC-CPN_Q&A'!#REF!,AG$1,'SPC-CPN_Q&A'!#REF!,'Writing assignments'!$C18,'SPC-CPN_Q&A'!$O:$O,"Application") -> #REF! | AP18: =COUNTIFS('SPC-CPN_Q&A'!#REF!,AG$1,'SPC-CPN_Q&A'!#REF!,'Writing assignments'!$C18,'SPC-CPN_Q&A'!$O:$O,"Analysis") -> #REF! | BB18: =SUM(BC18:BE18) -> #REF! | BC18: =COUNTIFS('SPC-CPN_Q&A'!#REF!,AV$1,'SPC-CPN_Q&A'!#REF!,'Writing assignments'!$C18,'SPC-CPN_Q&A'!$O:$O,"Recall") -> #REF! | BD18: =COUNTIFS('SPC-CPN_Q&A'!#REF!,AV$1,'SPC-CPN_Q&A'!#REF!,'Writing assignments'!$C18,'SPC-CPN_Q&A'!$O:$O,"Application") -> #REF! | BE18: =COUNTIFS('SPC-CPN_Q&A'!#REF!,AV$1,'SPC-CPN_Q&A'!#REF!,'Writing assignments'!$C18,'SPC-CPN_Q&A'!$O:$O,"Analysis") -> #REF! | BF18: X | BG18: 2 | BH18: 1 | BI18: 1 | BJ18: 0 | BL18: =SUM(BM18:BO18) -> #REF! | BM18: =COUNTIFS('SPC-CPN_Q&A'!#REF!,BF$1,'SPC-CPN_Q&A'!#REF!,'Writing assignments'!$C18,'SPC-CPN_Q&A'!$O:$O,"Recall") -> #REF! | BN18: =COUNTIFS('SPC-CPN_Q&A'!#REF!,BF$1,'SPC-CPN_Q&A'!#REF!,'Writing assignments'!$C18,'SPC-CPN_Q&A'!$O:$O,"Application") -> #REF! | BO18: =COUNTIFS('SPC-CPN_Q&A'!#REF!,BF$1,'SPC-CPN_Q&A'!#REF!,'Writing assignments'!$C18,'SPC-CPN_Q&A'!$O:$O,"Analysis") -> #REF! | BP18: X | BQ18: 2 | BR18: 0 | BS18: 1 | BT18: 1 | BV18: =SUM(BW18:BY18) -> #REF! | BW18: =COUNTIFS('SPC-CPN_Q&A'!#REF!,BP$1,'SPC-CPN_Q&A'!#REF!,'Writing assignments'!$C18,'SPC-CPN_Q&A'!$O:$O,"Recall") -> #REF! | BX18: =COUNTIFS('SPC-CPN_Q&A'!#REF!,BP$1,'SPC-CPN_Q&A'!#REF!,'Writing assignments'!$C18,'SPC-CPN_Q&A'!$O:$O,"Application") -> #REF! | BY18: =COUNTIFS('SPC-CPN_Q&A'!#REF!,BP$1,'SPC-CPN_Q&A'!#REF!,'Writing assignments'!$C18,'SPC-CPN_Q&A'!$O:$O,"Analysis") -> #REF! | CA18: 0
B19: Facilitate_Learning | C19: Ensure a positive and safe learning environment | E19: 1 | F19: 6 | G19: 3 | H19: =SUM(E19:G19) -> 10 | J19: =H19-SUM(N19,X19,AH19,AW19,BG19,BQ19,L19,CA19) -> 0 | K19: X | L19: 1 | M19: X | N19: =SUM(O19:Q19) -> 3 | P19: 2 | Q19: 1 | S19: =SUM(T19:V19) -> #REF! | T19: =COUNTIFS('SPC-CPN_Q&A'!#REF!,M$1,'SPC-CPN_Q&A'!#REF!,'Writing assignments'!$C19,'SPC-CPN_Q&A'!$O:$O,"Recall") -> #REF! | U19: =COUNTIFS('SPC-CPN_Q&A'!#REF!,M$1,'SPC-CPN_Q&A'!#REF!,'Writing assignments'!$C19,'SPC-CPN_Q&A'!$O:$O,"Application") -> #REF! | V19: =COUNTIFS('SPC-CPN_Q&A'!#REF!,M$1,'SPC-CPN_Q&A'!#REF!,'Writing assignments'!$C19,'SPC-CPN_Q&A'!$O:$O,"Analysis") -> #REF! | W19: X | X19: 3 | Y19: 1 | Z19: 1 | AA19: 1 | AC19: =SUM(AD19:AF19) -> #REF! | AD19: =COUNTIFS('SPC-CPN_Q&A'!#REF!,W$1,'SPC-CPN_Q&A'!#REF!,'Writing assignments'!$C19,'SPC-CPN_Q&A'!$O:$O,"Recall") -> #REF! | AE19: =COUNTIFS('SPC-CPN_Q&A'!#REF!,W$1,'SPC-CPN_Q&A'!#REF!,'Writing assignments'!$C19,'SPC-CPN_Q&A'!$O:$O,"Application") -> #REF! | AF19: =COUNTIFS('SPC-CPN_Q&A'!#REF!,W$1,'SPC-CPN_Q&A'!#REF!,'Writing assignments'!$C19,'SPC-CPN_Q&A'!$O:$O,"Analysis") -> #REF! | AG19: X | AH19: 3 | AI19: 0 | AJ19: 2 | AK19: 1 | AM19: =SUM(AN19:AP19) -> #REF! | AN19: =COUNTIFS('SPC-CPN_Q&A'!#REF!,AG$1,'SPC-CPN_Q&A'!#REF!,'Writing assignments'!$C19,'SPC-CPN_Q&A'!$O:$O,"Recall") -> #REF! | AO19: =COUNTIFS('SPC-CPN_Q&A'!#REF!,AG$1,'SPC-CPN_Q&A'!#REF!,'Writing assignments'!$C19,'SPC-CPN_Q&A'!$O:$O,"Application") -> #REF! | AP19: =COUNTIFS('SPC-CPN_Q&A'!#REF!,AG$1,'SPC-CPN_Q&A'!#REF!,'Writing assignments'!$C19,'SPC-CPN_Q&A'!$O:$O,"Analysis") -> #REF! | AQ19: X | AR19: 3 | AS19: 0 | AT19: 2 | AU19: 1 | BB19: =SUM(BC19:BE19) -> #REF! | BC19: =COUNTIFS('SPC-CPN_Q&A'!#REF!,AV$1,'SPC-CPN_Q&A'!#REF!,'Writing assignments'!$C19,'SPC-CPN_Q&A'!$O:$O,"Recall") -> #REF! | BD19: =COUNTIFS('SPC-CPN_Q&A'!#REF!,AV$1,'SPC-CPN_Q&A'!#REF!,'Writing assignments'!$C19,'SPC-CPN_Q&A'!$O:$O,"Application") -> #REF! | BE19: =COUNTIFS('SPC-CPN_Q&A'!#REF!,AV$1,'SPC-CPN_Q&A'!#REF!,'Writing assignments'!$C19,'SPC-CPN_Q&A'!$O:$O,"Analysis") -> #REF! | BL19: =SUM(BM19:BO19) -> #REF! | BM19: =COUNTIFS('SPC-CPN_Q&A'!#REF!,BF$1,'SPC-CPN_Q&A'!#REF!,'Writing assignments'!$C19,'SPC-CPN_Q&A'!$O:$O,"Recall") -> #REF! | BN19: =COUNTIFS('SPC-CPN_Q&A'!#REF!,BF$1,'SPC-CPN_Q&A'!#REF!,'Writing assignments'!$C19,'SPC-CPN_Q&A'!$O:$O,"Application") -> #REF! | BO19: =COUNTIFS('SPC-CPN_Q&A'!#REF!,BF$1,'SPC-CPN_Q&A'!#REF!,'Writing assignments'!$C19,'SPC-CPN_Q&A'!$O:$O,"Analysis") -> #REF! | BV19: =SUM(BW19:BY19) -> #REF! | BW19: =COUNTIFS('SPC-CPN_Q&A'!#REF!,BP$1,'SPC-CPN_Q&A'!#REF!,'Writing assignments'!$C19,'SPC-CPN_Q&A'!$O:$O,"Recall") -> #REF! | BX19: =COUNTIFS('SPC-CPN_Q&A'!#REF!,BP$1,'SPC-CPN_Q&A'!#REF!,'Writing assignments'!$C19,'SPC-CPN_Q&A'!$O:$O,"Application") -> #REF! | BY19: =COUNTIFS('SPC-CPN_Q&A'!#REF!,BP$1,'SPC-CPN_Q&A'!#REF!,'Writing assignments'!$C19,'SPC-CPN_Q&A'!$O:$O,"Analysis") -> #REF! | CA19: 0
B20: Facilitate_Learning | C20: Model attributes that facilitate learning (e.g., caring, confidence, patience, integrity, respect, flexibility, resilience, enthusiasm) | E20: 1 | F20: 6 | G20: 3 | H20: =SUM(E20:G20) -> 10 | J20: =H20-SUM(N20,X20,AH20,AW20,BG20,BQ20,L20,CA20) -> 0 | K20: X | L20: 2 | N20: =SUM(O20:Q20) -> 0 | S20: =SUM(T20:V20) -> #REF! | T20: =COUNTIFS('SPC-CPN_Q&A'!#REF!,M$1,'SPC-CPN_Q&A'!#REF!,'Writing assignments'!$C20,'SPC-CPN_Q&A'!$O:$O,"Recall") -> #REF! | U20: =COUNTIFS('SPC-CPN_Q&A'!#REF!,M$1,'SPC-CPN_Q&A'!#REF!,'Writing assignments'!$C20,'SPC-CPN_Q&A'!$O:$O,"Application") -> #REF! | V20: =COUNTIFS('SPC-CPN_Q&A'!#REF!,M$1,'SPC-CPN_Q&A'!#REF!,'Writing assignments'!$C20,'SPC-CPN_Q&A'!$O:$O,"Analysis") -> #REF! | AC20: =SUM(AD20:AF20) -> #REF! | AD20: =COUNTIFS('SPC-CPN_Q&A'!#REF!,W$1,'SPC-CPN_Q&A'!#REF!,'Writing assignments'!$C20,'SPC-CPN_Q&A'!$O:$O,"Recall") -> #REF! | AE20: =COUNTIFS('SPC-CPN_Q&A'!#REF!,W$1,'SPC-CPN_Q&A'!#REF!,'Writing assignments'!$C20,'SPC-CPN_Q&A'!$O:$O,"Application") -> #REF! | AF20: =COUNTIFS('SPC-CPN_Q&A'!#REF!,W$1,'SPC-CPN_Q&A'!#REF!,'Writing assignments'!$C20,'SPC-CPN_Q&A'!$O:$O,"Analysis") -> #REF! | AG20: X | AH20: 3 | AI20: 0 | AJ20: 2 | AK20: 1 | AM20: =SUM(AN20:AP20) -> #REF! | AN20: =COUNTIFS('SPC-CPN_Q&A'!#REF!,AG$1,'SPC-CPN_Q&A'!#REF!,'Writing assignments'!$C20,'SPC-CPN_Q&A'!$O:$O,"Recall") -> #REF! | AO20: =COUNTIFS('SPC-CPN_Q&A'!#REF!,AG$1,'SPC-CPN_Q&A'!#REF!,'Writing assignments'!$C20,'SPC-CPN_Q&A'!$O:$O,"Application") -> #REF! | AP20: =COUNTIFS('SPC-CPN_Q&A'!#REF!,AG$1,'SPC-CPN_Q&A'!#REF!,'Writing assignments'!$C20,'SPC-CPN_Q&A'!$O:$O,"Analysis") -> #REF! | AS20: 0 | AT20: 0 | AU20: 0 | BB20: =SUM(BC20:BE20) -> #REF! | BC20: =COUNTIFS('SPC-CPN_Q&A'!#REF!,AV$1,'SPC-CPN_Q&A'!#REF!,'Writing assignments'!$C20,'SPC-CPN_Q&A'!$O:$O,"Recall") -> #REF! | BD20: =COUNTIFS('SPC-CPN_Q&A'!#REF!,AV$1,'SPC-CPN_Q&A'!#REF!,'Writing assignments'!$C20,'SPC-CPN_Q&A'!$O:$O,"Application") -> #REF! | BE20: =COUNTIFS('SPC-CPN_Q&A'!#REF!,AV$1,'SPC-CPN_Q&A'!#REF!,'Writing assignments'!$C20,'SPC-CPN_Q&A'!$O:$O,"Analysis") -> #REF! | BF20: X | BG20: 2 | BH20: 0 | BI20: 1 | BJ20: 1 | BL20: =SUM(BM20:BO20) -> #REF! | BM20: =COUNTIFS('SPC-CPN_Q&A'!#REF!,BF$1,'SPC-CPN_Q&A'!#REF!,'Writing assignments'!$C20,'SPC-CPN_Q&A'!$O:$O,"Recall") -> #REF! | BN20: =COUNTIFS('SPC-CPN_Q&A'!#REF!,BF$1,'SPC-CPN_Q&A'!#REF!,'Writing assignments'!$C20,'SPC-CPN_Q&A'!$O:$O,"Application") -> #REF! | BO20: =COUNTIFS('SPC-CPN_Q&A'!#REF!,BF$1,'SPC-CPN_Q&A'!#REF!,'Writing assignments'!$C20,'SPC-CPN_Q&A'!$O:$O,"Analysis") -> #REF! | BP20: X | BQ20: 3 | BR20: 1 | BS20: 1 | BT20: 1 | BV20: =SUM(BW20:BY20) -> #REF! | BW20: =COUNTIFS('SPC-CPN_Q&A'!#REF!,BP$1,'SPC-CPN_Q&A'!#REF!,'Writing assignments'!$C20,'SPC-CPN_Q&A'!$O:$O,"Recall") -> #REF! | BX20: =COUNTIFS('SPC-CPN_Q&A'!#REF!,BP$1,'SPC-CPN_Q&A'!#REF!,'Writing assignments'!$C20,'SPC-CPN_Q&A'!$O:$O,"Application") -> #REF! | BY20: =COUNTIFS('SPC-CPN_Q&A'!#REF!,BP$1,'SPC-CPN_Q&A'!#REF!,'Writing assignments'!$C20,'SPC-CPN_Q&A'!$O:$O,"Analysis") -> #REF! | CA20: 0
B21: Facilitate_Learning | C21: Develop and maintain effective working relationships with healthcare and education partners | E21: 1 | F21: 6 | G21: 3 | H21: =SUM(E21:G21) -> 10 | J21: =H21-SUM(N21,X21,AH21,AW21,BG21,BQ21,L21,CA21) -> 0 | L21: 0 | N21: =SUM(O21:Q21) -> 0 | S21: =SUM(T21:V21) -> #REF! | T21: =COUNTIFS('SPC-CPN_Q&A'!#REF!,M$1,'SPC-CPN_Q&A'!#REF!,'Writing assignments'!$C21,'SPC-CPN_Q&A'!$O:$O,"Recall") -> #REF! | U21: =COUNTIFS('SPC-CPN_Q&A'!#REF!,M$1,'SPC-CPN_Q&A'!#REF!,'Writing assignments'!$C21,'SPC-CPN_Q&A'!$O:$O,"Application") -> #REF! | V21: =COUNTIFS('SPC-CPN_Q&A'!#REF!,M$1,'SPC-CPN_Q&A'!#REF!,'Writing assignments'!$C21,'SPC-CPN_Q&A'!$O:$O,"Analysis") -> #REF! | W21: X | X21: 3 | Y21: 1 | Z21: 1 | AA21: 1 | AC21: =SUM(AD21:AF21) -> #REF! | AD21: =COUNTIFS('SPC-CPN_Q&A'!#REF!,W$1,'SPC-CPN_Q&A'!#REF!,'Writing assignments'!$C21,'SPC-CPN_Q&A'!$O:$O,"Recall") -> #REF! | AE21: =COUNTIFS('SPC-CPN_Q&A'!#REF!,W$1,'SPC-CPN_Q&A'!#REF!,'Writing assignments'!$C21,'SPC-CPN_Q&A'!$O:$O,"Application") -> #REF! | AF21: =COUNTIFS('SPC-CPN_Q&A'!#REF!,W$1,'SPC-CPN_Q&A'!#REF!,'Writing assignments'!$C21,'SPC-CPN_Q&A'!$O:$O,"Analysis") -> #REF! | AG21: X | AH21: 3 | AI21: 0 | AJ21: 2 | AK21: 1 | AM21: =SUM(AN21:AP21) -> #REF! | AN21: =COUNTIFS('SPC-CPN_Q&A'!#REF!,AG$1,'SPC-CPN_Q&A'!#REF!,'Writing assignments'!$C21,'SPC-CPN_Q&A'!$O:$O,"Recall") -> #REF! | AO21: =COUNTIFS('SPC-CPN_Q&A'!#REF!,AG$1,'SPC-CPN_Q&A'!#REF!,'Writing assignments'!$C21,'SPC-CPN_Q&A'!$O:$O,"Application") -> #REF! | AP21: =COUNTIFS('SPC-CPN_Q&A'!#REF!,AG$1,'SPC-CPN_Q&A'!#REF!,'Writing assignments'!$C21,'SPC-CPN_Q&A'!$O:$O,"Analysis") -> #REF! | AV21: X | AW21: 2 | AX21: 0 | AY21: 1 | AZ21: 1 | BB21: =SUM(BC21:BE21) -> #REF! | BC21: =COUNTIFS('SPC-CPN_Q&A'!#REF!,AV$1,'SPC-CPN_Q&A'!#REF!,'Writing assignments'!$C21,'SPC-CPN_Q&A'!$O:$O,"Recall") -> #REF! | BD21: =COUNTIFS('SPC-CPN_Q&A'!#REF!,AV$1,'SPC-CPN_Q&A'!#REF!,'Writing assignments'!$C21,'SPC-CPN_Q&A'!$O:$O,"Application") -> #REF! | BE21: =COUNTIFS('SPC-CPN_Q&A'!#REF!,AV$1,'SPC-CPN_Q&A'!#REF!,'Writing assignments'!$C21,'SPC-CPN_Q&A'!$O:$O,"Analysis") -> #REF! | BF21: X | BG21: 2 | BH21: 0 | BI21: 2 | BJ21: 0 | BL21: =SUM(BM21:BO21) -> #REF! | BM21: =COUNTIFS('SPC-CPN_Q&A'!#REF!,BF$1,'SPC-CPN_Q&A'!#REF!,'Writing assignments'!$C21,'SPC-CPN_Q&A'!$O:$O,"Recall") -> #REF! | BN21: =COUNTIFS('SPC-CPN_Q&A'!#REF!,BF$1,'SPC-CPN_Q&A'!#REF!,'Writing assignments'!$C21,'SPC-CPN_Q&A'!$O:$O,"Application") -> #REF! | BO21: =COUNTIFS('SPC-CPN_Q&A'!#REF!,BF$1,'SPC-CPN_Q&A'!#REF!,'Writing assignments'!$C21,'SPC-CPN_Q&A'!$O:$O,"Analysis") -> #REF! | BV21: =SUM(BW21:BY21) -> #REF! | BW21: =COUNTIFS('SPC-CPN_Q&A'!#REF!,BP$1,'SPC-CPN_Q&A'!#REF!,'Writing assignments'!$C21,'SPC-CPN_Q&A'!$O:$O,"Recall") -> #REF! | BX21: =COUNTIFS('SPC-CPN_Q&A'!#REF!,BP$1,'SPC-CPN_Q&A'!#REF!,'Writing assignments'!$C21,'SPC-CPN_Q&A'!$O:$O,"Application") -> #REF! | BY21: =COUNTIFS('SPC-CPN_Q&A'!#REF!,BP$1,'SPC-CPN_Q&A'!#REF!,'Writing assignments'!$C21,'SPC-CPN_Q&A'!$O:$O,"Analysis") -> #REF! | CA21: 0
B22: Facilitate_Learning | C22: Apply concepts of evidence-based practice in nursing to guide teaching | E22: 1 | F22: 6 | G22: 3 | H22: =SUM(E22:G22) -> 10 | J22: =H22-SUM(N22,X22,AH22,AW22,BG22,BQ22,L22,CA22) -> 0 | K22: X | L22: 1 | M22: X | N22: =SUM(O22:Q22) -> 1 | P22: 1 | S22: =SUM(T22:V22) -> #REF! | T22: =COUNTIFS('SPC-CPN_Q&A'!#REF!,M$1,'SPC-CPN_Q&A'!#REF!,'Writing assignments'!$C22,'SPC-CPN_Q&A'!$O:$O,"Recall") -> #REF! | U22: =COUNTIFS('SPC-CPN_Q&A'!#REF!,M$1,'SPC-CPN_Q&A'!#REF!,'Writing assignments'!$C22,'SPC-CPN_Q&A'!$O:$O,"Application") -> #REF! | V22: =COUNTIFS('SPC-CPN_Q&A'!#REF!,M$1,'SPC-CPN_Q&A'!#REF!,'Writing assignments'!$C22,'SPC-CPN_Q&A'!$O:$O,"Analysis") -> #REF! | W22: X | X22: 3 | Y22: 0 | Z22: 2 | AA22: 1 | AC22: =SUM(AD22:AF22) -> #REF! | AD22: =COUNTIFS('SPC-CPN_Q&A'!#REF!,W$1,'SPC-CPN_Q&A'!#REF!,'Writing assignments'!$C22,'SPC-CPN_Q&A'!$O:$O,"Recall") -> #REF! | AE22: =COUNTIFS('SPC-CPN_Q&A'!#REF!,W$1,'SPC-CPN_Q&A'!#REF!,'Writing assignments'!$C22,'SPC-CPN_Q&A'!$O:$O,"Application") -> #REF! | AF22: =COUNTIFS('SPC-CPN_Q&A'!#REF!,W$1,'SPC-CPN_Q&A'!#REF!,'Writing assignments'!$C22,'SPC-CPN_Q&A'!$O:$O,"Analysis") -> #REF! | AM22: =SUM(AN22:AP22) -> #REF! | AN22: =COUNTIFS('SPC-CPN_Q&A'!#REF!,AG$1,'SPC-CPN_Q&A'!#REF!,'Writing assignments'!$C22,'SPC-CPN_Q&A'!$O:$O,"Recall") -> #REF! | AO22: =COUNTIFS('SPC-CPN_Q&A'!#REF!,AG$1,'SPC-CPN_Q&A'!#REF!,'Writing assignments'!$C22,'SPC-CPN_Q&A'!$O:$O,"Application") -> #REF! | AP22: =COUNTIFS('SPC-CPN_Q&A'!#REF!,AG$1,'SPC-CPN_Q&A'!#REF!,'Writing assignments'!$C22,'SPC-CPN_Q&A'!$O:$O,"Analysis") -> #REF! | AQ22: X | AR22: 1 | AS22: 0 | AT22: 1 | AU22: 0 | BB22: =SUM(BC22:BE22) -> #REF! | BC22: =COUNTIFS('SPC-CPN_Q&A'!#REF!,AV$1,'SPC-CPN_Q&A'!#REF!,'Writing assignments'!$C22,'SPC-CPN_Q&A'!$O:$O,"Recall") -> #REF! | BD22: =COUNTIFS('SPC-CPN_Q&A'!#REF!,AV$1,'SPC-CPN_Q&A'!#REF!,'Writing assignments'!$C22,'SPC-CPN_Q&A'!$O:$O,"Application") -> #REF! | BE22: =COUNTIFS('SPC-CPN_Q&A'!#REF!,AV$1,'SPC-CPN_Q&A'!#REF!,'Writing assignments'!$C22,'SPC-CPN_Q&A'!$O:$O,"Analysis") -> #REF! | BF22: X | BG22: 2 | BH22: 1 | BI22: 1 | BJ22: 0 | BL22: =SUM(BM22:BO22) -> #REF! | BM22: =COUNTIFS('SPC-CPN_Q&A'!#REF!,BF$1,'SPC-CPN_Q&A'!#REF!,'Writing assignments'!$C22,'SPC-CPN_Q&A'!$O:$O,"Recall") -> #REF! | BN22: =COUNTIFS('SPC-CPN_Q&A'!#REF!,BF$1,'SPC-CPN_Q&A'!#REF!,'Writing assignments'!$C22,'SPC-CPN_Q&A'!$O:$O,"Application") -> #REF! | BO22: =COUNTIFS('SPC-CPN_Q&A'!#REF!,BF$1,'SPC-CPN_Q&A'!#REF!,'Writing assignments'!$C22,'SPC-CPN_Q&A'!$O:$O,"Analysis") -> #REF! | BP22: X | BQ22: 3 | BR22: 0 | BS22: 2 | BT22: 1 | BV22: =SUM(BW22:BY22) -> #REF! | BW22: =COUNTIFS('SPC-CPN_Q&A'!#REF!,BP$1,'SPC-CPN_Q&A'!#REF!,'Writing assignments'!$C22,'SPC-CPN_Q&A'!$O:$O,"Recall") -> #REF! | BX22: =COUNTIFS('SPC-CPN_Q&A'!#REF!,BP$1,'SPC-CPN_Q&A'!#REF!,'Writing assignments'!$C22,'SPC-CPN_Q&A'!$O:$O,"Application") -> #REF! | BY22: =COUNTIFS('SPC-CPN_Q&A'!#REF!,BP$1,'SPC-CPN_Q&A'!#REF!,'Writing assignments'!$C22,'SPC-CPN_Q&A'!$O:$O,"Analysis") -> #REF! | CA22: 0
B23: Facilitate_Learner_Development_and_Socialization | C23: Identify learner attributes and needs based on consideration of learners' diversity | E23: 1 | F23: 4 | G23: 2 | H23: =SUM(E23:G23) -> 7 | J23: =H23-SUM(N23,X23,AH23,AW23,BG23,BQ23,L23,CA23) -> 0 | K23: X | L23: 1 | N23: =SUM(O23:Q23) -> 0 | S23: =SUM(T23:V23) -> #REF! | T23: =COUNTIFS('SPC-CPN_Q&A'!#REF!,M$1,'SPC-CPN_Q&A'!#REF!,'Writing assignments'!$C23,'SPC-CPN_Q&A'!$O:$O,"Recall") -> #REF! | U23: =COUNTIFS('SPC-CPN_Q&A'!#REF!,M$1,'SPC-CPN_Q&A'!#REF!,'Writing assignments'!$C23,'SPC-CPN_Q&A'!$O:$O,"Application") -> #REF! | V23: =COUNTIFS('SPC-CPN_Q&A'!#REF!,M$1,'SPC-CPN_Q&A'!#REF!,'Writing assignments'!$C23,'SPC-CPN_Q&A'!$O:$O,"Analysis") -> #REF! | W23: X | X23: 2 | Y23: 0 | Z23: 1 | AA23: 1 | AC23: =SUM(AD23:AF23) -> #REF! | AD23: =COUNTIFS('SPC-CPN_Q&A'!#REF!,W$1,'SPC-CPN_Q&A'!#REF!,'Writing assignments'!$C23,'SPC-CPN_Q&A'!$O:$O,"Recall") -> #REF! | AE23: =COUNTIFS('SPC-CPN_Q&A'!#REF!,W$1,'SPC-CPN_Q&A'!#REF!,'Writing assignments'!$C23,'SPC-CPN_Q&A'!$O:$O,"Application") -> #REF! | AF23: =COUNTIFS('SPC-CPN_Q&A'!#REF!,W$1,'SPC-CPN_Q&A'!#REF!,'Writing assignments'!$C23,'SPC-CPN_Q&A'!$O:$O,"Analysis") -> #REF! | AG23: X | AH23: 2 | AI23: 1 | AJ23: 1 | AM23: =SUM(AN23:AP23) -> #REF! | AN23: =COUNTIFS('SPC-CPN_Q&A'!#REF!,AG$1,'SPC-CPN_Q&A'!#REF!,'Writing assignments'!$C23,'SPC-CPN_Q&A'!$O:$O,"Recall") -> #REF! | AO23: =COUNTIFS('SPC-CPN_Q&A'!#REF!,AG$1,'SPC-CPN_Q&A'!#REF!,'Writing assignments'!$C23,'SPC-CPN_Q&A'!$O:$O,"Application") -> #REF! | AP23: =COUNTIFS('SPC-CPN_Q&A'!#REF!,AG$1,'SPC-CPN_Q&A'!#REF!,'Writing assignments'!$C23,'SPC-CPN_Q&A'!$O:$O,"Analysis") -> #REF! | AR23: 0 | BB23: =SUM(BC23:BE23) -> #REF! | BC23: =COUNTIFS('SPC-CPN_Q&A'!#REF!,AV$1,'SPC-CPN_Q&A'!#REF!,'Writing assignments'!$C23,'SPC-CPN_Q&A'!$O:$O,"Recall") -> #REF! | BD23: =COUNTIFS('SPC-CPN_Q&A'!#REF!,AV$1,'SPC-CPN_Q&A'!#REF!,'Writing assignments'!$C23,'SPC-CPN_Q&A'!$O:$O,"Application") -> #REF! | BE23: =COUNTIFS('SPC-CPN_Q&A'!#REF!,AV$1,'SPC-CPN_Q&A'!#REF!,'Writing assignments'!$C23,'SPC-CPN_Q&A'!$O:$O,"Analysis") -> #REF! | BL23: =SUM(BM23:BO23) -> #REF! | BM23: =COUNTIFS('SPC-CPN_Q&A'!#REF!,BF$1,'SPC-CPN_Q&A'!#REF!,'Writing assignments'!$C23,'SPC-CPN_Q&A'!$O:$O,"Recall") -> #REF! | BN23: =COUNTIFS('SPC-CPN_Q&A'!#REF!,BF$1,'SPC-CPN_Q&A'!#REF!,'Writing assignments'!$C23,'SPC-CPN_Q&A'!$O:$O,"Application") -> #REF! | BO23: =COUNTIFS('SPC-CPN_Q&A'!#REF!,BF$1,'SPC-CPN_Q&A'!#REF!,'Writing assignments'!$C23,'SPC-CPN_Q&A'!$O:$O,"Analysis") -> #REF! | BP23: X | BQ23: 2 | BR23: 0 | BS23: 1 | BT23: 1 | BV23: =SUM(BW23:BY23) -> #REF! | BW23: =COUNTIFS('SPC-CPN_Q&A'!#REF!,BP$1,'SPC-CPN_Q&A'!#REF!,'Writing assignments'!$C23,'SPC-CPN_Q&A'!$O:$O,"Recall") -> #REF! | BX23: =COUNTIFS('SPC-CPN_Q&A'!#REF!,BP$1,'SPC-CPN_Q&A'!#REF!,'Writing assignments'!$C23,'SPC-CPN_Q&A'!$O:$O,"Application") -> #REF! | BY23: =COUNTIFS('SPC-CPN_Q&A'!#REF!,BP$1,'SPC-CPN_Q&A'!#REF!,'Writing assignments'!$C23,'SPC-CPN_Q&A'!$O:$O,"Analysis") -> #REF! | CA23: 0
B24: Facilitate_Learner_Development_and_Socialization | C24: Identify learner attributes and needs based on consideration of learners' social determinants of learning (i.e., physical health, psychosocial health, economic stability, physical environment, social environment, and self- motivation) | E24: 2 | F24: 6 | G24: 3 | H24: =SUM(E24:G24) -> 11 | J24: =H24-SUM(N24,X24,AH24,AW24,BG24,BQ24,L24,CA24) -> 0 | K24: X | L24: 1 | M24: X | N24: =SUM(O24:Q24) -> 2 | O24: 1 | P24: 1 | S24: =SUM(T24:V24) -> #REF! | T24: =COUNTIFS('SPC-CPN_Q&A'!#REF!,M$1,'SPC-CPN_Q&A'!#REF!,'Writing assignments'!$C24,'SPC-CPN_Q&A'!$O:$O,"Recall") -> #REF! | U24: =COUNTIFS('SPC-CPN_Q&A'!#REF!,M$1,'SPC-CPN_Q&A'!#REF!,'Writing assignments'!$C24,'SPC-CPN_Q&A'!$O:$O,"Application") -> #REF! | V24: =COUNTIFS('SPC-CPN_Q&A'!#REF!,M$1,'SPC-CPN_Q&A'!#REF!,'Writing assignments'!$C24,'SPC-CPN_Q&A'!$O:$O,"Analysis") -> #REF! | W24: X | X24: 2 | Y24: 1 | Z24: 1 | AA24: 0 | AC24: =SUM(AD24:AF24) -> #REF! | AD24: =COUNTIFS('SPC-CPN_Q&A'!#REF!,W$1,'SPC-CPN_Q&A'!#REF!,'Writing assignments'!$C24,'SPC-CPN_Q&A'!$O:$O,"Recall") -> #REF! | AE24: =COUNTIFS('SPC-CPN_Q&A'!#REF!,W$1,'SPC-CPN_Q&A'!#REF!,'Writing assignments'!$C24,'SPC-CPN_Q&A'!$O:$O,"Application") -> #REF! | AF24: =COUNTIFS('SPC-CPN_Q&A'!#REF!,W$1,'SPC-CPN_Q&A'!#REF!,'Writing assignments'!$C24,'SPC-CPN_Q&A'!$O:$O,"Analysis") -> #REF! | AG24: X | AH24: 2 | AI24: 0 | AJ24: 1 | AK24: 1 | AM24: =SUM(AN24:AP24) -> #REF! | AN24: =COUNTIFS('SPC-CPN_Q&A'!#REF!,AG$1,'SPC-CPN_Q&A'!#REF!,'Writing assignments'!$C24,'SPC-CPN_Q&A'!$O:$O,"Recall") -> #REF! | AO24: =COUNTIFS('SPC-CPN_Q&A'!#REF!,AG$1,'SPC-CPN_Q&A'!#REF!,'Writing assignments'!$C24,'SPC-CPN_Q&A'!$O:$O,"Application") -> #REF! | AP24: =COUNTIFS('SPC-CPN_Q&A'!#REF!,AG$1,'SPC-CPN_Q&A'!#REF!,'Writing assignments'!$C24,'SPC-CPN_Q&A'!$O:$O,"Analysis") -> #REF! | AQ24: X | AR24: 2 | AS24: 1 | AT24: 1 | AU24: 0 | BB24: =SUM(BC24:BE24) -> #REF! | BC24: =COUNTIFS('SPC-CPN_Q&A'!#REF!,AV$1,'SPC-CPN_Q&A'!#REF!,'Writing assignments'!$C24,'SPC-CPN_Q&A'!$O:$O,"Recall") -> #REF! | BD24: =COUNTIFS('SPC-CPN_Q&A'!#REF!,AV$1,'SPC-CPN_Q&A'!#REF!,'Writing assignments'!$C24,'SPC-CPN_Q&A'!$O:$O,"Application") -> #REF! | BE24: =COUNTIFS('SPC-CPN_Q&A'!#REF!,AV$1,'SPC-CPN_Q&A'!#REF!,'Writing assignments'!$C24,'SPC-CPN_Q&A'!$O:$O,"Analysis") -> #REF! | BF24: X | BG24: 2 | BH24: 0 | BI24: 1 | BJ24: 1 | BL24: =SUM(BM24:BO24) -> #REF! | BM24: =COUNTIFS('SPC-CPN_Q&A'!#REF!,BF$1,'SPC-CPN_Q&A'!#REF!,'Writing assignments'!$C24,'SPC-CPN_Q&A'!$O:$O,"Recall") -> #REF! | BN24: =COUNTIFS('SPC-CPN_Q&A'!#REF!,BF$1,'SPC-CPN_Q&A'!#REF!,'Writing assignments'!$C24,'SPC-CPN_Q&A'!$O:$O,"Application") -> #REF! | BO24: =COUNTIFS('SPC-CPN_Q&A'!#REF!,BF$1,'SPC-CPN_Q&A'!#REF!,'Writing assignments'!$C24,'SPC-CPN_Q&A'!$O:$O,"Analysis") -> #REF! | BP24: X | BQ24: 2 | BR24: 0 | BS24: 1 | BT24: 1 | BV24: =SUM(BW24:BY24) -> #REF! | BW24: =COUNTIFS('SPC-CPN_Q&A'!#REF!,BP$1,'SPC-CPN_Q&A'!#REF!,'Writing assignments'!$C24,'SPC-CPN_Q&A'!$O:$O,"Recall") -> #REF! | BX24: =COUNTIFS('SPC-CPN_Q&A'!#REF!,BP$1,'SPC-CPN_Q&A'!#REF!,'Writing assignments'!$C24,'SPC-CPN_Q&A'!$O:$O,"Application") -> #REF! | BY24: =COUNTIFS('SPC-CPN_Q&A'!#REF!,BP$1,'SPC-CPN_Q&A'!#REF!,'Writing assignments'!$C24,'SPC-CPN_Q&A'!$O:$O,"Analysis") -> #REF! | CA24: 0
B25: Facilitate_Learner_Development_and_Socialization | C25: Identify learner attributes and needs based on consideration of learners' past clinical, educational, and life experiences | E25: 1 | F25: 4 | G25: 2 | H25: =SUM(E25:G25) -> 7 | J25: =H25-SUM(N25,X25,AH25,AW25,BG25,BQ25,L25,CA25) -> 0 | K25: X | L25: 1 | M25: X | N25: =SUM(O25:Q25) -> 1 | P25: 1 | S25: =SUM(T25:V25) -> #REF! | T25: =COUNTIFS('SPC-CPN_Q&A'!#REF!,M$1,'SPC-CPN_Q&A'!#REF!,'Writing assignments'!$C25,'SPC-CPN_Q&A'!$O:$O,"Recall") -> #REF! | U25: =COUNTIFS('SPC-CPN_Q&A'!#REF!,M$1,'SPC-CPN_Q&A'!#REF!,'Writing assignments'!$C25,'SPC-CPN_Q&A'!$O:$O,"Application") -> #REF! | V25: =COUNTIFS('SPC-CPN_Q&A'!#REF!,M$1,'SPC-CPN_Q&A'!#REF!,'Writing assignments'!$C25,'SPC-CPN_Q&A'!$O:$O,"Analysis") -> #REF! | AC25: =SUM(AD25:AF25) -> #REF! | AD25: =COUNTIFS('SPC-CPN_Q&A'!#REF!,W$1,'SPC-CPN_Q&A'!#REF!,'Writing assignments'!$C25,'SPC-CPN_Q&A'!$O:$O,"Recall") -> #REF! | AE25: =COUNTIFS('SPC-CPN_Q&A'!#REF!,W$1,'SPC-CPN_Q&A'!#REF!,'Writing assignments'!$C25,'SPC-CPN_Q&A'!$O:$O,"Application") -> #REF! | AF25: =COUNTIFS('SPC-CPN_Q&A'!#REF!,W$1,'SPC-CPN_Q&A'!#REF!,'Writing assignments'!$C25,'SPC-CPN_Q&A'!$O:$O,"Analysis") -> #REF! | AG25: X | AH25: 3 | AI25: 1 | AJ25: 1 | AK25: 1 | AM25: =SUM(AN25:AP25) -> #REF! | AN25: =COUNTIFS('SPC-CPN_Q&A'!#REF!,AG$1,'SPC-CPN_Q&A'!#REF!,'Writing assignments'!$C25,'SPC-CPN_Q&A'!$O:$O,"Recall") -> #REF! | AO25: =COUNTIFS('SPC-CPN_Q&A'!#REF!,AG$1,'SPC-CPN_Q&A'!#REF!,'Writing assignments'!$C25,'SPC-CPN_Q&A'!$O:$O,"Application") -> #REF! | AP25: =COUNTIFS('SPC-CPN_Q&A'!#REF!,AG$1,'SPC-CPN_Q&A'!#REF!,'Writing assignments'!$C25,'SPC-CPN_Q&A'!$O:$O,"Analysis") -> #REF! | AR25: 0 | BB25: =SUM(BC25:BE25) -> #REF! | BC25: =COUNTIFS('SPC-CPN_Q&A'!#REF!,AV$1,'SPC-CPN_Q&A'!#REF!,'Writing assignments'!$C25,'SPC-CPN_Q&A'!$O:$O,"Recall") -> #REF! | BD25: =COUNTIFS('SPC-CPN_Q&A'!#REF!,AV$1,'SPC-CPN_Q&A'!#REF!,'Writing assignments'!$C25,'SPC-CPN_Q&A'!$O:$O,"Application") -> #REF! | BE25: =COUNTIFS('SPC-CPN_Q&A'!#REF!,AV$1,'SPC-CPN_Q&A'!#REF!,'Writing assignments'!$C25,'SPC-CPN_Q&A'!$O:$O,"Analysis") -> #REF! | BF25: X | BG25: 2 | BH25: 0 | BI25: 1 | BJ25: 1 | BL25: =SUM(BM25:BO25) -> #REF! | BM25: =COUNTIFS('SPC-CPN_Q&A'!#REF!,BF$1,'SPC-CPN_Q&A'!#REF!,'Writing assignments'!$C25,'SPC-CPN_Q&A'!$O:$O,"Recall") -> #REF! | BN25: =COUNTIFS('SPC-CPN_Q&A'!#REF!,BF$1,'SPC-CPN_Q&A'!#REF!,'Writing assignments'!$C25,'SPC-CPN_Q&A'!$O:$O,"Application") -> #REF! | BO25: =COUNTIFS('SPC-CPN_Q&A'!#REF!,BF$1,'SPC-CPN_Q&A'!#REF!,'Writing assignments'!$C25,'SPC-CPN_Q&A'!$O:$O,"Analysis") -> #REF! | BV25: =SUM(BW25:BY25) -> #REF! | BW25: =COUNTIFS('SPC-CPN_Q&A'!#REF!,BP$1,'SPC-CPN_Q&A'!#REF!,'Writing assignments'!$C25,'SPC-CPN_Q&A'!$O:$O,"Recall") -> #REF! | BX25: =COUNTIFS('SPC-CPN_Q&A'!#REF!,BP$1,'SPC-CPN_Q&A'!#REF!,'Writing assignments'!$C25,'SPC-CPN_Q&A'!$O:$O,"Application") -> #REF! | BY25: =COUNTIFS('SPC-CPN_Q&A'!#REF!,BP$1,'SPC-CPN_Q&A'!#REF!,'Writing assignments'!$C25,'SPC-CPN_Q&A'!$O:$O,"Analysis") -> #REF! | CA25: 0
B26: Facilitate_Learner_Development_and_Socialization | C26: Facilitate access to various resources to support diverse learners | E26: 2 | F26: 5 | G26: 2 | H26: =SUM(E26:G26) -> 9 | J26: =H26-SUM(N26,X26,AH26,AW26,BG26,BQ26,L26,CA26) -> 0 | L26: 0 | M26: X | N26: =SUM(O26:Q26) -> 3 | P26: 2 | Q26: 1 | S26: =SUM(T26:V26) -> #REF! | T26: =COUNTIFS('SPC-CPN_Q&A'!#REF!,M$1,'SPC-CPN_Q&A'!#REF!,'Writing assignments'!$C26,'SPC-CPN_Q&A'!$O:$O,"Recall") -> #REF! | U26: =COUNTIFS('SPC-CPN_Q&A'!#REF!,M$1,'SPC-CPN_Q&A'!#REF!,'Writing assignments'!$C26,'SPC-CPN_Q&A'!$O:$O,"Application") -> #REF! | V26: =COUNTIFS('SPC-CPN_Q&A'!#REF!,M$1,'SPC-CPN_Q&A'!#REF!,'Writing assignments'!$C26,'SPC-CPN_Q&A'!$O:$O,"Analysis") -> #REF! | AC26: =SUM(AD26:AF26) -> #REF! | AD26: =COUNTIFS('SPC-CPN_Q&A'!#REF!,W$1,'SPC-CPN_Q&A'!#REF!,'Writing assignments'!$C26,'SPC-CPN_Q&A'!$O:$O,"Recall") -> #REF! | AE26: =COUNTIFS('SPC-CPN_Q&A'!#REF!,W$1,'SPC-CPN_Q&A'!#REF!,'Writing assignments'!$C26,'SPC-CPN_Q&A'!$O:$O,"Application") -> #REF! | AF26: =COUNTIFS('SPC-CPN_Q&A'!#REF!,W$1,'SPC-CPN_Q&A'!#REF!,'Writing assignments'!$C26,'SPC-CPN_Q&A'!$O:$O,"Analysis") -> #REF! | AG26: X | AH26: 3 | AI26: 0 | AJ26: 2 | AK26: 1 | AM26: =SUM(AN26:AP26) -> #REF! | AN26: =COUNTIFS('SPC-CPN_Q&A'!#REF!,AG$1,'SPC-CPN_Q&A'!#REF!,'Writing assignments'!$C26,'SPC-CPN_Q&A'!$O:$O,"Recall") -> #REF! | AO26: =COUNTIFS('SPC-CPN_Q&A'!#REF!,AG$1,'SPC-CPN_Q&A'!#REF!,'Writing assignments'!$C26,'SPC-CPN_Q&A'!$O:$O,"Application") -> #REF! | AP26: =COUNTIFS('SPC-CPN_Q&A'!#REF!,AG$1,'SPC-CPN_Q&A'!#REF!,'Writing assignments'!$C26,'SPC-CPN_Q&A'!$O:$O,"Analysis") -> #REF! | AQ26: X | AR26: 3 | AS26: 1 | AT26: 1 | AU26: 1 | BB26: =SUM(BC26:BE26) -> #REF! | BC26: =COUNTIFS('SPC-CPN_Q&A'!#REF!,AV$1,'SPC-CPN_Q&A'!#REF!,'Writing assignments'!$C26,'SPC-CPN_Q&A'!$O:$O,"Recall") -> #REF! | BD26: =COUNTIFS('SPC-CPN_Q&A'!#REF!,AV$1,'SPC-CPN_Q&A'!#REF!,'Writing assignments'!$C26,'SPC-CPN_Q&A'!$O:$O,"Application") -> #REF! | BE26: =COUNTIFS('SPC-CPN_Q&A'!#REF!,AV$1,'SPC-CPN_Q&A'!#REF!,'Writing assignments'!$C26,'SPC-CPN_Q&A'!$O:$O,"Analysis") -> #REF! | BF26: X | BG26: 3 | BH26: 1 | BI26: 2 | BJ26: 0 | BL26: =SUM(BM26:BO26) -> #REF! | BM26: =COUNTIFS('SPC-CPN_Q&A'!#REF!,BF$1,'SPC-CPN_Q&A'!#REF!,'Writing assignments'!$C26,'SPC-CPN_Q&A'!$O:$O,"Recall") -> #REF! | BN26: =COUNTIFS('SPC-CPN_Q&A'!#REF!,BF$1,'SPC-CPN_Q&A'!#REF!,'Writing assignments'!$C26,'SPC-CPN_Q&A'!$O:$O,"Application") -> #REF! | BO26: =COUNTIFS('SPC-CPN_Q&A'!#REF!,BF$1,'SPC-CPN_Q&A'!#REF!,'Writing assignments'!$C26,'SPC-CPN_Q&A'!$O:$O,"Analysis") -> #REF! | BV26: =SUM(BW26:BY26) -> #REF! | BW26: =COUNTIFS('SPC-CPN_Q&A'!#REF!,BP$1,'SPC-CPN_Q&A'!#REF!,'Writing assignments'!$C26,'SPC-CPN_Q&A'!$O:$O,"Recall") -> #REF! | BX26: =COUNTIFS('SPC-CPN_Q&A'!#REF!,BP$1,'SPC-CPN_Q&A'!#REF!,'Writing assignments'!$C26,'SPC-CPN_Q&A'!$O:$O,"Application") -> #REF! | BY26: =COUNTIFS('SPC-CPN_Q&A'!#REF!,BP$1,'SPC-CPN_Q&A'!#REF!,'Writing assignments'!$C26,'SPC-CPN_Q&A'!$O:$O,"Analysis") -> #REF! | CA26: 0
B27: Facilitate_Learner_Development_and_Socialization | C27: Assist learners to identify and develop a plan to meet professional goals | E27: 1 | F27: 5 | G27: 3 | H27: =SUM(E27:G27) -> 9 | J27: =H27-SUM(N27,X27,AH27,AW27,BG27,BQ27,L27,CA27) -> 0 | K27: X | L27: 1 | M27: X | N27: =SUM(O27:Q27) -> 2 | P27: 2 | S27: =SUM(T27:V27) -> #REF! | T27: =COUNTIFS('SPC-CPN_Q&A'!#REF!,M$1,'SPC-CPN_Q&A'!#REF!,'Writing assignments'!$C27,'SPC-CPN_Q&A'!$O:$O,"Recall") -> #REF! | U27: =COUNTIFS('SPC-CPN_Q&A'!#REF!,M$1,'SPC-CPN_Q&A'!#REF!,'Writing assignments'!$C27,'SPC-CPN_Q&A'!$O:$O,"Application") -> #REF! | V27: =COUNTIFS('SPC-CPN_Q&A'!#REF!,M$1,'SPC-CPN_Q&A'!#REF!,'Writing assignments'!$C27,'SPC-CPN_Q&A'!$O:$O,"Analysis") -> #REF! | W27: X | X27: 2 | Y27: 0 | Z27: 1 | AA27: 1 | AC27: =SUM(AD27:AF27) -> #REF! | AD27: =COUNTIFS('SPC-CPN_Q&A'!#REF!,W$1,'SPC-CPN_Q&A'!#REF!,'Writing assignments'!$C27,'SPC-CPN_Q&A'!$O:$O,"Recall") -> #REF! | AE27: =COUNTIFS('SPC-CPN_Q&A'!#REF!,W$1,'SPC-CPN_Q&A'!#REF!,'Writing assignments'!$C27,'SPC-CPN_Q&A'!$O:$O,"Application") -> #REF! | AF27: =COUNTIFS('SPC-CPN_Q&A'!#REF!,W$1,'SPC-CPN_Q&A'!#REF!,'Writing assignments'!$C27,'SPC-CPN_Q&A'!$O:$O,"Analysis") -> #REF! | AM27: =SUM(AN27:AP27) -> #REF! | AN27: =COUNTIFS('SPC-CPN_Q&A'!#REF!,AG$1,'SPC-CPN_Q&A'!#REF!,'Writing assignments'!$C27,'SPC-CPN_Q&A'!$O:$O,"Recall") -> #REF! | AO27: =COUNTIFS('SPC-CPN_Q&A'!#REF!,AG$1,'SPC-CPN_Q&A'!#REF!,'Writing assignments'!$C27,'SPC-CPN_Q&A'!$O:$O,"Application") -> #REF! | AP27: =COUNTIFS('SPC-CPN_Q&A'!#REF!,AG$1,'SPC-CPN_Q&A'!#REF!,'Writing assignments'!$C27,'SPC-CPN_Q&A'!$O:$O,"Analysis") -> #REF! | AQ27: X | AR27: 2 | AS27: 0 | AT27: 1 | AU27: 1 | BB27: =SUM(BC27:BE27) -> #REF! | BC27: =COUNTIFS('SPC-CPN_Q&A'!#REF!,AV$1,'SPC-CPN_Q&A'!#REF!,'Writing assignments'!$C27,'SPC-CPN_Q&A'!$O:$O,"Recall") -> #REF! | BD27: =COUNTIFS('SPC-CPN_Q&A'!#REF!,AV$1,'SPC-CPN_Q&A'!#REF!,'Writing assignments'!$C27,'SPC-CPN_Q&A'!$O:$O,"Application") -> #REF! | BE27: =COUNTIFS('SPC-CPN_Q&A'!#REF!,AV$1,'SPC-CPN_Q&A'!#REF!,'Writing assignments'!$C27,'SPC-CPN_Q&A'!$O:$O,"Analysis") -> #REF! | BF27: X | BG27: 2 | BH27: 0 | BI27: 1 | BJ27: 1 | BL27: =SUM(BM27:BO27) -> #REF! | BM27: =COUNTIFS('SPC-CPN_Q&A'!#REF!,BF$1,'SPC-CPN_Q&A'!#REF!,'Writing assignments'!$C27,'SPC-CPN_Q&A'!$O:$O,"Recall") -> #REF! | BN27: =COUNTIFS('SPC-CPN_Q&A'!#REF!,BF$1,'SPC-CPN_Q&A'!#REF!,'Writing assignments'!$C27,'SPC-CPN_Q&A'!$O:$O,"Application") -> #REF! | BO27: =COUNTIFS('SPC-CPN_Q&A'!#REF!,BF$1,'SPC-CPN_Q&A'!#REF!,'Writing assignments'!$C27,'SPC-CPN_Q&A'!$O:$O,"Analysis") -> #REF! | BP27: X | BQ27: 2 | BR27: 1 | BS27: 1 | BT27: 0 | BV27: =SUM(BW27:BY27) -> #REF! | BW27: =COUNTIFS('SPC-CPN_Q&A'!#REF!,BP$1,'SPC-CPN_Q&A'!#REF!,'Writing assignments'!$C27,'SPC-CPN_Q&A'!$O:$O,"Recall") -> #REF! | BX27: =COUNTIFS('SPC-CPN_Q&A'!#REF!,BP$1,'SPC-CPN_Q&A'!#REF!,'Writing assignments'!$C27,'SPC-CPN_Q&A'!$O:$O,"Application") -> #REF! | BY27: =COUNTIFS('SPC-CPN_Q&A'!#REF!,BP$1,'SPC-CPN_Q&A'!#REF!,'Writing assignments'!$C27,'SPC-CPN_Q&A'!$O:$O,"Analysis") -> #REF! | CA27: 0
B28: Facilitate_Learner_Development_and_Socialization | C28: Facilitate learners’ self-reflection, goal setting, and socialization to the role of the nurse | E28: 2 | F28: 5 | G28: 2 | H28: =SUM(E28:G28) -> 9 | J28: =H28-SUM(N28,X28,AH28,AW28,BG28,BQ28,L28,CA28) -> 0 | L28: 0 | N28: =SUM(O28:Q28) -> 0 | S28: =SUM(T28:V28) -> #REF! | T28: =COUNTIFS('SPC-CPN_Q&A'!#REF!,M$1,'SPC-CPN_Q&A'!#REF!,'Writing assignments'!$C28,'SPC-CPN_Q&A'!$O:$O,"Recall") -> #REF! | U28: =COUNTIFS('SPC-CPN_Q&A'!#REF!,M$1,'SPC-CPN_Q&A'!#REF!,'Writing assignments'!$C28,'SPC-CPN_Q&A'!$O:$O,"Application") -> #REF! | V28: =COUNTIFS('SPC-CPN_Q&A'!#REF!,M$1,'SPC-CPN_Q&A'!#REF!,'Writing assignments'!$C28,'SPC-CPN_Q&A'!$O:$O,"Analysis") -> #REF! | W28: X | X28: 3 | Y28: 1 | Z28: 1 | AA28: 1 | AC28: =SUM(AD28:AF28) -> #REF! | AD28: =COUNTIFS('SPC-CPN_Q&A'!#REF!,W$1,'SPC-CPN_Q&A'!#REF!,'Writing assignments'!$C28,'SPC-CPN_Q&A'!$O:$O,"Recall") -> #REF! | AE28: =COUNTIFS('SPC-CPN_Q&A'!#REF!,W$1,'SPC-CPN_Q&A'!#REF!,'Writing assignments'!$C28,'SPC-CPN_Q&A'!$O:$O,"Application") -> #REF! | AF28: =COUNTIFS('SPC-CPN_Q&A'!#REF!,W$1,'SPC-CPN_Q&A'!#REF!,'Writing assignments'!$C28,'SPC-CPN_Q&A'!$O:$O,"Analysis") -> #REF! | AG28: X | AH28: 3 | AI28: 0 | AJ28: 2 | AK28: 1 | AM28: =SUM(AN28:AP28) -> #REF! | AN28: =COUNTIFS('SPC-CPN_Q&A'!#REF!,AG$1,'SPC-CPN_Q&A'!#REF!,'Writing assignments'!$C28,'SPC-CPN_Q&A'!$O:$O,"Recall") -> #REF! | AO28: =COUNTIFS('SPC-CPN_Q&A'!#REF!,AG$1,'SPC-CPN_Q&A'!#REF!,'Writing assignments'!$C28,'SPC-CPN_Q&A'!$O:$O,"Application") -> #REF! | AP28: =COUNTIFS('SPC-CPN_Q&A'!#REF!,AG$1,'SPC-CPN_Q&A'!#REF!,'Writing assignments'!$C28,'SPC-CPN_Q&A'!$O:$O,"Analysis") -> #REF! | BB28: =SUM(BC28:BE28) -> #REF! | BC28: =COUNTIFS('SPC-CPN_Q&A'!#REF!,AV$1,'SPC-CPN_Q&A'!#REF!,'Writing assignments'!$C28,'SPC-CPN_Q&A'!$O:$O,"Recall") -> #REF! | BD28: =COUNTIFS('SPC-CPN_Q&A'!#REF!,AV$1,'SPC-CPN_Q&A'!#REF!,'Writing assignments'!$C28,'SPC-CPN_Q&A'!$O:$O,"Application") -> #REF! | BE28: =COUNTIFS('SPC-CPN_Q&A'!#REF!,AV$1,'SPC-CPN_Q&A'!#REF!,'Writing assignments'!$C28,'SPC-CPN_Q&A'!$O:$O,"Analysis") -> #REF! | BL28: =SUM(BM28:BO28) -> #REF! | BM28: =COUNTIFS('SPC-CPN_Q&A'!#REF!,BF$1,'SPC-CPN_Q&A'!#REF!,'Writing assignments'!$C28,'SPC-CPN_Q&A'!$O:$O,"Recall") -> #REF! | BN28: =COUNTIFS('SPC-CPN_Q&A'!#REF!,BF$1,'SPC-CPN_Q&A'!#REF!,'Writing assignments'!$C28,'SPC-CPN_Q&A'!$O:$O,"Application") -> #REF! | BO28: =COUNTIFS('SPC-CPN_Q&A'!#REF!,BF$1,'SPC-CPN_Q&A'!#REF!,'Writing assignments'!$C28,'SPC-CPN_Q&A'!$O:$O,"Analysis") -> #REF! | BP28: X | BQ28: 3 | BR28: 1 | BS28: 2 | BT28: 0 | BV28: =SUM(BW28:BY28) -> #REF! | BW28: =COUNTIFS('SPC-CPN_Q&A'!#REF!,BP$1,'SPC-CPN_Q&A'!#REF!,'Writing assignments'!$C28,'SPC-CPN_Q&A'!$O:$O,"Recall") -> #REF! | BX28: =COUNTIFS('SPC-CPN_Q&A'!#REF!,BP$1,'SPC-CPN_Q&A'!#REF!,'Writing assignments'!$C28,'SPC-CPN_Q&A'!$O:$O,"Application") -> #REF! | BY28: =COUNTIFS('SPC-CPN_Q&A'!#REF!,BP$1,'SPC-CPN_Q&A'!#REF!,'Writing assignments'!$C28,'SPC-CPN_Q&A'!$O:$O,"Analysis") -> #REF! | CA28: 0
B29: Facilitate_Learner_Development_and_Socialization | C29: Engage learners in thoughtful and constructive self and peer evaluation | E29: 1 | F29: 5 | G29: 3 | H29: =SUM(E29:G29) -> 9 | J29: =H29-SUM(N29,X29,AH29,AW29,BG29,BQ29,L29,CA29) -> 0 | L29: 0 | M29: X | N29: =SUM(O29:Q29) -> 3 | P29: 2 | Q29: 1 | S29: =SUM(T29:V29) -> #REF! | T29: =COUNTIFS('SPC-CPN_Q&A'!#REF!,M$1,'SPC-CPN_Q&A'!#REF!,'Writing assignments'!$C29,'SPC-CPN_Q&A'!$O:$O,"Recall") -> #REF! | U29: =COUNTIFS('SPC-CPN_Q&A'!#REF!,M$1,'SPC-CPN_Q&A'!#REF!,'Writing assignments'!$C29,'SPC-CPN_Q&A'!$O:$O,"Application") -> #REF! | V29: =COUNTIFS('SPC-CPN_Q&A'!#REF!,M$1,'SPC-CPN_Q&A'!#REF!,'Writing assignments'!$C29,'SPC-CPN_Q&A'!$O:$O,"Analysis") -> #REF! | AC29: =SUM(AD29:AF29) -> #REF! | AD29: =COUNTIFS('SPC-CPN_Q&A'!#REF!,W$1,'SPC-CPN_Q&A'!#REF!,'Writing assignments'!$C29,'SPC-CPN_Q&A'!$O:$O,"Recall") -> #REF! | AE29: =COUNTIFS('SPC-CPN_Q&A'!#REF!,W$1,'SPC-CPN_Q&A'!#REF!,'Writing assignments'!$C29,'SPC-CPN_Q&A'!$O:$O,"Application") -> #REF! | AF29: =COUNTIFS('SPC-CPN_Q&A'!#REF!,W$1,'SPC-CPN_Q&A'!#REF!,'Writing assignments'!$C29,'SPC-CPN_Q&A'!$O:$O,"Analysis") -> #REF! | AG29: X | AH29: 2 | AI29: 1 | AJ29: 0 | AK29: 1 | AM29: =SUM(AN29:AP29) -> #REF! | AN29: =COUNTIFS('SPC-CPN_Q&A'!#REF!,AG$1,'SPC-CPN_Q&A'!#REF!,'Writing assignments'!$C29,'SPC-CPN_Q&A'!$O:$O,"Recall") -> #REF! | AO29: =COUNTIFS('SPC-CPN_Q&A'!#REF!,AG$1,'SPC-CPN_Q&A'!#REF!,'Writing assignments'!$C29,'SPC-CPN_Q&A'!$O:$O,"Application") -> #REF! | AP29: =COUNTIFS('SPC-CPN_Q&A'!#REF!,AG$1,'SPC-CPN_Q&A'!#REF!,'Writing assignments'!$C29,'SPC-CPN_Q&A'!$O:$O,"Analysis") -> #REF! | BB29: =SUM(BC29:BE29) -> #REF! | BC29: =COUNTIFS('SPC-CPN_Q&A'!#REF!,AV$1,'SPC-CPN_Q&A'!#REF!,'Writing assignments'!$C29,'SPC-CPN_Q&A'!$O:$O,"Recall") -> #REF! | BD29: =COUNTIFS('SPC-CPN_Q&A'!#REF!,AV$1,'SPC-CPN_Q&A'!#REF!,'Writing assignments'!$C29,'SPC-CPN_Q&A'!$O:$O,"Application") -> #REF! | BE29: =COUNTIFS('SPC-CPN_Q&A'!#REF!,AV$1,'SPC-CPN_Q&A'!#REF!,'Writing assignments'!$C29,'SPC-CPN_Q&A'!$O:$O,"Analysis") -> #REF! | BF29: X | BG29: 2 | BH29: 0 | BI29: 1 | BJ29: 1 | BL29: =SUM(BM29:BO29) -> #REF! | BM29: =COUNTIFS('SPC-CPN_Q&A'!#REF!,BF$1,'SPC-CPN_Q&A'!#REF!,'Writing assignments'!$C29,'SPC-CPN_Q&A'!$O:$O,"Recall") -> #REF! | BN29: =COUNTIFS('SPC-CPN_Q&A'!#REF!,BF$1,'SPC-CPN_Q&A'!#REF!,'Writing assignments'!$C29,'SPC-CPN_Q&A'!$O:$O,"Application") -> #REF! | BO29: =COUNTIFS('SPC-CPN_Q&A'!#REF!,BF$1,'SPC-CPN_Q&A'!#REF!,'Writing assignments'!$C29,'SPC-CPN_Q&A'!$O:$O,"Analysis") -> #REF! | BP29: X | BQ29: 2 | BR29: 0 | BS29: 2 | BT29: 0 | BV29: =SUM(BW29:BY29) -> #REF! | BW29: =COUNTIFS('SPC-CPN_Q&A'!#REF!,BP$1,'SPC-CPN_Q&A'!#REF!,'Writing assignments'!$C29,'SPC-CPN_Q&A'!$O:$O,"Recall") -> #REF! | BX29: =COUNTIFS('SPC-CPN_Q&A'!#REF!,BP$1,'SPC-CPN_Q&A'!#REF!,'Writing assignments'!$C29,'SPC-CPN_Q&A'!$O:$O,"Application") -> #REF! | BY29: =COUNTIFS('SPC-CPN_Q&A'!#REF!,BP$1,'SPC-CPN_Q&A'!#REF!,'Writing assignments'!$C29,'SPC-CPN_Q&A'!$O:$O,"Analysis") -> #REF! | CA29: 0
B30: Facilitate_Learner_Development_and_Socialization | C30: Promote professional development of learners | E30: 2 | F30: 5 | G30: 2 | H30: =SUM(E30:G30) -> 9 | J30: =H30-SUM(N30,X30,AH30,AW30,BG30,BQ30,L30,CA30) -> 0 | K30: X | L30: 1 | N30: =SUM(O30:Q30) -> 0 | S30: =SUM(T30:V30) -> #REF! | T30: =COUNTIFS('SPC-CPN_Q&A'!#REF!,M$1,'SPC-CPN_Q&A'!#REF!,'Writing assignments'!$C30,'SPC-CPN_Q&A'!$O:$O,"Recall") -> #REF! | U30: =COUNTIFS('SPC-CPN_Q&A'!#REF!,M$1,'SPC-CPN_Q&A'!#REF!,'Writing assignments'!$C30,'SPC-CPN_Q&A'!$O:$O,"Application") -> #REF! | V30: =COUNTIFS('SPC-CPN_Q&A'!#REF!,M$1,'SPC-CPN_Q&A'!#REF!,'Writing assignments'!$C30,'SPC-CPN_Q&A'!$O:$O,"Analysis") -> #REF! | W30: X | X30: 2 | Y30: ` | Z30: 1 | AA30: 1 | AC30: =SUM(AD30:AF30) -> #REF! | AD30: =COUNTIFS('SPC-CPN_Q&A'!#REF!,W$1,'SPC-CPN_Q&A'!#REF!,'Writing assignments'!$C30,'SPC-CPN_Q&A'!$O:$O,"Recall") -> #REF! | AE30: =COUNTIFS('SPC-CPN_Q&A'!#REF!,W$1,'SPC-CPN_Q&A'!#REF!,'Writing assignments'!$C30,'SPC-CPN_Q&A'!$O:$O,"Application") -> #REF! | AF30: =COUNTIFS('SPC-CPN_Q&A'!#REF!,W$1,'SPC-CPN_Q&A'!#REF!,'Writing assignments'!$C30,'SPC-CPN_Q&A'!$O:$O,"Analysis") -> #REF! | AM30: =SUM(AN30:AP30) -> #REF! | AN30: =COUNTIFS('SPC-CPN_Q&A'!#REF!,AG$1,'SPC-CPN_Q&A'!#REF!,'Writing assignments'!$C30,'SPC-CPN_Q&A'!$O:$O,"Recall") -> #REF! | AO30: =COUNTIFS('SPC-CPN_Q&A'!#REF!,AG$1,'SPC-CPN_Q&A'!#REF!,'Writing assignments'!$C30,'SPC-CPN_Q&A'!$O:$O,"Application") -> #REF! | AP30: =COUNTIFS('SPC-CPN_Q&A'!#REF!,AG$1,'SPC-CPN_Q&A'!#REF!,'Writing assignments'!$C30,'SPC-CPN_Q&A'!$O:$O,"Analysis") -> #REF! | AV30: X | AW30: 2 | AX30: 1 | AY30: 1 | AZ30: 0 | BB30: =SUM(BC30:BE30) -> #REF! | BC30: =COUNTIFS('SPC-CPN_Q&A'!#REF!,AV$1,'SPC-CPN_Q&A'!#REF!,'Writing assignments'!$C30,'SPC-CPN_Q&A'!$O:$O,"Recall") -> #REF! | BD30: =COUNTIFS('SPC-CPN_Q&A'!#REF!,AV$1,'SPC-CPN_Q&A'!#REF!,'Writing assignments'!$C30,'SPC-CPN_Q&A'!$O:$O,"Application") -> #REF! | BE30: =COUNTIFS('SPC-CPN_Q&A'!#REF!,AV$1,'SPC-CPN_Q&A'!#REF!,'Writing assignments'!$C30,'SPC-CPN_Q&A'!$O:$O,"Analysis") -> #REF! | BF30: X | BG30: 2 | BH30: 1 | BI30: 1 | BJ30: 0 | BL30: =SUM(BM30:BO30) -> #REF! | BM30: =COUNTIFS('SPC-CPN_Q&A'!#REF!,BF$1,'SPC-CPN_Q&A'!#REF!,'Writing assignments'!$C30,'SPC-CPN_Q&A'!$O:$O,"Recall") -> #REF! | BN30: =COUNTIFS('SPC-CPN_Q&A'!#REF!,BF$1,'SPC-CPN_Q&A'!#REF!,'Writing assignments'!$C30,'SPC-CPN_Q&A'!$O:$O,"Application") -> #REF! | BO30: =COUNTIFS('SPC-CPN_Q&A'!#REF!,BF$1,'SPC-CPN_Q&A'!#REF!,'Writing assignments'!$C30,'SPC-CPN_Q&A'!$O:$O,"Analysis") -> #REF! | BP30: X | BQ30: 2 | BR30: 0 | BS30: 1 | BT30: 1 | BV30: =SUM(BW30:BY30) -> #REF! | BW30: =COUNTIFS('SPC-CPN_Q&A'!#REF!,BP$1,'SPC-CPN_Q&A'!#REF!,'Writing assignments'!$C30,'SPC-CPN_Q&A'!$O:$O,"Recall") -> #REF! | BX30: =COUNTIFS('SPC-CPN_Q&A'!#REF!,BP$1,'SPC-CPN_Q&A'!#REF!,'Writing assignments'!$C30,'SPC-CPN_Q&A'!$O:$O,"Application") -> #REF! | BY30: =COUNTIFS('SPC-CPN_Q&A'!#REF!,BP$1,'SPC-CPN_Q&A'!#REF!,'Writing assignments'!$C30,'SPC-CPN_Q&A'!$O:$O,"Analysis") -> #REF! | CA30: 0
B31: Use_Assessment_and_Evaluation_Strategies | C31: Design and apply formative and summative evaluation strategies | E31: 1 | F31: 4 | G31: 2 | H31: =SUM(E31:G31) -> 7 | J31: =H31-SUM(N31,X31,AH31,AW31,BG31,BQ31,L31,CA31) -> 0 | K31: X | L31: 1 | N31: =SUM(O31:Q31) -> 0 | S31: =SUM(T31:V31) -> #REF! | T31: =COUNTIFS('SPC-CPN_Q&A'!#REF!,M$1,'SPC-CPN_Q&A'!#REF!,'Writing assignments'!$C31,'SPC-CPN_Q&A'!$O:$O,"Recall") -> #REF! | U31: =COUNTIFS('SPC-CPN_Q&A'!#REF!,M$1,'SPC-CPN_Q&A'!#REF!,'Writing assignments'!$C31,'SPC-CPN_Q&A'!$O:$O,"Application") -> #REF! | V31: =COUNTIFS('SPC-CPN_Q&A'!#REF!,M$1,'SPC-CPN_Q&A'!#REF!,'Writing assignments'!$C31,'SPC-CPN_Q&A'!$O:$O,"Analysis") -> #REF! | AC31: =SUM(AD31:AF31) -> #REF! | AD31: =COUNTIFS('SPC-CPN_Q&A'!#REF!,W$1,'SPC-CPN_Q&A'!#REF!,'Writing assignments'!$C31,'SPC-CPN_Q&A'!$O:$O,"Recall") -> #REF! | AE31: =COUNTIFS('SPC-CPN_Q&A'!#REF!,W$1,'SPC-CPN_Q&A'!#REF!,'Writing assignments'!$C31,'SPC-CPN_Q&A'!$O:$O,"Application") -> #REF! | AF31: =COUNTIFS('SPC-CPN_Q&A'!#REF!,W$1,'SPC-CPN_Q&A'!#REF!,'Writing assignments'!$C31,'SPC-CPN_Q&A'!$O:$O,"Analysis") -> #REF! | AM31: =SUM(AN31:AP31) -> #REF! | AN31: =COUNTIFS('SPC-CPN_Q&A'!#REF!,AG$1,'SPC-CPN_Q&A'!#REF!,'Writing assignments'!$C31,'SPC-CPN_Q&A'!$O:$O,"Recall") -> #REF! | AO31: =COUNTIFS('SPC-CPN_Q&A'!#REF!,AG$1,'SPC-CPN_Q&A'!#REF!,'Writing assignments'!$C31,'SPC-CPN_Q&A'!$O:$O,"Application") -> #REF! | AP31: =COUNTIFS('SPC-CPN_Q&A'!#REF!,AG$1,'SPC-CPN_Q&A'!#REF!,'Writing assignments'!$C31,'SPC-CPN_Q&A'!$O:$O,"Analysis") -> #REF! | BB31: =SUM(BC31:BE31) -> #REF! | BC31: =COUNTIFS('SPC-CPN_Q&A'!#REF!,AV$1,'SPC-CPN_Q&A'!#REF!,'Writing assignments'!$C31,'SPC-CPN_Q&A'!$O:$O,"Recall") -> #REF! | BD31: =COUNTIFS('SPC-CPN_Q&A'!#REF!,AV$1,'SPC-CPN_Q&A'!#REF!,'Writing assignments'!$C31,'SPC-CPN_Q&A'!$O:$O,"Application") -> #REF! | BE31: =COUNTIFS('SPC-CPN_Q&A'!#REF!,AV$1,'SPC-CPN_Q&A'!#REF!,'Writing assignments'!$C31,'SPC-CPN_Q&A'!$O:$O,"Analysis") -> #REF! | BF31: X | BG31: 3 | BH31: 0 | BI31: 2 | BJ31: 1 | BL31: =SUM(BM31:BO31) -> #REF! | BM31: =COUNTIFS('SPC-CPN_Q&A'!#REF!,BF$1,'SPC-CPN_Q&A'!#REF!,'Writing assignments'!$C31,'SPC-CPN_Q&A'!$O:$O,"Recall") -> #REF! | BN31: =COUNTIFS('SPC-CPN_Q&A'!#REF!,BF$1,'SPC-CPN_Q&A'!#REF!,'Writing assignments'!$C31,'SPC-CPN_Q&A'!$O:$O,"Application") -> #REF! | BO31: =COUNTIFS('SPC-CPN_Q&A'!#REF!,BF$1,'SPC-CPN_Q&A'!#REF!,'Writing assignments'!$C31,'SPC-CPN_Q&A'!$O:$O,"Analysis") -> #REF! | BP31: X | BQ31: 3 | BR31: 1 | BS31: 1 | BT31: 1 | BV31: =SUM(BW31:BY31) -> #REF! | BW31: =COUNTIFS('SPC-CPN_Q&A'!#REF!,BP$1,'SPC-CPN_Q&A'!#REF!,'Writing assignments'!$C31,'SPC-CPN_Q&A'!$O:$O,"Recall") -> #REF! | BX31: =COUNTIFS('SPC-CPN_Q&A'!#REF!,BP$1,'SPC-CPN_Q&A'!#REF!,'Writing assignments'!$C31,'SPC-CPN_Q&A'!$O:$O,"Application") -> #REF! | BY31: =COUNTIFS('SPC-CPN_Q&A'!#REF!,BP$1,'SPC-CPN_Q&A'!#REF!,'Writing assignments'!$C31,'SPC-CPN_Q&A'!$O:$O,"Analysis") -> #REF! | CA31: 0
B32: Use_Assessment_and_Evaluation_Strategies | C32: Implement evidence-based assessment and evaluation strategies in these learning domains: cognitive | E32: 0 | F32: 2 | G32: 3 | H32: =SUM(E32:G32) -> 5 | J32: =H32-SUM(N32,X32,AH32,AW32,BG32,BQ32,L32,CA32) -> 0 | K32: X | L32: 1 | N32: =SUM(O32:Q32) -> 0 | S32: =SUM(T32:V32) -> #REF! | T32: =COUNTIFS('SPC-CPN_Q&A'!#REF!,M$1,'SPC-CPN_Q&A'!#REF!,'Writing assignments'!$C32,'SPC-CPN_Q&A'!$O:$O,"Recall") -> #REF! | U32: =COUNTIFS('SPC-CPN_Q&A'!#REF!,M$1,'SPC-CPN_Q&A'!#REF!,'Writing assignments'!$C32,'SPC-CPN_Q&A'!$O:$O,"Application") -> #REF! | V32: =COUNTIFS('SPC-CPN_Q&A'!#REF!,M$1,'SPC-CPN_Q&A'!#REF!,'Writing assignments'!$C32,'SPC-CPN_Q&A'!$O:$O,"Analysis") -> #REF! | AC32: =SUM(AD32:AF32) -> #REF! | AD32: =COUNTIFS('SPC-CPN_Q&A'!#REF!,W$1,'SPC-CPN_Q&A'!#REF!,'Writing assignments'!$C32,'SPC-CPN_Q&A'!$O:$O,"Recall") -> #REF! | AE32: =COUNTIFS('SPC-CPN_Q&A'!#REF!,W$1,'SPC-CPN_Q&A'!#REF!,'Writing assignments'!$C32,'SPC-CPN_Q&A'!$O:$O,"Application") -> #REF! | AF32: =COUNTIFS('SPC-CPN_Q&A'!#REF!,W$1,'SPC-CPN_Q&A'!#REF!,'Writing assignments'!$C32,'SPC-CPN_Q&A'!$O:$O,"Analysis") -> #REF! | AG32: X | AH32: 2 | AI32: 0 | AJ32: 1 | AK32: 1 | AM32: =SUM(AN32:AP32) -> #REF! | AN32: =COUNTIFS('SPC-CPN_Q&A'!#REF!,AG$1,'SPC-CPN_Q&A'!#REF!,'Writing assignments'!$C32,'SPC-CPN_Q&A'!$O:$O,"Recall") -> #REF! | AO32: =COUNTIFS('SPC-CPN_Q&A'!#REF!,AG$1,'SPC-CPN_Q&A'!#REF!,'Writing assignments'!$C32,'SPC-CPN_Q&A'!$O:$O,"Application") -> #REF! | AP32: =COUNTIFS('SPC-CPN_Q&A'!#REF!,AG$1,'SPC-CPN_Q&A'!#REF!,'Writing assignments'!$C32,'SPC-CPN_Q&A'!$O:$O,"Analysis") -> #REF! | AV32: X | AW32: 2 | AX32: 0 | AY32: 1 | AZ32: 1 | BB32: =SUM(BC32:BE32) -> #REF! | BC32: =COUNTIFS('SPC-CPN_Q&A'!#REF!,AV$1,'SPC-CPN_Q&A'!#REF!,'Writing assignments'!$C32,'SPC-CPN_Q&A'!$O:$O,"Recall") -> #REF! | BD32: =COUNTIFS('SPC-CPN_Q&A'!#REF!,AV$1,'SPC-CPN_Q&A'!#REF!,'Writing assignments'!$C32,'SPC-CPN_Q&A'!$O:$O,"Application") -> #REF! | BE32: =COUNTIFS('SPC-CPN_Q&A'!#REF!,AV$1,'SPC-CPN_Q&A'!#REF!,'Writing assignments'!$C32,'SPC-CPN_Q&A'!$O:$O,"Analysis") -> #REF! | BL32: =SUM(BM32:BO32) -> #REF! | BM32: =COUNTIFS('SPC-CPN_Q&A'!#REF!,BF$1,'SPC-CPN_Q&A'!#REF!,'Writing assignments'!$C32,'SPC-CPN_Q&A'!$O:$O,"Recall") -> #REF! | BN32: =COUNTIFS('SPC-CPN_Q&A'!#REF!,BF$1,'SPC-CPN_Q&A'!#REF!,'Writing assignments'!$C32,'SPC-CPN_Q&A'!$O:$O,"Application") -> #REF! | BO32: =COUNTIFS('SPC-CPN_Q&A'!#REF!,BF$1,'SPC-CPN_Q&A'!#REF!,'Writing assignments'!$C32,'SPC-CPN_Q&A'!$O:$O,"Analysis") -> #REF! | BV32: =SUM(BW32:BY32) -> #REF! | BW32: =COUNTIFS('SPC-CPN_Q&A'!#REF!,BP$1,'SPC-CPN_Q&A'!#REF!,'Writing assignments'!$C32,'SPC-CPN_Q&A'!$O:$O,"Recall") -> #REF! | BX32: =COUNTIFS('SPC-CPN_Q&A'!#REF!,BP$1,'SPC-CPN_Q&A'!#REF!,'Writing assignments'!$C32,'SPC-CPN_Q&A'!$O:$O,"Application") -> #REF! | BY32: =COUNTIFS('SPC-CPN_Q&A'!#REF!,BP$1,'SPC-CPN_Q&A'!#REF!,'Writing assignments'!$C32,'SPC-CPN_Q&A'!$O:$O,"Analysis") -> #REF! | CA32: 0
B33: Use_Assessment_and_Evaluation_Strategies | C33: Implement evidence-based assessment and evaluation strategies in these learning domains: psychomotor | E33: 0 | F33: 3 | G33: 2 | H33: =SUM(E33:G33) -> 5 | J33: =H33-SUM(N33,X33,AH33,AW33,BG33,BQ33,L33,CA33) -> 0 | K33: X | L33: 1 | N33: =SUM(O33:Q33) -> 0 | S33: =SUM(T33:V33) -> #REF! | T33: =COUNTIFS('SPC-CPN_Q&A'!#REF!,M$1,'SPC-CPN_Q&A'!#REF!,'Writing assignments'!$C33,'SPC-CPN_Q&A'!$O:$O,"Recall") -> #REF! | U33: =COUNTIFS('SPC-CPN_Q&A'!#REF!,M$1,'SPC-CPN_Q&A'!#REF!,'Writing assignments'!$C33,'SPC-CPN_Q&A'!$O:$O,"Application") -> #REF! | V33: =COUNTIFS('SPC-CPN_Q&A'!#REF!,M$1,'SPC-CPN_Q&A'!#REF!,'Writing assignments'!$C33,'SPC-CPN_Q&A'!$O:$O,"Analysis") -> #REF! | AC33: =SUM(AD33:AF33) -> #REF! | AD33: =COUNTIFS('SPC-CPN_Q&A'!#REF!,W$1,'SPC-CPN_Q&A'!#REF!,'Writing assignments'!$C33,'SPC-CPN_Q&A'!$O:$O,"Recall") -> #REF! | AE33: =COUNTIFS('SPC-CPN_Q&A'!#REF!,W$1,'SPC-CPN_Q&A'!#REF!,'Writing assignments'!$C33,'SPC-CPN_Q&A'!$O:$O,"Application") -> #REF! | AF33: =COUNTIFS('SPC-CPN_Q&A'!#REF!,W$1,'SPC-CPN_Q&A'!#REF!,'Writing assignments'!$C33,'SPC-CPN_Q&A'!$O:$O,"Analysis") -> #REF! | AG33: X | AH33: 2 | AI33: 0 | AJ33: 1 | AK33: 1 | AM33: =SUM(AN33:AP33) -> #REF! | AN33: =COUNTIFS('SPC-CPN_Q&A'!#REF!,AG$1,'SPC-CPN_Q&A'!#REF!,'Writing assignments'!$C33,'SPC-CPN_Q&A'!$O:$O,"Recall") -> #REF! | AO33: =COUNTIFS('SPC-CPN_Q&A'!#REF!,AG$1,'SPC-CPN_Q&A'!#REF!,'Writing assignments'!$C33,'SPC-CPN_Q&A'!$O:$O,"Application") -> #REF! | AP33: =COUNTIFS('SPC-CPN_Q&A'!#REF!,AG$1,'SPC-CPN_Q&A'!#REF!,'Writing assignments'!$C33,'SPC-CPN_Q&A'!$O:$O,"Analysis") -> #REF! | AV33: X | AW33: 2 | AX33: 0 | AY33: 1 | AZ33: 1 | BB33: =SUM(BC33:BE33) -> #REF! | BC33: =COUNTIFS('SPC-CPN_Q&A'!#REF!,AV$1,'SPC-CPN_Q&A'!#REF!,'Writing assignments'!$C33,'SPC-CPN_Q&A'!$O:$O,"Recall") -> #REF! | BD33: =COUNTIFS('SPC-CPN_Q&A'!#REF!,AV$1,'SPC-CPN_Q&A'!#REF!,'Writing assignments'!$C33,'SPC-CPN_Q&A'!$O:$O,"Application") -> #REF! | BE33: =COUNTIFS('SPC-CPN_Q&A'!#REF!,AV$1,'SPC-CPN_Q&A'!#REF!,'Writing assignments'!$C33,'SPC-CPN_Q&A'!$O:$O,"Analysis") -> #REF! | BL33: =SUM(BM33:BO33) -> #REF! | BM33: =COUNTIFS('SPC-CPN_Q&A'!#REF!,BF$1,'SPC-CPN_Q&A'!#REF!,'Writing assignments'!$C33,'SPC-CPN_Q&A'!$O:$O,"Recall") -> #REF! | BN33: =COUNTIFS('SPC-CPN_Q&A'!#REF!,BF$1,'SPC-CPN_Q&A'!#REF!,'Writing assignments'!$C33,'SPC-CPN_Q&A'!$O:$O,"Application") -> #REF! | BO33: =COUNTIFS('SPC-CPN_Q&A'!#REF!,BF$1,'SPC-CPN_Q&A'!#REF!,'Writing assignments'!$C33,'SPC-CPN_Q&A'!$O:$O,"Analysis") -> #REF! | BV33: =SUM(BW33:BY33) -> #REF! | BW33: =COUNTIFS('SPC-CPN_Q&A'!#REF!,BP$1,'SPC-CPN_Q&A'!#REF!,'Writing assignments'!$C33,'SPC-CPN_Q&A'!$O:$O,"Recall") -> #REF! | BX33: =COUNTIFS('SPC-CPN_Q&A'!#REF!,BP$1,'SPC-CPN_Q&A'!#REF!,'Writing assignments'!$C33,'SPC-CPN_Q&A'!$O:$O,"Application") -> #REF! | BY33: =COUNTIFS('SPC-CPN_Q&A'!#REF!,BP$1,'SPC-CPN_Q&A'!#REF!,'Writing assignments'!$C33,'SPC-CPN_Q&A'!$O:$O,"Analysis") -> #REF! | CA33: 0
